Workbook
Name Scenario: Drivers!$C$4

Sheet Summary
A1: FTAI Aviation (NASDAQ: FTAI): valuation summary
A2: [TEAM NAME] | Point72 Academy pitch | market data as of 10/6/26 | USD m except per-share | Scenario selected on Drivers tab
A4: RECOMMENDATION (formula-driven) | B4: =IF(Valuation!B100>Drivers!$D$228,"LONG",IF(Valuation!B100<-Drivers!$D$228,"SHORT","NEUTRAL / marginal"))&": probability-weighted value $"&TEXT(Valuation!B98,"0")&" vs price $"&TEXT(Drivers!$D$180,"0.00")&" ("&TEXT(Valuation!B100,"0%")&")"&IF(ABS(ABS(Valuation!B100)-Drivers!$D$228)<Drivers!$D$229," - MARGINAL call","")
A5: Current price ($) | B5: =Drivers!$D$180
A6: Probability-weighted blended price target ($) | B6: =Valuation!B98
A7: Upside / (downside) vs current price | B7: =Valuation!B100
A8: Base-case blended price target ($) and upside | B8: =Valuation!C93 | C8: =B8/Drivers!$D$180-1
A9: Street mean PT ($, methodology not public) | B9: =Drivers!$D$215
A11: Price target by method: selected scenario (live)
A12: Scenario currently selected | B12: =Drivers!$C$4
A13: Method | B13: Value / share | C13: Weight | D13: vs price
A14: SOTP (2027E, Leasing at book) | B14: =Valuation!B68 | C14: =Valuation!C68 | D14: =B14/Drivers!$D$180-1
A15: Forward P/E x FY27E EPS | B15: =Valuation!B69 | C15: =Valuation!C69 | D15: =B15/Drivers!$D$180-1
A16: DCF (clean FCF) | B16: =Valuation!B70 | C16: =Valuation!C70 | D16: =B16/Drivers!$D$180-1
A17: Blended (weights are inputs on Drivers) | B17: =Valuation!D71 | C17: =Valuation!C71 | D17: =B17/Drivers!$D$180-1
A18: Model FY27E EPS ($) vs consensus-implied ($8.87) | B18: =Valuation!B39 | C18: =Valuation!B43 | D18: =Valuation!B46
A20: Scenario table (SOTP is live; EPS, P/E, DCF, blended come from the snapshot of four full recalculations)
A21: Metric | B21: Bear | C21: Base | D21: Bull | E21: Mgmt Guide | F21: Prob-weighted
A22: Probability weight | B22: =Valuation!B97 | C22: =Valuation!C97 | D22: =Valuation!D97 | E22: =Valuation!E97 | F22: =SUM(B22:E22)
A23: FY26E segment EBITDA ($M) | B23: =Valuation!B85 | C23: =Valuation!C85 | D23: =Valuation!D85 | E23: =Valuation!E85 | F23: =SUMPRODUCT(B23:E23,$B$22:$E$22)/SUM($B$22:$E$22)
A24: FY27E segment EBITDA ($M) | B24: =Valuation!B86 | C24: =Valuation!C86 | D24: =Valuation!D86 | E24: =Valuation!E86 | F24: =SUMPRODUCT(B24:E24,$B$22:$E$22)/SUM($B$22:$E$22)
A25: FY27E diluted EPS ($) | B25: =Valuation!B89 | C25: =Valuation!C89 | D25: =Valuation!D89 | E25: =Valuation!E89 | F25: =SUMPRODUCT(B25:E25,$B$22:$E$22)/SUM($B$22:$E$22)
A26: SOTP value / share ($) | B26: =Valuation!B31 | C26: =Valuation!C31 | D26: =Valuation!D31 | E26: =Valuation!E31 | F26: =SUMPRODUCT(B26:E26,$B$22:$E$22)/SUM($B$22:$E$22)
A27: P/E value / share ($) | B27: =Valuation!B91 | C27: =Valuation!C91 | D27: =Valuation!D91 | E27: =Valuation!E91 | F27: =SUMPRODUCT(B27:E27,$B$22:$E$22)/SUM($B$22:$E$22)
A28: DCF value / share ($) | B28: =Valuation!B92 | C28: =Valuation!C92 | D28: =Valuation!D92 | E28: =Valuation!E92 | F28: =SUMPRODUCT(B28:E28,$B$22:$E$22)/SUM($B$22:$E$22)
A29: Blended value / share ($) | B29: =Valuation!B93 | C29: =Valuation!C93 | D29: =Valuation!D93 | E29: =Valuation!E93 | F29: =SUMPRODUCT(B29:E29,$B$22:$E$22)/SUM($B$22:$E$22)
A30: Upside / (downside) vs price (blended) | B30: =B29/Drivers!$D$180-1 | C30: =C29/Drivers!$D$180-1 | D30: =D29/Drivers!$D$180-1 | E30: =E29/Drivers!$D$180-1 | F30: =F29/Drivers!$D$180-1
A32: The 3 KEY ASSUMPTIONS (flagged; values by scenario)
A33: Key assumption | B33: Bear | C33: Base | D33: Bull | E33: Mgmt Guide | F33: Selected
A34: KEY #1: 2027E Aerospace EBITDA ($M) = modules x EBITDA/module (guide is a volume call) | B34: =Drivers!D9 | C34: =Drivers!E9 | D34: =Drivers!F9 | E34: =Drivers!G9 | F34: =Drivers!H9
A35: KEY #2: inventory conversion % (2H26 FCF ramp; Mgmt value back-solved to the $878M guide) | B35: =Drivers!D10 | C35: =Drivers!E10 | D35: =Drivers!F10 | E35: =Drivers!G10 | F35: =Drivers!H10
A36: KEY #3: 2027E Power EBITDA ($M) = units x $7.5M/unit (unverified) | B36: =Drivers!D11 | C36: =Drivers!E11 | D36: =Drivers!F11 | E36: =Drivers!G11 | F36: =Drivers!H11
A38: Thesis in three bullets
A39: 1. Cash quality: FY25 Adjusted FCF of $724M vs CFO+CFI of $412.6M; 1H26 clean cash was about $26M after $176M of non-recurring seed sales and $48M of insurance, and the $878M FY26 guide needs ~$623M in 2H26 (about 3x the Q2 run-rate).
A40: 2. Growth runs through affiliates: 25% of 1H26 Aerospace revenue was sold to the 19%-owned SCI vehicle, Power sits in a JV that Jereh consolidates, and pro-rata SCI/JV EBITDA is counted in Adj. EBITDA but arrives as cash only via distributions.
A41: 3. Valuation: the 2027 guide is roughly our Bull case. On Base (1,920 EBITDA) SOTP and P/E sit near the current price, far below the Street's ~$330; the call depends on the 2027 EBITDA delivery and the Q3 (10/28) FCF test.

Sheet Drivers
A1: Drivers: every projection traces to this tab
A2: Blue = typed input; black = formula; green = link. Yellow fill + red bold label = KEY ASSUMPTION. Scenario selector below drives all 'Selected' rows. USD m unless stated.
A4: SCENARIO SELECTOR (dropdown) | C4: Base | E4: =MATCH(C4,G4:J4,0) | F4: list: | G4: Bear | H4: Base | I4: Bull | J4: Mgmt Guide
A5: Scenario index (formula)
A7: KEY ASSUMPTIONS (3): values by scenario
A8: Key assumption | B8: Unit | D8: Bear | E8: Base | F8: Bull | G8: Mgmt Guide | H8: Selected
A9: KEY #1: 2027 Aerospace EBITDA (modules x EBITDA per module) | B9: $M | D9: =Drivers!$D$263 | E9: =Drivers!$E$263 | F9: =Drivers!$F$263 | G9: =Drivers!$G$263 | H9: =INDEX(D9:G9,$E$4)
A10: KEY #2: Inventory conversion % (drives the 2H26 FCF ramp) | B10: % | D10: =$D$162 | E10: =$D$163 | F10: =$D$164 | G10: =$D$165 | H10: =INDEX(D10:G10,$E$4)
A11: KEY #3: 2027 Power EBITDA (units x EBITDA per unit) | B11: $M | D11: =Drivers!$D$264 | E11: =Drivers!$E$264 | F11: =Drivers!$F$264 | G11: =Drivers!$G$264 | H11: =INDEX(D11:G11,$E$4)
A12: Memo: 2027 segment EBITDA total | D12: =Drivers!$D$266 | E12: =Drivers!$E$266 | F12: =Drivers!$F$266 | G12: =Drivers!$G$266 | H12: =INDEX(D12:G12,$E$4)
A16: 0. General constants
A17: Driver | B17: Unit | C17: Q2'26A | D17: Q3'26E | E17: Q4'26E | F17: Q1'27E | G17: Q2'27E | H17: Q3'27E | I17: Q4'27E | J17: FY2028E | K17: FY2029E | L17: FY2030E | M17: Source / rationale
A18: Quarters per year | B18: # | D18: 4 | M18: Calendar constant
A19: Days per quarter | B19: days | D19: 91.25 | M19: 365/4
A20: Days per year | B20: days | D20: 365 | M20: Calendar constant
A21: Months per year | B21: months | D21: 12 | M21: Calendar constant
A22: Quarters of actuals in 1H26 | B22: # | D22: 2 | M22: Q1-26 and Q2-26 actuals
A23: Preferred liquidation preference per share | B23: $ | D23: 25 | M23: $25 per preferred share (balance_sheet.csv label)
A24: 1. Aerospace (SCI / MRE modules + products)
A25: Driver | B25: Unit | C25: Q2'26A | D25: Q3'26E | E25: Q4'26E | F25: Q1'27E | G25: Q2'27E | H25: Q3'27E | I25: Q4'27E | J25: FY2028E | K25: FY2029E | L25: FY2030E | M25: Source / rationale
A26: Modules produced and sold per quarter | B26: units | M26: KEY #1. 2027 totals Bear 1,350 / Base 1,500 / Bull 1,700 / Mgmt 1,700 per A_2027_guide_segment_build.csv. 2026 Mgmt total 1,200 (Q2-26 call). 2H26 splits are analyst assumptions (Q2-26 actual 296)
A27: Bear | D27: 285 | E27: 295 | F27: 315 | G27: 330 | H27: 350 | I27: 355
A28: Base | D28: 305 | E28: 320 | F28: 355 | G28: 370 | H28: 385 | I28: 390
A29: Bull | D29: 315 | E29: 345 | F29: 400 | G29: 420 | H29: 435 | I29: 445
A30: Mgmt Guide | D30: 310 | E30: 330 | F30: 400 | G30: 420 | H30: 435 | I30: 445
A31: Selected scenario (live) | D31: =INDEX(D27:D30,$E$4) | E31: =INDEX(E27:E30,$E$4) | F31: =INDEX(F27:F30,$E$4) | G31: =INDEX(G27:G30,$E$4) | H31: =INDEX(H27:H30,$E$4) | I31: =INDEX(I27:I30,$E$4)
A33: Module growth y/y (FY28-FY30) | B33: % | M33: ASSUMPTION: guidance ends 2027. Mgmt Guide FY28+ set equal to Bull. Rationale: 3,000-module physical capacity, GE shop-visit demand ~2,400/yr
A34: Bear | J34: 0.03 | K34: 0.03 | L34: 0.03
A35: Base | J35: 0.08 | K35: 0.06 | L35: 0.05
A36: Bull | J36: 0.12 | K36: 0.1 | L36: 0.08
A37: Mgmt Guide | J37: 0.12 | K37: 0.1 | L37: 0.08
A38: Selected scenario (live) | J38: =INDEX(J34:J37,$E$4) | K38: =INDEX(K34:K37,$E$4) | L38: =INDEX(L34:L37,$E$4)
A40: Aerospace revenue per module (products + MRE) | B40: $M | D40: 2.96 | E40: 2.96 | F40: 2.96 | G40: 2.96 | H40: 2.96 | I40: 2.96 | M40: Q2-26 actual: 875.0 segment revenue / 296 modules = 2.956 (A_2027_guide.md uses ~2.96)
A42: Revenue per module growth y/y (FY28-FY30) | B42: % | J42: 0 | K42: 0 | L42: 0 | M42: ASSUMPTION: flat pricing/mix
A44: Aerospace EBITDA per module | B44: $M | M44: 2027: Bear 0.78 / Base 0.82 / Bull 0.84 per A segment build (rounded to land 1,050 / 1,230 / 1,430); Mgmt 0.8235 = 1,400/1,700. Mgmt 2H26 0.9027 solves to 1,050 FY26 guide. Q2-26 actual 0.84
A45: Bear | D45: 0.8 | E45: 0.8 | F45: 0.7778 | G45: 0.7778 | H45: 0.7778 | I45: 0.7778
A46: Base | D46: 0.84 | E46: 0.84 | F46: 0.82 | G46: 0.82 | H46: 0.82 | I46: 0.82
A47: Bull | D47: 0.86 | E47: 0.88 | F47: 0.8412 | G47: 0.8412 | H47: 0.8412 | I47: 0.8412
A48: Mgmt Guide | D48: 0.9027 | E48: 0.9027 | F48: 0.8235 | G48: 0.8235 | H48: 0.8235 | I48: 0.8235
A49: Selected scenario (live) | D49: =INDEX(D45:D48,$E$4) | E49: =INDEX(E45:E48,$E$4) | F49: =INDEX(F45:F48,$E$4) | G49: =INDEX(G45:G48,$E$4) | H49: =INDEX(H45:H48,$E$4) | I49: =INDEX(I45:I48,$E$4)
A51: MRE share of Aerospace revenue | B51: % | D51: 0.22 | E51: 0.22 | F51: 0.22 | G51: 0.22 | H51: 0.22 | I51: 0.22 | J51: 0.2 | K51: 0.2 | L51: 0.2 | M51: Q2-26 actual 20.9%; 1H26 25.0%; FY25 17.3%. ASSUMPTION: 22% 2H26-2027, 20% after
A53: Aerospace margin cap (economies of scale limit) | B53: % | M53: ASSUMPTION: margin cannot exceed cap. Mgmt now guides ~30% near term (walked back from 40% target)
A54: Bear | D54: 0.28
A55: Base | D55: 0.31
A56: Bull | D56: 0.33
A57: Mgmt Guide | D57: 0.31
A58: Selected scenario (live) | D58: =INDEX(D54:D57,$E$4)
A60: Scale elasticity: margin points gained per 1 point of volume growth | B60: pp/pp | D60: 0.1 | M60: ASSUMPTION: +10% module volume adds +1.0pp margin, up to the cap (competition tip on economies of scale)
A61: 2. Power (J&F JV, equity-accounted; Adj. EBITDA includes pro-rata share)
A62: Driver | B62: Unit | C62: Q2'26A | D62: Q3'26E | E62: Q4'26E | F62: Q1'27E | G62: Q2'27E | H62: Q3'27E | I62: Q4'27E | J62: FY2028E | K62: FY2029E | L62: FY2030E | M62: Source / rationale
A63: Power units delivered per quarter (FY28-30: per year) | B63: units | M63: KEY #3. A_2027_guide_segment_build.csv: Bear 20, Base 44, Bull 59 + ~20 add-on, Mgmt 450/7.5 = 60. 2026 = 0 (first delivery 'prudent to expect' 2027). Quarterly phasing is an assumption (batches run through Nov-2027)
A64: Bear | D64: 0 | E64: 0 | F64: 0 | G64: 4 | H64: 8 | I64: 8 | J64: 40 | K64: 50 | L64: 50
A65: Base | D65: 0 | E65: 0 | F65: 4 | G65: 10 | H65: 14 | I65: 16 | J65: 70 | K65: 80 | L65: 90
A66: Bull | D66: 0 | E66: 0 | F66: 10 | G66: 18 | H66: 24 | I66: 28 | J66: 100 | K66: 100 | L66: 100
A67: Mgmt Guide | D67: 0 | E67: 0 | F67: 6 | G67: 14 | H67: 19 | I67: 21 | J67: 80 | K67: 100 | L67: 100
A68: Selected scenario (live) | D68: =INDEX(D64:D67,$E$4) | E68: =INDEX(E64:E67,$E$4) | F68: =INDEX(F64:F67,$E$4) | G68: =INDEX(G64:G67,$E$4) | H68: =INDEX(H64:H67,$E$4) | I68: =INDEX(I64:I67,$E$4) | J68: =INDEX(J64:J67,$E$4) | K68: =INDEX(K64:K67,$E$4) | L68: =INDEX(L64:L67,$E$4)
A70: Power EBITDA per unit (pro-rata) | B70: $M | M70: UNVERIFIED secondary source ($7-8M per unit; $1M/MW x 25MW). Held at 7.5 in all scenarios so the units drive the spread (per A segment build)
A71: Bear | D71: 7.5 | E71: 7.5 | F71: 7.5 | G71: 7.5 | H71: 7.5 | I71: 7.5 | J71: 7.5 | K71: 7.5 | L71: 7.5
A72: Base | D72: 7.5 | E72: 7.5 | F72: 7.5 | G72: 7.5 | H72: 7.5 | I72: 7.5 | J72: 7.5 | K72: 7.5 | L72: 7.5
A73: Bull | D73: 7.5 | E73: 7.5 | F73: 7.5 | G73: 7.5 | H73: 7.5 | I73: 7.5 | J73: 7.5 | K73: 7.5 | L73: 7.5
A74: Mgmt Guide | D74: 7.5 | E74: 7.5 | F74: 7.5 | G74: 7.5 | H74: 7.5 | I74: 7.5 | J74: 7.5 | K74: 7.5 | L74: 7.5
A75: Selected scenario (live) | D75: =INDEX(D71:D74,$E$4) | E75: =INDEX(E71:E74,$E$4) | F75: =INDEX(F71:F74,$E$4) | G75: =INDEX(G71:G74,$E$4) | H75: =INDEX(H71:H74,$E$4) | I75: =INDEX(I71:I74,$E$4) | J75: =INDEX(J71:J74,$E$4) | K75: =INDEX(K71:K74,$E$4) | L75: =INDEX(L71:L74,$E$4)
A77: Power revenue per unit to FTAI (turbine sale to JV) | B77: $M | D77: 25 | M77: UNVERIFIED: ~$1M per MW x 25 MW (secondary). Used for revenue memo only
A78: Power turbine cost per unit (working-capital investment) | B78: $M | D78: 17.5 | M78: ASSUMPTION = price less EBITDA per unit (25 - 7.5). Funded one quarter ahead of delivery
A79: Power: share of EBITDA that is cash in CFO | B79: % | D79: 0.75 | M79: ASSUMPTION (invented): pro-rata JV earnings are non-cash until distributed; 25% haircut
A80: Power: share of EBITDA that reaches pre-tax income | B80: % | D80: 0.75 | M80: ASSUMPTION (invented): JV-level D&A/interest/tax absorb 25% of pro-rata EBITDA. Moves Bull EPS materially
A81: 3. Leasing (book run-off, SCI fees and co-investment returns)
A82: Driver | B82: Unit | C82: Q2'26A | D82: Q3'26E | E82: Q4'26E | F82: Q1'27E | G82: Q2'27E | H82: Q3'27E | I82: Q4'27E | J82: FY2028E | K82: FY2029E | L82: FY2030E | M82: Source / rationale
A83: Leasing book value sold (per quarter; FY28-30 per year) | B83: $M | M83: ASSUMPTION calibrated so segment Leasing EBITDA lands on A's 2027 targets (270/360/450/450) and the 2026 guide (475). Book was 1,146 at 6/30/26 (22 aircraft, 176 engines); balance-sheet check on Checks tab
A84: Bear | D84: 100 | E84: 80 | F84: 70 | G84: 60 | H84: 50 | I84: 40 | J84: 150 | K84: 100 | L84: 75
A85: Base | D85: 150 | E85: 130 | F85: 110 | G85: 100 | H85: 90 | I85: 80 | J85: 250 | K85: 150 | L85: 100
A86: Bull | D86: 170 | E86: 150 | F86: 130 | G86: 120 | H86: 110 | I86: 100 | J86: 200 | K86: 100 | L86: 50
A87: Mgmt Guide | D87: 170 | E87: 150 | F87: 130 | G87: 120 | H87: 110 | I87: 100 | J87: 200 | K87: 100 | L87: 50
A88: Selected scenario (live) | D88: =INDEX(D84:D87,$E$4) | E88: =INDEX(E84:E87,$E$4) | F88: =INDEX(F84:F87,$E$4) | G88: =INDEX(G84:G87,$E$4) | H88: =INDEX(H84:H87,$E$4) | I88: =INDEX(I84:I87,$E$4) | J88: =INDEX(J84:J87,$E$4) | K88: =INDEX(K84:K87,$E$4) | L88: =INDEX(L84:L87,$E$4)
A90: Gain on sale as % of book value sold | B90: % | D90: 0.15 | M90: ASSUMPTION: Q2-26 'balance-sheet leasing and gains' $48M less ~$26M rent implies ~15% gains on ~$140M sold. 1H26 CFS gains $178M + $18M
A91: Lease EBITDA yield on beginning book (annualised) | B91: % | D91: 0.085 | M91: ASSUMPTION: ~$25M quarterly rent EBITDA on ~$1.2B book (lease income 27.8 + maintenance 25.8 less costs)
A92: SCI total AUM (end of period; FY28-30 year-end) | B92: $M | M92: Q2'26A ~6,000: SCI I total capital ~$6.0B (thesis.md). SCI II targets $6B, deploys $2-3B in 2026-27 (bull). Growth path is an ASSUMPTION; servicing fee grows with AUM
A93: Bear | C93: 6000 | D93: 6150 | E93: 6300 | F93: 6450 | G93: 6600 | H93: 6750 | I93: 6900 | J93: 7500 | K93: 8100 | L93: 8700
A94: Base | C94: 6000 | D94: 6300 | E94: 6600 | F94: 6900 | G94: 7200 | H94: 7500 | I94: 7800 | J94: 9000 | K94: 10200 | L94: 11400
A95: Bull | C95: 6000 | D95: 6450 | E95: 6900 | F95: 7350 | G95: 7800 | H95: 8250 | I95: 8700 | J95: 10500 | K95: 12000 | L95: 13500
A96: Mgmt Guide | C96: 6000 | D96: 6450 | E96: 6900 | F96: 7350 | G96: 7800 | H96: 8250 | I96: 8700 | J96: 10500 | K96: 12000 | L96: 13500
A97: Selected scenario (live) | C97: =INDEX(C93:C96,$E$4) | D97: =INDEX(D93:D96,$E$4) | E97: =INDEX(E93:E96,$E$4) | F97: =INDEX(F93:F96,$E$4) | G97: =INDEX(G93:G96,$E$4) | H97: =INDEX(H93:H96,$E$4) | I97: =INDEX(I93:I96,$E$4) | J97: =INDEX(J93:J96,$E$4) | ... L97: =INDEX(L93:L96,$E$4)
A99: SCI fees and co-invest returns per Q2-26 call (quarter) | B99: $M | D99: 35 | M99: Q2-26 call (secondary): $5M insurance / $48M balance-sheet leasing and gains / $35M SCI fees and co-invest returns
A100: SCI servicing fee rate (annualised % of AUM) | B100: % | D100: =Historical!$N$74*Drivers!$D$18/$C$94 | M100: Formula: Q2-26 servicing fees 6.988 x 4 / AUM 6,000
A101: Pro-rata SCI EBITDA and co-invest returns (included in Adj. EBITDA; non-cash until distributed) | B101: $M | M101: Calibrated to A's SCI component (Bear 190 / Base 240 / Bull 300 for 2027, 2027 = fees + this line). Q2-26 run-rate ~28 (35 less 7.0 fees). NOTE: Mgmt 2H26 of 63/qtr is what the 475 guide requires, roughly double the Q2 run-rate
A102: Bear | D102: 28.3 | E102: 28.3 | F102: 30.9 | G102: 32.9 | H102: 34.9 | I102: 37
A103: Base | D103: 33.2 | E103: 33.3 | F103: 50 | G103: 52 | H103: 54 | I103: 56.2
A104: Bull | D104: 53.9 | E104: 53.8 | F104: 70.3 | G104: 72.3 | H104: 74.3 | I104: 76.5
A105: Mgmt Guide | D105: 63.3 | E105: 63.3 | F105: 70.3 | G105: 72.3 | H105: 74.3 | I105: 76.5
A106: Selected scenario (live) | D106: =INDEX(D102:D105,$E$4) | E106: =INDEX(E102:E105,$E$4) | F106: =INDEX(F102:F105,$E$4) | G106: =INDEX(G102:G105,$E$4) | H106: =INDEX(H102:H105,$E$4) | I106: =INDEX(I102:I105,$E$4)
A108: Insurance recoveries included in Leasing EBITDA | B108: $M | D108: 0 | E108: 0 | F108: 0 | G108: 0 | H108: 0 | I108: 0 | M108: ASSUMPTION: none (Q1-26 44.6 gain, Q2-26 5.0 were one-offs)
A110: Leasing EBITDA growth y/y (FY28-30) | B110: % | M110: ASSUMPTION: SCI fees grow with AUM while book run-off continues
A111: Bear | J111: -0.05 | K111: 0 | L111: 0
A112: Base | J112: 0.05 | K112: 0.05 | L112: 0.05
A113: Bull | J113: 0.1 | K113: 0.08 | L113: 0.06
A114: Mgmt Guide | J114: 0.1 | K114: 0.08 | L114: 0.06
A115: Selected scenario (live) | J115: =INDEX(J111:J114,$E$4) | K115: =INDEX(K111:K114,$E$4) | L115: =INDEX(L111:L114,$E$4)
A117: Leasing equipment acquisitions (cash; FY28-30 per year) | B117: $M | D117: 25 | E117: 25 | F117: 25 | G117: 25 | H117: 25 | I117: 25 | J117: 100 | K117: 100 | L117: 100 | M117: ASSUMPTION: asset-light. 1H26 actual 163 (87.8 + 75.3), falling; added to book value
A119: SCI cash distributions as % of pro-rata EBITDA | B119: % | D119: 0.65 | M119: Q2-26 return of capital 19.2 vs ~28 pro-rata (69%); FY25 27.1 total. ASSUMPTION 65%
A120: SCI co-investment as % of AUM growth (cash) | B120: % | D120: 0.15 | M120: FTAI commits ~15% of SCI II (Q2-26 call, secondary); 19% of SCI I
...

Sheet Historical
A1: Historical financials (typed inputs, blue; each row cites its source)
A2: USD millions except per-share. Fiscal year = calendar year. Q4 figures are derived as FY less 9M, so 'quarters sum to FY' for IS rows holds by construction (not independent verification).
A4: USD m | B4: FY2023A | C4: FY2024A | D4: FY2025A | E4: Q1'24A | F4: Q2'24A | G4: Q3'24A | H4: Q4'24A | I4: Q1'25A | J4: Q2'25A | K4: Q3'25A | L4: Q4'25A | M4: Q1'26A | N4: Q2'26A | O4: Source / rationale
A5: Income statement (USD m, EPS in $)
A6: Aerospace products revenue (ex-MRE) | B6: 454.97 | C6: 1079.821 | D6: 1600.456 | E6: 189.057 | F6: 245.2 | G6: 303.469 | H6: 342.095 | I6: 264.425 | J6: 420.686 | K6: 459.206 | L6: 456.139 | M6: 522.585 | N6: 692.229 | O6: SEC EDGAR 10-Q/10-K segment note, latest filing containing each period (Q2-26 10-Q acc 0001628280-26-051412; FY25 10-K; Q4 = FY less 9M, derived). Via phase2/data/is_quarterly.csv
A7: MRE Contract revenue (to 2025 Partnership) | D7: 335.788 | I7: 100.638 | J7: 69.585 | K7: 58.663 | L7: 106.902 | M7: 221.23 | N7: 182.799 | O7: SEC EDGAR 10-Q/10-K segment note, latest filing containing each period (Q2-26 10-Q acc 0001628280-26-051412; FY25 10-K; Q4 = FY less 9M, derived). Via phase2/data/is_quarterly.csv. Starts Q1-25
A8: Lease income | B8: 207.936 | C8: 255.338 | D8: 235.21 | E8: 53.24 | F8: 70.754 | G8: 65.45 | H8: 65.973 | I8: 68.44 | J8: 62.439 | K8: 55.072 | L8: 49.259 | M8: 39.892 | N8: 27.765 | O8: SEC EDGAR 10-Q/10-K segment note, latest filing containing each period (Q2-26 10-Q acc 0001628280-26-051412; FY25 10-K; Q4 = FY less 9M, derived). Via phase2/data/is_quarterly.csv. FY24 differs from quarterly sum by 0.08 (recast between lease income and other revenue; total unaffected)
A9: Maintenance revenue | B9: 191.347 | C9: 200.809 | D9: 218.499 | E9: 45.79 | F9: 51.187 | G9: 59.917 | H9: 43.915 | I9: 49.607 | J9: 73.104 | K9: 52.37 | L9: 43.418 | M9: 30.599 | N9: 25.793 | O9: SEC EDGAR 10-Q/10-K segment note, latest filing containing each period (Q2-26 10-Q acc 0001628280-26-051412; FY25 10-K; Q4 = FY less 9M, derived). Via phase2/data/is_quarterly.csv
A10: Asset sales revenue | B10: 303.141 | C10: 192.176 | D10: 106.945 | E10: 38.607 | F10: 72.433 | G10: 34.953 | H10: 46.183 | I10: 18.939 | J10: 47.915 | K10: 38.461 | L10: 1.63 | M10: 10.184 | N10: 16.925 | O10: SEC EDGAR 10-Q/10-K segment note, latest filing containing each period (Q2-26 10-Q acc 0001628280-26-051412; FY25 10-K; Q4 = FY less 9M, derived). Via phase2/data/is_quarterly.csv
A11: Other revenue | B11: 13.502 | C11: 6.757 | D11: 10.511 | F11: 4.02 | G11: 2.005 | H11: 0.653 | I11: 0.031 | J11: 2.508 | K11: 3.292 | L11: 4.68 | M11: 6.207 | N11: 7.574 | O11: SEC EDGAR 10-Q/10-K segment note, latest filing containing each period (Q2-26 10-Q acc 0001628280-26-051412; FY25 10-K; Q4 = FY less 9M, derived). Via phase2/data/is_quarterly.csv
A12: Total revenues (reported) | B12: 1170.896 | C12: 1734.901 | D12: 2507.409 | E12: 326.694 | F12: 443.594 | G12: 465.794 | H12: 498.819 | I12: 502.08 | J12: 676.237 | K12: 667.064 | L12: 662.028 | M12: 830.697 | N12: 953.085 | O12: SEC EDGAR 10-Q/10-K segment note, latest filing containing each period (Q2-26 10-Q acc 0001628280-26-051412; FY25 10-K; Q4 = FY less 9M, derived). Via phase2/data/is_quarterly.csv
A13: check: components less total (should be ~0) | B13: =SUM(B6:B11)-B12 | C13: =SUM(C6:C11)-C12 | D13: =SUM(D6:D11)-D12 | E13: =SUM(E6:E11)-E12 | F13: =SUM(F6:F11)-F12 | G13: =SUM(G6:G11)-G12 | H13: =SUM(H6:H11)-H12 | I13: =SUM(I6:I11)-I12 | ... N13: =SUM(N6:N11)-N12 | O13: Formula check (small FY24 differences are source recasts)
A14: Aerospace segment revenue (products + MRE) | B14: 454.97 | C14: 1079.821 | D14: 1936.244 | E14: 189.057 | F14: 245.2 | G14: 303.469 | H14: 342.095 | I14: 365.063 | J14: 490.271 | K14: 517.869 | L14: 563.041 | M14: 743.815 | N14: 875.028 | O14: SEC EDGAR 10-Q/10-K segment note, latest filing containing each period (Q2-26 10-Q acc 0001628280-26-051412; FY25 10-K; Q4 = FY less 9M, derived). Via phase2/data/is_quarterly.csv
A15: Aviation Leasing segment revenue | B15: 681.611 | C15: 628.437 | D15: 571.161 | E15: 135.31 | F15: 184.437 | G15: 152.266 | H15: 156.424 | I15: 137.013 | J15: 185.966 | K15: 149.195 | L15: 98.987 | M15: 86.882 | N15: 78.057 | O15: SEC EDGAR 10-Q/10-K segment note, latest filing containing each period (Q2-26 10-Q acc 0001628280-26-051412; FY25 10-K; Q4 = FY less 9M, derived). Via phase2/data/is_quarterly.csv
A16: Cost of sales (total) | B16: 502.132 | C16: 825.884 | D16: 1349.719 | E16: 142.804 | F16: 205.857 | G16: 219.496 | H16: 257.727 | I16: 248.714 | J16: 369.258 | K16: 362.922 | L16: 368.825 | M16: 524.268 | N16: 635.782 | O16: SEC EDGAR 10-Q/10-K segment note, latest filing containing each period (Q2-26 10-Q acc 0001628280-26-051412; FY25 10-K; Q4 = FY less 9M, derived). Via phase2/data/is_quarterly.csv
A17: Cost of sales - Aerospace segment | B17: 280.28 | C17: 673.907 | D17: 1240.368 | E17: 110.915 | F17: 146.888 | G17: 198.812 | H17: 217.292 | I17: 228.755 | J17: 317.469 | K17: 328.153 | L17: 365.991 | M17: 511.012 | N17: 614.529 | O17: SEC EDGAR 10-Q/10-K segment note, latest filing containing each period (Q2-26 10-Q acc 0001628280-26-051412; FY25 10-K; Q4 = FY less 9M, derived). Via phase2/data/is_quarterly.csv
A18: Operating expenses | B18: 110.163 | C18: 115.861 | D18: 152.541 | E18: 25.317 | F18: 29.099 | G18: 26.858 | H18: 34.587 | I18: 32.438 | J18: 34.328 | K18: 39.092 | L18: 46.683 | M18: 64.987 | N18: 67.567 | O18: SEC EDGAR 10-Q/10-K segment note, latest filing containing each period (Q2-26 10-Q acc 0001628280-26-051412; FY25 10-K; Q4 = FY less 9M, derived). Via phase2/data/is_quarterly.csv
A19: General and administrative | B19: 13.7 | C19: 14.263 | D19: 9.478 | E19: 3.683 | F19: 2.969 | G19: 4.045 | H19: 3.566 | I19: 3.116 | J19: 2.442 | K19: 1.829 | L19: 2.091 | M19: 2.413 | N19: 2.245 | O19: SEC EDGAR 10-Q/10-K segment note, latest filing containing each period (Q2-26 10-Q acc 0001628280-26-051412; FY25 10-K; Q4 = FY less 9M, derived). Via phase2/data/is_quarterly.csv
A20: Acquisition and transaction expenses | B20: 15.194 | C20: 32.296 | D20: 28.587 | E20: 6.179 | F20: 8.019 | G20: 9.341 | H20: 8.757 | I20: 7.292 | J20: 4.489 | K20: 7.066 | L20: 9.74 | M20: 16.361 | N20: 5.699 | O20: SEC EDGAR 10-Q/10-K segment note, latest filing containing each period (Q2-26 10-Q acc 0001628280-26-051412; FY25 10-K; Q4 = FY less 9M, derived). Via phase2/data/is_quarterly.csv
A21: Depreciation and amortization | B21: 169.877 | C21: 218.064 | D21: 225.797 | E21: 49.92 | F21: 56.691 | G21: 56.775 | H21: 54.678 | I21: 59.562 | J21: 55.236 | K21: 55.278 | L21: 55.721 | M21: 52.289 | N21: 46.986 | O21: SEC EDGAR 10-Q/10-K segment note, latest filing containing each period (Q2-26 10-Q acc 0001628280-26-051412; FY25 10-K; Q4 = FY less 9M, derived). Via phase2/data/is_quarterly.csv
A22: Interest expense (positive = expense) | B22: 161.639 | C22: 221.721 | D22: 247.751 | E22: 47.707 | F22: 55.196 | G22: 57.937 | H22: 60.881 | I22: 62.04 | J22: 63.965 | K22: 60.784 | L22: 60.962 | M22: 61.407 | N22: 64.102 | O22: SEC EDGAR 10-Q/10-K segment note, latest filing containing each period (Q2-26 10-Q acc 0001628280-26-051412; FY25 10-K; Q4 = FY less 9M, derived). Via phase2/data/is_quarterly.csv. Sign normalised to positive in source CSV
A23: Gain on sale to the 2025 Partnership | D23: 46.38 | I23: 10.87 | J23: 34.604 | K23: 4.609 | L23: -3.703 | M23: 15.168 | N23: 2.465 | O23: SEC EDGAR 10-Q/10-K segment note, latest filing containing each period (Q2-26 10-Q acc 0001628280-26-051412; FY25 10-K; Q4 = FY less 9M, derived). Via phase2/data/is_quarterly.csv. Booked in Aviation Leasing
A24: Equity in earnings (losses) of unconsolidated entities | B24: -3.275 | C24: -2.2 | D24: -23.659 | E24: -0.667 | F24: -0.694 | G24: -0.438 | H24: -0.401 | I24: -7.614 | J24: -5.003 | K24: -4.224 | L24: -6.818 | M24: -2.363 | N24: 9.97 | O24: SEC EDGAR 10-Q/10-K segment note, latest filing containing each period (Q2-26 10-Q acc 0001628280-26-051412; FY25 10-K; Q4 = FY less 9M, derived). Via phase2/data/is_quarterly.csv. FY = sum of quarters (the CSV FY25 value of -6.8 is the Q4 figure only). FY23 not complete
A25: Income (loss) before income taxes | D25: 606.684 | E25: 45.194 | F25: -232.903 | G25: 93.813 | I25: 125.245 | J25: 203.276 | K25: 144.048 | L25: 134.115 | M25: 169.359 | N25: 150.713 | O25: SEC EDGAR 10-Q/10-K segment note, latest filing containing each period (Q2-26 10-Q acc 0001628280-26-051412; FY25 10-K; Q4 = FY less 9M, derived). Via phase2/data/is_quarterly.csv. FY23/FY24 and Q4-24 not cleanly parsed in source (continuing/discontinued label variants), left blank
A26: Provision for income taxes | D26: 105.62 | F26: -13.033 | G26: 7.331 | I26: 22.859 | J26: 37.878 | K26: 26.33 | L26: 18.553 | M26: 31.46 | N26: 25.619 | O26: SEC EDGAR 10-Q/10-K segment note, latest filing containing each period (Q2-26 10-Q acc 0001628280-26-051412; FY25 10-K; Q4 = FY less 9M, derived). Via phase2/data/is_quarterly.csv. As above
A27: Net income (loss) | D27: 501.064 | E27: 39.622 | F27: -219.87 | G27: 86.482 | I27: 102.386 | J27: 165.398 | K27: 117.718 | L27: 115.562 | M27: 137.899 | N27: 125.094 | O27: SEC EDGAR 10-Q/10-K segment note, latest filing containing each period (Q2-26 10-Q acc 0001628280-26-051412; FY25 10-K; Q4 = FY less 9M, derived). Via phase2/data/is_quarterly.csv. As above
A28: Net income attributable to shareholders | B28: 212.022 | C28: -32.079 | D28: 477.494 | E28: 31.287 | F28: -228.205 | G28: 78.147 | H28: 86.692 | I28: 89.944 | J28: 161.689 | K28: 114.009 | L28: 111.852 | M28: 134.19 | N28: 117.585 | O28: SEC EDGAR 10-Q/10-K segment note, latest filing containing each period (Q2-26 10-Q acc 0001628280-26-051412; FY25 10-K; Q4 = FY less 9M, derived). Via phase2/data/is_quarterly.csv
A29: Preferred dividends + non-controlling interest (NI less attributable) | B29: =IF(OR(B27="",B28=""),"",B27-B28) | C29: =IF(OR(C27="",C28=""),"",C27-C28) | D29: =IF(OR(D27="",D28=""),"",D27-D28) | E29: =IF(OR(E27="",E28=""),"",E27-E28) | F29: =IF(OR(F27="",F28=""),"",F27-F28) | G29: =IF(OR(G27="",G28=""),"",G27-G28) | H29: =IF(OR(H27="",H28=""),"",H27-H28) | I29: =IF(OR(I27="",I28=""),"",I27-I28) | ... N29: =IF(OR(N27="",N28=""),"",N27-N28) | O29: Formula
A30: Diluted EPS ($) | B30: 2.11 | C30: -0.32 | D30: 4.6 | E30: 0.31 | F30: -2.26 | G30: 0.76 | H30: 0.84 | I30: 0.87 | J30: 1.57 | K30: 1.1 | L30: 1.08 | M30: 1.29 | N30: 1.13 | O30: SEC EDGAR 10-Q/10-K segment note, latest filing containing each period (Q2-26 10-Q acc 0001628280-26-051412; FY25 10-K; Q4 = FY less 9M, derived). Via phase2/data/is_quarterly.csv
A31: Diluted weighted shares (M) | B31: 100.42578 | C31: 101.53884 | D31: 103.84691 | E31: 100.96007 | F31: 100.95852 | G31: 103.39535 | H31: 103.60335 | I31: 103.15905 | J31: 103.14786 | K31: 103.96665 | L31: 103.86494 | M31: 104.2559 | N31: 104.04411 | O31: SEC EDGAR 10-Q/10-K segment note, latest filing containing each period (Q2-26 10-Q acc 0001628280-26-051412; FY25 10-K; Q4 = FY less 9M, derived). Via phase2/data/is_quarterly.csv
A32: Segment Adjusted EBITDA (USD m)
A33: Aerospace Products | B33: 160.009 | C33: 380.636 | D33: 671.252 | E33: 70.277 | F33: 91.24 | G33: 101.814 | H33: 117.305 | I33: 130.945 | J33: 164.864 | K33: 180.421 | L33: 195.022 | M33: 222.576 | N33: 249.716 | O33: Q2-26 8-K Ex99.1 2026-07-29 acc 0001628280-26-050622 and 10-Q MD&A/segment notes (phase2/data/segment_ebitda.csv). Eliminations = Total less 3 segments
A34: Aviation Leasing | B34: 467.388 | C34: 500.062 | D34: 608.912 | E34: 104.807 | F34: 124.981 | G34: 136.423 | H34: 133.851 | I34: 161.989 | J34: 199.303 | K34: 134.408 | L34: 113.212 | M34: 152.959 | N34: 88.21 | O34: Q2-26 8-K Ex99.1 2026-07-29 acc 0001628280-26-050622 and 10-Q MD&A/segment notes (phase2/data/segment_ebitda.csv). Eliminations = Total less 3 segments
A35: Corporate and Other | B35: -30.115 | C35: -18.648 | D35: -66.413 | E35: -10.983 | F35: -2.317 | G35: -6.207 | H35: 0.859 | I35: -17.426 | J35: -11.427 | K35: -13.54 | L35: -24.02 | M35: -39.958 | N35: -39.885 | O35: Q2-26 8-K Ex99.1 2026-07-29 acc 0001628280-26-050622 and 10-Q MD&A/segment notes (phase2/data/segment_ebitda.csv). Eliminations = Total less 3 segments
A36: Eliminations (profit elimination on sales to 2025 Partnership) | B36: 0 | C36: 0 | D36: -22.829 | E36: 0 | F36: 0 | G36: 0 | H36: 0 | I36: -6.95 | J36: -4.935 | K36: -3.908 | L36: -7.036 | M36: -10 | N36: -6.597 | O36: Q2-26 8-K Ex99.1 2026-07-29 acc 0001628280-26-050622 and 10-Q MD&A/segment notes (phase2/data/segment_ebitda.csv). Eliminations = Total less 3 segments
A37: Total Adjusted EBITDA (company basis) | B37: 597.282 | C37: 862.05 | D37: 1190.922 | E37: 164.101 | F37: 213.904 | G37: 232.03 | H37: 252.015 | I37: 268.558 | J37: 347.805 | K37: 297.381 | L37: 277.178 | M37: 325.577 | N37: 291.444 | O37: Q2-26 8-K Ex99.1 2026-07-29 acc 0001628280-26-050622 and 10-Q MD&A/segment notes (phase2/data/segment_ebitda.csv). Eliminations = Total less 3 segments
A38: check: segments less total (should be 0) | B38: =B33+B34+B35+B36-B37 | C38: =C33+C34+C35+C36-C37 | D38: =D33+D34+D35+D36-D37 | E38: =E33+E34+E35+E36-E37 | F38: =F33+F34+F35+F36-F37 | G38: =G33+G34+G35+G36-G37 | H38: =H33+H34+H35+H36-H37 | I38: =I33+I34+I35+I36-I37 | ... N38: =N33+N34+N35+N36-N37 | O38: Formula check
A39: Segment-basis EBITDA (Aerospace + Leasing; excl. Corporate and Elims) | B39: =B33+B34 | C39: =C33+C34 | D39: =D33+D34 | E39: =E33+E34 | F39: =F33+F34 | G39: =G33+G34 | H39: =H33+H34 | I39: =I33+I34 | ... N39: =N33+N34 | O39: Formula. Basis used by management guidance (2026: 1,525 = 1,050 + 475)
A40: Aerospace modules produced (units) | I40: 138 | J40: 184 | L40: 228 | N40: 296 | O40: Q2-25 release (184); Q4-25 call (228); Q2-26 call (296); Q1-25 (~138) back-solved from '+33%'. Q3-25 and Q1-26 not found. Call figures are secondary
A41: Aerospace modules incl. Q1-26 estimate (Q1-26 = EBITDA / Q2-26 EBITDA per module) | M41: =ROUND(M33/(N33/N40),0) | N41: =N40 | O41: ASSUMPTION (derived): Q1-26 modules not disclosed in sources; estimated at Q2-26 derived EBITDA/module of 0.84
A42: Gains embedded in Adjusted EBITDA (cash-flow-statement add-backs, positive = gain)
A43: Gain on sale of assets | B43: 160.742 | C43: 377.909 | D43: 377.54 | E43: 58.061 | F43: 88.023 | G43: 98.269 | H43: 133.556 | I43: 8.549 | J43: 217.567 | K43: 68.645 | L43: 82.779 | M43: 92.533 | N43: 85.404 | O43: Statement of cash flows; Q2-Q4 derived as YTD less prior YTD (DERIVED). phase2/data/cash_flow.csv
A44: Gain on sale to the 2025 Partnership (seed assets) | D44: 46.38 | I44: 10.87 | J44: 34.604 | K44: 4.609 | L44: -3.703 | M44: 15.168 | N44: 2.465 | O44: Statement of cash flows; Q2-Q4 derived as YTD less prior YTD (DERIVED). phase2/data/cash_flow.csv
A45: Gain on insurance recoveries (Russia) | D45: 54.325 | I45: 30.125 | J45: 24.2 | K45: 0 | L45: 0 | M45: 44.595 | N45: 4.95 | O45: Statement of cash flows; Q2-Q4 derived as YTD less prior YTD (DERIVED). phase2/data/cash_flow.csv
A46: Total gains (segment attribution not disclosed) | B46: =SUM(B43:B45) | C46: =SUM(C43:C45) | D46: =SUM(D43:D45) | E46: =SUM(E43:E45) | F46: =SUM(F43:F45) | G46: =SUM(G43:G45) | H46: =SUM(H43:H45) | I46: =SUM(I43:I45) | ... N46: =SUM(N43:N45) | O46: Formula
A47: Cash flow (USD m)
A48: Cash flow from operations (CFO) | B48: 128.982 | C48: -187.956 | D48: -310.745 | E48: -0.345 | F48: -187.291 | G48: 41.483 | H48: -41.803 | I48: -25.966 | J48: -110.318 | K48: 4.618 | L48: -179.079 | M48: -160.076 | N48: -105.227 | O48: Statement of cash flows; Q2-Q4 derived as YTD less prior YTD (DERIVED). phase2/data/cash_flow.csv
A49: Cash flow from investing (CFI) | B49: -373.349 | C49: -469.498 | D49: 723.314 | E49: -169.213 | F49: -50.17 | G49: -223.348 | H49: -26.767 | I49: -27.627 | J49: 523.775 | K49: 226.52 | L49: 0.646 | M49: 317.018 | N49: 198.696 | O49: Statement of cash flows; Q2-Q4 derived as YTD less prior YTD (DERIVED). phase2/data/cash_flow.csv
A50: CFO + CFI | B50: =B48+B49 | C50: =C48+C49 | D50: =D48+D49 | E50: =E48+E49 | F50: =F48+F49 | G50: =G48+G49 | H50: =H48+H49 | I50: =I48+I49 | ... N50: =N48+N49 | O50: Formula
A51: CFI: proceeds from sale of assets | B51: 477.886 | C51: 969.28 | D51: 1182.495 | E51: 128.384 | F51: 205.276 | G51: 209.278 | H51: 426.342 | I51: 174.054 | J51: 415.283 | K51: 301.097 | L51: 292.061 | M51: 292.281 | N51: 325.061 | O51: Statement of cash flows; Q2-Q4 derived as YTD less prior YTD (DERIVED). phase2/data/cash_flow.csv
A52: CFI: proceeds from sale of seed assets to 2025 Partnership | D52: 529.97 | I52: 58.892 | J52: 338.256 | K52: 87.96 | L52: 44.862 | M52: 117.345 | N52: 58.312 | O52: Statement of cash flows; Q2-Q4 derived as YTD less prior YTD (DERIVED). phase2/data/cash_flow.csv
A53: CFI: insurance settlement proceeds (Russia) | D53: 54.325 | I53: 30.125 | J53: 24.2 | K53: 0 | L53: 0 | M53: 27.04 | N53: 21.293 | O53: Statement of cash flows; Q2-Q4 derived as YTD less prior YTD (DERIVED). phase2/data/cash_flow.csv. Proceeds (not the CFO gain add-back)
A54: CFI: acquisition of leasing equipment | B54: -749.78 | C54: -1147.341 | D54: -658.799 | E54: -276.99 | F54: -159.19 | G54: -186.186 | H54: -524.975 | I54: -267.417 | J54: -144.719 | K54: -77.645 | L54: -169.018 | M54: -87.793 | N54: -75.261 | O54: Statement of cash flows; Q2-Q4 derived as YTD less prior YTD (DERIVED). phase2/data/cash_flow.csv
A55: CFI: investment in unconsolidated entities (SCI) | B55: -19.5 | D55: -328.546 | I55: -19.967 | J55: -98.76 | K55: -69.971 | L55: -139.848 | M55: -1.246 | N55: -98.005 | O55: Statement of cash flows; Q2-Q4 derived as YTD less prior YTD (DERIVED). phase2/data/cash_flow.csv. Not reported 2024
A56: CFI: acquisition of PP&E | B56: -6.148 | C56: -9.22 | D56: -27.712 | E56: -1.312 | F56: -1.159 | G56: -0.497 | H56: -6.252 | I56: -4.156 | J56: -6.929 | K56: -6.426 | L56: -10.201 | M56: -6.641 | N56: -17.375 | O56: Statement of cash flows; Q2-Q4 derived as YTD less prior YTD (DERIVED). phase2/data/cash_flow.csv
A57: CFI: return of capital from unconsolidated entities (SCI distributions) | D57: 27.1 | I57: 0 | J57: 0 | K57: 27.1 | L57: 0 | M57: 0 | N57: 19.2 | O57: Carried from prior research (phase2/data/cash_flow.csv), not re-parsed from filings. Reported from Q1-25
A58: CFO: change in inventory (negative = outflow) | B58: -31.884 | C58: -206.88 | D58: -645.464 | E58: -6.877 | F58: -52.12 | G58: -104.903 | H58: -42.98 | I58: -127.211 | J58: -141.56 | K58: -123.137 | L58: -253.556 | M58: -186.896 | N58: -266.163 | O58: Statement of cash flows; Q2-Q4 derived as YTD less prior YTD (DERIVED). phase2/data/cash_flow.csv
A59: Memo: inventory-sourced sale proceeds booked in CFI | D59: 1058.9 | I59: 145.4 | J59: 270 | K59: 220.4 | L59: 423.1 | M59: 280.7 | N59: 257.8 | O59: Prior research carry-over (inventory-sourced items), labelled in cash_flow.csv. Reported from Q1-25
A60: Company-reported Adjusted FCF | D60: 724 | J60: 423.5 | M60: 158 | N60: 97 | O60: Q2-25 release (EDGAR); FY25 724 and Q1-26 158 from calls (secondary). Q2-26 = 1H26 255 less Q1 158 (derived)
A61: Balance sheet (period end, USD m)
A62: Cash and cash equivalents | B62: 90.756 | C62: 115.116 | D62: 300.476 | E62: 65.224 | F62: 169.485 | G62: 111.888 | H62: 115.116 | I62: 112.133 | J62: 301.911 | K62: 509.945 | L62: 300.476 | M62: 412.24 | N62: 337.195 | O62: 10-Q/10-K balance sheet & debt note (phase2/data/balance_sheet.csv); FY = Q4 balance
A63: Inventory, net | B63: 316.637 | C63: 551.156 | D63: 1193.773 | E63: 345.47 | F63: 373.282 | G63: 490.997 | H63: 551.156 | I63: 645.163 | J63: 752.866 | K63: 897.216 | L63: 1193.773 | M63: 1364.256 | N63: 1544.592 | O63: 10-Q/10-K balance sheet & debt note (phase2/data/balance_sheet.csv); FY = Q4 balance
A64: Leasing equipment, net | B64: 2032.413 | C64: 2373.73 | D64: 1545.804 | E64: 2187.716 | F64: 2202.866 | G64: 2066.337 | H64: 2373.73 | I64: 1989.367 | J64: 1849.116 | K64: 1669.634 | L64: 1545.804 | M64: 1248.793 | N64: 1146.373 | O64: 10-Q/10-K balance sheet & debt note (phase2/data/balance_sheet.csv); FY = Q4 balance
A65: Investments in unconsolidated entities (incl. 2025 Partnership) | B65: 22.722 | C65: 19.048 | D65: 314.156 | E65: 22.055 | F65: 19.886 | G65: 19.448 | H65: 19.048 | I65: 31.4 | J65: 125.713 | K65: 164.346 | L65: 314.156 | M65: 313.039 | N65: 401.803 | O65: 10-Q/10-K balance sheet & debt note (phase2/data/balance_sheet.csv); FY = Q4 balance
A66: of which: 2025 Partnership (SCI I) equity-method carrying value | D66: 281.74 | L66: 281.74 | N66: 365.485 | O66: related_party.csv: 12/31/25 281.74; 6/30/26 365.485 (19% interest)
A67: Total assets | B67: 2964.685 | C67: 4037.952 | D67: 4373.758 | E67: 3175.906 | F67: 3449.252 | G67: 3738.91 | H67: 4037.952 | I67: 4268.144 | J67: 4101.075 | K67: 4240.2 | L67: 4373.758 | M67: 4528.911 | N67: 4489.162 | O67: 10-Q/10-K balance sheet & debt note (phase2/data/balance_sheet.csv); FY = Q4 balance
A68: Total debt (carrying, before issuance costs) | B68: 2550.493 | C68: 3496.004 | D68: 3496.249 | E68: 2725.234 | F68: 3129.358 | G68: 3278.951 | H68: 3496.004 | I68: 3696.063 | J68: 3496.122 | K68: 3496.185 | L68: 3496.249 | M68: 3496.314 | N68: 3496.38 | O68: 10-Q/10-K balance sheet & debt note (phase2/data/balance_sheet.csv); FY = Q4 balance
A69: Unamortized issuance costs | B69: -33.15 | C69: -55.526 | D69: -47.358 | E69: -31.48 | F69: -51.762 | G69: -60.608 | H69: -55.526 | I69: -53.536 | J69: -51.51 | K69: -49.452 | L69: -47.358 | M69: -45.227 | N69: -43.06 | O69: 10-Q/10-K balance sheet & debt note (phase2/data/balance_sheet.csv); FY = Q4 balance
A70: Total liabilities | B70: 2788.802 | C70: 3956.584 | D70: 4039.584 | E70: 2998.3 | F70: 3379.685 | G70: 3620.378 | H70: 3956.584 | I70: 4239.811 | J70: 3936.131 | K70: 3987.736 | L70: 4039.584 | M70: 4097.235 | N70: 4085.175 | O70: 10-Q/10-K balance sheet & debt note (phase2/data/balance_sheet.csv); FY = Q4 balance
A71: Shareholders' equity | B71: 175.349 | C71: 81.368 | D71: 334.174 | E71: 177.072 | F71: 69.567 | G71: 118.532 | H71: 81.368 | I71: 28.333 | J71: 164.944 | K71: 252.464 | L71: 334.174 | M71: 431.676 | N71: 403.987 | O71: 10-Q/10-K balance sheet & debt note (phase2/data/balance_sheet.csv); FY = Q4 balance
A72: Preferred shares outstanding (M; $25 liquidation preference) | B72: 15.92 | C72: 11.74 | D72: 6.8 | E72: 15.92 | F72: 15.92 | G72: 15.92 | H72: 11.74 | I72: 6.8 | J72: 6.8 | K72: 6.8 | L72: 6.8 | M72: 6.8 | N72: 2.6 | O72: 10-Q/10-K balance sheet & debt note (phase2/data/balance_sheet.csv); FY = Q4 balance
A73: Related party (2025 Partnership / SCI)
A74: Servicing / management fees from Partnership | I74: 0 | J74: 2.052 | K74: 3.035 | L74: 4.515 | M74: 5.861 | N74: 6.988 | O74: related_party.csv (10-Q segment note)
A75: Accounts receivable from Partnership | J75: 93.576 | K75: 41.556 | L75: 47.294 | M75: 35.422 | N75: 25.456 | O75: related_party.csv
A76: KPIs (computed)
A77: Days in period | B77: 365 | C77: 365 | D77: 365 | E77: 91.25 | F77: 91.25 | G77: 91.25 | H77: 91.25 | I77: 91.25 | J77: 91.25 | K77: 91.25 | L77: 91.25 | M77: 91.25 | N77: 91.25 | O77: Input: 365 for FY, 365/4 for quarters
A78: Gains as % of Adjusted EBITDA | B78: =IF(B37=0,"",B46/B37) | C78: =IF(C37=0,"",C46/C37) | D78: =IF(D37=0,"",D46/D37) | E78: =IF(E37=0,"",E46/E37) | F78: =IF(F37=0,"",F46/F37) | G78: =IF(G37=0,"",G46/G37) | H78: =IF(H37=0,"",H46/H37) | I78: =IF(I37=0,"",I46/I37) | ... N78: =IF(N37=0,"",N46/N37) | O78: Formula (gains from CFS add-backs)
A79: MRE share of Aerospace segment revenue | B79: =IF(OR(B7="",B14=0),"",B7/B14) | C79: =IF(OR(C7="",C14=0),"",C7/C14) | D79: =IF(OR(D7="",D14=0),"",D7/D14) | E79: =IF(OR(E7="",E14=0),"",E7/E14) | F79: =IF(OR(F7="",F14=0),"",F7/F14) | G79: =IF(OR(G7="",G14=0),"",G7/G14) | H79: =IF(OR(H7="",H14=0),"",H7/H14) | I79: =IF(OR(I7="",I14=0),"",I7/I14) | ... N79: =IF(OR(N7="",N14=0),"",N7/N14) | O79: Formula
A80: Aerospace Adj. EBITDA margin | B80: =IF(B14=0,"",B33/B14) | C80: =IF(C14=0,"",C33/C14) | D80: =IF(D14=0,"",D33/D14) | E80: =IF(E14=0,"",E33/E14) | F80: =IF(F14=0,"",F33/F14) | G80: =IF(G14=0,"",G33/G14) | H80: =IF(H14=0,"",H33/H14) | I80: =IF(I14=0,"",I33/I14) | ... N80: =IF(N14=0,"",N33/N14) | O80: Formula
A81: Inventory days (on total cost of sales) | B81: =IF(B16=0,"",B63/B16*B77) | C81: =IF(C16=0,"",C63/C16*C77) | D81: =IF(D16=0,"",D63/D16*D77) | E81: =IF(E16=0,"",E63/E16*E77) | F81: =IF(F16=0,"",F63/F16*F77) | G81: =IF(G16=0,"",G63/G16*G77) | H81: =IF(H16=0,"",H63/H16*H77) | I81: =IF(I16=0,"",I63/I16*I77) | ... N81: =IF(N16=0,"",N63/N16*N77) | O81: Formula: period-end inventory / period cost of sales x days. Q2-26 ~222
A82: Inventory days (on Aerospace cost of sales) | B82: =IF(B17=0,"",B63/B17*B77) | C82: =IF(C17=0,"",C63/C17*C77) | D82: =IF(D17=0,"",D63/D17*D77) | E82: =IF(E17=0,"",E63/E17*E77) | F82: =IF(F17=0,"",F63/F17*F77) | G82: =IF(G17=0,"",G63/G17*G77) | H82: =IF(H17=0,"",H63/H17*H77) | I82: =IF(I17=0,"",I63/I17*I77) | ... N82: =IF(N17=0,"",N63/N17*N77) | O82: Formula
A83: CFO / Adjusted EBITDA | B83: =IF(B37=0,"",B48/B37) | C83: =IF(C37=0,"",C48/C37) | D83: =IF(D37=0,"",D48/D37) | E83: =IF(E37=0,"",E48/E37) | F83: =IF(F37=0,"",F48/F37) | G83: =IF(G37=0,"",G48/G37) | H83: =IF(H37=0,"",H48/H37) | I83: =IF(I37=0,"",I48/I37) | ... N83: =IF(N37=0,"",N48/N37) | O83: Formula
A84: (CFO + CFI) / Adjusted EBITDA | B84: =IF(B37=0,"",B50/B37) | C84: =IF(C37=0,"",C50/C37) | D84: =IF(D37=0,"",D50/D37) | E84: =IF(E37=0,"",E50/E37) | F84: =IF(F37=0,"",F50/F37) | G84: =IF(G37=0,"",G50/G37) | H84: =IF(H37=0,"",H50/H37) | I84: =IF(I37=0,"",I50/I37) | ... N84: =IF(N37=0,"",N50/N37) | O84: Formula
A85: Seed-sale proceeds + insurance proceeds (one-off CFI items) | B85: =N(B52)+N(B53) | C85: =N(C52)+N(C53) | D85: =N(D52)+N(D53) | E85: =N(E52)+N(E53) | F85: =N(F52)+N(F53) | G85: =N(G52)+N(G53) | H85: =N(H52)+N(H53) | I85: =N(I52)+N(I53) | ... N85: =N(N52)+N(N53) | O85: Formula
A86: Clean CFO + CFI (excl. seed-sale and insurance proceeds) | B86: =B50-B85 | C86: =C50-C85 | D86: =D50-D85 | E86: =E50-E85 | F86: =F50-F85 | G86: =G50-G85 | H86: =H50-H85 | I86: =I50-I85 | ... N86: =N50-N85 | O86: Formula

Sheet Quarterly
A1: Quarterly model: Q1'26A, Q2'26A, Q3'26E - Q4'27E (8 quarters, 2 actual)
A2: Forecast cells are formulas on the Drivers tab (selected scenario). Actual columns link to Historical (green). USD m except per-share.
A4: USD m | B4: Q1'26A | C4: Q2'26A | D4: Q3'26E | E4: Q4'26E | F4: Q1'27E | G4: Q2'27E | H4: Q3'27E | I4: Q4'27E | J4: FY2026E | K4: FY2027E | L4: Notes
A5: AEROSPACE
A6: Modules produced / sold (units) | B6: =Historical!$M$41 | C6: =Historical!$N$41 | D6: =Drivers!D$31 | E6: =Drivers!E$31 | F6: =Drivers!F$31 | G6: =Drivers!G$31 | H6: =Drivers!H$31 | I6: =Drivers!I$31 | J6: =SUM(B6:E6) | K6: =SUM(F6:I6) | L6: Q1'26 modules estimated (not disclosed)
A7: Revenue per module ($M) | B7: =IF(B6=0,"",B8/B6) | C7: =IF(C6=0,"",C8/C6) | D7: =Drivers!D$40 | E7: =Drivers!E$40 | F7: =Drivers!F$40 | G7: =Drivers!G$40 | H7: =Drivers!H$40 | I7: =Drivers!I$40 | J7: =IF(J6=0,"",J8/J6) | K7: =IF(K6=0,"",K8/K6)
A8: Aerospace segment revenue | B8: =Historical!$M$14 | C8: =Historical!$N$14 | D8: =D6*D7 | E8: =E6*E7 | F8: =F6*F7 | G8: =G6*G7 | H8: =H6*H7 | I8: =I6*I7 | J8: =SUM(B8:E8) | K8: =SUM(F8:I8)
A9: MRE share of Aerospace revenue | B9: =IF(B8=0,"",B10/B8) | C9: =IF(C8=0,"",C10/C8) | D9: =Drivers!D$51 | E9: =Drivers!E$51 | F9: =Drivers!F$51 | G9: =Drivers!G$51 | H9: =Drivers!H$51 | I9: =Drivers!I$51 | J9: =IF(J8=0,"",J10/J8) | K9: =IF(K8=0,"",K10/K8)
A10: MRE Contract revenue (to 2025 Partnership) | B10: =Historical!$M$7 | C10: =Historical!$N$7 | D10: =D8*D9 | E10: =E8*E9 | F10: =F8*F9 | G10: =G8*G9 | H10: =H8*H9 | I10: =I8*I9 | J10: =SUM(B10:E10) | K10: =SUM(F10:I10)
A11: EBITDA per module ($M) | B11: =IF(B6=0,"",B12/B6) | C11: =IF(C6=0,"",C12/C6) | D11: =Drivers!D$49 | E11: =Drivers!E$49 | F11: =Drivers!F$49 | G11: =Drivers!G$49 | H11: =Drivers!H$49 | I11: =Drivers!I$49 | J11: =IF(J6=0,"",J12/J6) | K11: =IF(K6=0,"",K12/K6)
A12: Aerospace Adj. EBITDA [KEY #1 = modules x EBITDA per module] | B12: =Historical!$M$33 | C12: =Historical!$N$33 | D12: =D6*D11 | E12: =E6*E11 | F12: =F6*F11 | G12: =G6*G11 | H12: =H6*H11 | I12: =I6*I11 | J12: =SUM(B12:E12) | K12: =SUM(F12:I12) | L12: KEY #1. Mgmt FY27 1,400 / Base 1,230
A13: Aerospace EBITDA margin | B13: =IF(B8=0,"",B12/B8) | C13: =IF(C8=0,"",C12/C8) | D13: =D12/D8 | E13: =E12/E8 | F13: =F12/F8 | G13: =G12/G8 | H13: =H12/H8 | I13: =I12/I8 | J13: =IF(J8=0,"",J12/J8) | K13: =IF(K8=0,"",K12/K8)
A14: Aerospace cost of sales (actual; forecast proxy = revenue less EBITDA) | B14: =Historical!$M$17 | C14: =Historical!$N$17 | D14: =D8-D12 | E14: =E8-E12 | F14: =F8-F12 | G14: =G8-G12 | H14: =H8-H12 | I14: =I8-I12 | J14: =SUM(B14:E14) | K14: =SUM(F14:I14)
A15: POWER (J&F JV; pro-rata Adj. EBITDA)
A16: Power units delivered | B16: 0 | C16: 0 | D16: =Drivers!D$68 | E16: =Drivers!E$68 | F16: =Drivers!F$68 | G16: =Drivers!G$68 | H16: =Drivers!H$68 | I16: =Drivers!I$68 | J16: =SUM(B16:E16) | K16: =SUM(F16:I16)
A17: EBITDA per unit ($M) | D17: =Drivers!D$75 | E17: =Drivers!E$75 | F17: =Drivers!F$75 | G17: =Drivers!G$75 | H17: =Drivers!H$75 | I17: =Drivers!I$75
A18: Power Adj. EBITDA [KEY #3 = units x EBITDA per unit] | B18: 0 | C18: 0 | D18: =D16*D17 | E18: =E16*E17 | F18: =F16*F17 | G18: =G16*G17 | H18: =H16*H17 | I18: =I16*I17 | J18: =SUM(B18:E18) | K18: =SUM(F18:I18) | L18: KEY #3. 2026 = 0 (first units 'prudent to expect' 2027)
A19: Power revenue to FTAI (memo, unverified price) | B19: 0 | C19: 0 | D19: =D16*Drivers!$D$77 | E19: =E16*Drivers!$D$77 | F19: =F16*Drivers!$D$77 | G19: =G16*Drivers!$D$77 | H19: =H16*Drivers!$D$77 | I19: =I16*Drivers!$D$77 | J19: =SUM(B19:E19) | K19: =SUM(F19:I19)
A20: LEASING
A21: Leasing book, beginning | B21: =Historical!$L$64 | C21: =B25 | D21: =C25 | E21: =D25 | F21: =E25 | G21: =F25 | H21: =G25 | I21: =H25 | J21: =B21 | K21: =F21 | L21: Q2'26 ending book 1,146.4 is the 6/30/26 balance sheet
A22: less: book value sold (run-off) | D22: =Drivers!D$88 | E22: =Drivers!E$88 | F22: =Drivers!F$88 | G22: =Drivers!G$88 | H22: =Drivers!H$88 | I22: =Drivers!I$88 | J22: =SUM(B22:E22) | K22: =SUM(F22:I22)
A23: less: depreciation on book | D23: =Drivers!$D$129*D21 | E23: =Drivers!$D$129*E21 | F23: =Drivers!$D$129*F21 | G23: =Drivers!$D$129*G21 | H23: =Drivers!$D$129*H21 | I23: =Drivers!$D$129*I21 | J23: =SUM(B23:E23) | K23: =SUM(F23:I23)
A24: plus: leasing equipment acquisitions | B24: =-Historical!$M$54 | C24: =-Historical!$N$54 | D24: =Drivers!D$117 | E24: =Drivers!E$117 | F24: =Drivers!F$117 | G24: =Drivers!G$117 | H24: =Drivers!H$117 | I24: =Drivers!I$117 | J24: =SUM(B24:E24) | K24: =SUM(F24:I24)
A25: Leasing book, end | B25: =Historical!$M$64 | C25: =Historical!$N$64 | D25: =D21-D22-D23+D24 | E25: =E21-E22-E23+E24 | F25: =F21-F22-F23+F24 | G25: =G21-G22-G23+G24 | H25: =H21-H22-H23+H24 | I25: =I21-I22-I23+I24 | J25: =E25 | K25: =I25
A26: Lease EBITDA on beginning book (yield) | D26: =Drivers!$D$91/Drivers!$D$18*D21 | E26: =Drivers!$D$91/Drivers!$D$18*E21 | F26: =Drivers!$D$91/Drivers!$D$18*F21 | G26: =Drivers!$D$91/Drivers!$D$18*G21 | H26: =Drivers!$D$91/Drivers!$D$18*H21 | I26: =Drivers!$D$91/Drivers!$D$18*I21 | J26: =SUM(B26:E26) | K26: =SUM(F26:I26)
A27: Gains on sale (% of book sold) | D27: =Drivers!$D$90*D22 | E27: =Drivers!$D$90*E22 | F27: =Drivers!$D$90*F22 | G27: =Drivers!$D$90*G22 | H27: =Drivers!$D$90*H22 | I27: =Drivers!$D$90*I22 | J27: =SUM(B27:E27) | K27: =SUM(F27:I27)
A28: SCI AUM, end ($M) | C28: =Drivers!C$97 | D28: =Drivers!D$97 | E28: =Drivers!E$97 | F28: =Drivers!F$97 | G28: =Drivers!G$97 | H28: =Drivers!H$97 | I28: =Drivers!I$97 | J28: =E28 | K28: =I28
A29: SCI servicing fees (grow with AUM) | B29: =Historical!$M$74 | C29: =Historical!$N$74 | D29: =Drivers!$D$100/Drivers!$D$18*C28 | E29: =Drivers!$D$100/Drivers!$D$18*D28 | F29: =Drivers!$D$100/Drivers!$D$18*E28 | G29: =Drivers!$D$100/Drivers!$D$18*F28 | H29: =Drivers!$D$100/Drivers!$D$18*G28 | I29: =Drivers!$D$100/Drivers!$D$18*H28 | J29: =SUM(B29:E29) | K29: =SUM(F29:I29)
A30: Pro-rata SCI EBITDA and co-invest returns (non-cash) | B30: =Drivers!$D$152 | C30: =Drivers!$D$152 | D30: =Drivers!D$106 | E30: =Drivers!E$106 | F30: =Drivers!F$106 | G30: =Drivers!G$106 | H30: =Drivers!H$106 | I30: =Drivers!I$106 | J30: =SUM(B30:E30) | K30: =SUM(F30:I30)
A31: Insurance recoveries | D31: =Drivers!D$108 | E31: =Drivers!E$108 | F31: =Drivers!F$108 | G31: =Drivers!G$108 | H31: =Drivers!H$108 | I31: =Drivers!I$108 | J31: =SUM(B31:E31) | K31: =SUM(F31:I31)
A32: Leasing Adj. EBITDA | B32: =Historical!$M$34 | C32: =Historical!$N$34 | D32: =D26+D27+D29+D30+D31 | E32: =E26+E27+E29+E30+E31 | F32: =F26+F27+F29+F30+F31 | G32: =G26+G27+G29+G30+G31 | H32: =H26+H27+H29+H30+H31 | I32: =I26+I27+I29+I30+I31 | J32: =SUM(B32:E32) | K32: =SUM(F32:I32)
A33: Leasing segment revenue | B33: =Historical!$M$15 | C33: =Historical!$N$15 | D33: =D32*Drivers!$D$122 | E33: =E32*Drivers!$D$122 | F33: =F32*Drivers!$D$122 | G33: =G32*Drivers!$D$122 | H33: =H32*Drivers!$D$122 | I33: =I32*Drivers!$D$122 | J33: =SUM(B33:E33) | K33: =SUM(F33:I33)
A34: CORPORATE AND TOTALS
A35: Corporate and Other EBITDA | B35: =Historical!$M$35 | C35: =Historical!$N$35 | D35: =Drivers!D$125 | E35: =Drivers!E$125 | F35: =Drivers!F$125 | G35: =Drivers!G$125 | H35: =Drivers!H$125 | I35: =Drivers!I$125 | J35: =SUM(B35:E35) | K35: =SUM(F35:I35)
A36: Eliminations (profit on sales to 2025 Partnership) | B36: =Historical!$M$36 | C36: =Historical!$N$36 | D36: =-Drivers!$D$127*D10 | E36: =-Drivers!$D$127*E10 | F36: =-Drivers!$D$127*F10 | G36: =-Drivers!$D$127*G10 | H36: =-Drivers!$D$127*H10 | I36: =-Drivers!$D$127*I10 | J36: =SUM(B36:E36) | K36: =SUM(F36:I36)
A37: Total Adjusted EBITDA (company basis) | B37: =B12+B18+B32+B35+B36 | C37: =C12+C18+C32+C35+C36 | D37: =D12+D18+D32+D35+D36 | E37: =E12+E18+E32+E35+E36 | F37: =F12+F18+F32+F35+F36 | G37: =G12+G18+G32+G35+G36 | H37: =H12+H18+H32+H35+H36 | I37: =I12+I18+I32+I35+I36 | J37: =SUM(B37:E37) | K37: =SUM(F37:I37)
A38: Segment-basis EBITDA (Aero + Power + Leasing; guide basis) | B38: =B12+B18+B32 | C38: =C12+C18+C32 | D38: =D12+D18+D32 | E38: =E12+E18+E32 | F38: =F12+F18+F32 | G38: =G12+G18+G32 | H38: =H12+H18+H32 | I38: =I12+I18+I32 | J38: =SUM(B38:E38) | K38: =SUM(F38:I38) | L38: Ties to guide: FY26 1,525 / FY27 2,300 in Mgmt Guide scenario
A39: Total revenues | B39: =Historical!$M$12 | C39: =Historical!$N$12 | D39: =D8+D19+D33 | E39: =E8+E19+E33 | F39: =F8+F19+F33 | G39: =G8+G19+G33 | H39: =H8+H19+H33 | I39: =I8+I19+I33 | J39: =SUM(B39:E39) | K39: =SUM(F39:I39)
A40: Adj. EBITDA margin on revenue | B40: =IF(B39=0,"",B37/B39) | C40: =IF(C39=0,"",C37/C39) | D40: =D37/D39 | E40: =E37/E39 | F40: =F37/F39 | G40: =G37/G39 | H40: =H37/H39 | I40: =I37/I39 | J40: =IF(J39=0,"",J37/J39) | K40: =IF(K39=0,"",K37/K39)
A41: EPS BRIDGE
A42: Total Adjusted EBITDA | B42: =B37 | C42: =C37 | D42: =D37 | E42: =E37 | F42: =F37 | G42: =G37 | H42: =H37 | I42: =I37 | J42: =SUM(B42:E42) | K42: =SUM(F42:I42)
A43: less: D&A (leasing book + Aerospace capex base) | B43: =Historical!$M$21 | C43: =Historical!$N$21 | D43: =D23+D44 | E43: =E23+E44 | F43: =F23+F44 | G43: =G23+G44 | H43: =H23+H44 | I43: =I23+I44 | J43: =SUM(B43:E43) | K43: =SUM(F43:I43)
A44: memo: other (non-leasing) D&A | C44: =Drivers!$D$128 | D44: =C44+D45/(Drivers!$D$130*Drivers!$D$18) | E44: =D44+E45/(Drivers!$D$130*Drivers!$D$18) | F44: =E44+F45/(Drivers!$D$130*Drivers!$D$18) | G44: =F44+G45/(Drivers!$D$130*Drivers!$D$18) | H44: =G44+H45/(Drivers!$D$130*Drivers!$D$18) | I44: =H44+I45/(Drivers!$D$130*Drivers!$D$18) | K44: =SUM(F44:I44)
A45: memo: PP&E capex | B45: =-Historical!$M$56 | C45: =-Historical!$N$56 | D45: =Drivers!D$131 | E45: =Drivers!E$131 | F45: =Drivers!F$131 | G45: =Drivers!G$131 | H45: =Drivers!H$131 | I45: =Drivers!I$131 | J45: =SUM(B45:E45) | K45: =SUM(F45:I45)
A46: less: interest expense (debt schedule) | B46: =Historical!$M$22 | C46: =Historical!$N$22 | D46: =Drivers!$D$150/Drivers!$D$18+Drivers!$D$151+C83*Drivers!$D$141/Drivers!$D$18 | E46: =Drivers!$D$150/Drivers!$D$18+Drivers!$D$151+D83*Drivers!$D$141/Drivers!$D$18 | F46: =Drivers!$D$150/Drivers!$D$18+Drivers!$D$151+E83*Drivers!$D$141/Drivers!$D$18 | G46: =Drivers!$D$150/Drivers!$D$18+Drivers!$D$151+F83*Drivers!$D$141/Drivers!$D$18 | H46: =Drivers!$D$150/Drivers!$D$18+Drivers!$D$151+G83*Drivers!$D$141/Drivers!$D$18 | I46: =Drivers!$D$150/Drivers!$D$18+Drivers!$D$151+H83*Drivers!$D$141/Drivers!$D$18 | J46: =SUM(B46:E46) | K46: =SUM(F46:I46)
A47: less: EBITDA-to-pretax adjustments (SCI/Power pro-rata not in pretax, SBC, other) | B47: =B48-(B37-B43-B46) | C47: =C48-(C37-C43-C46) | D47: =-(D30*(1-Drivers!$D$153)+Drivers!$D$154+(1-Drivers!$D$80)*D18) | E47: =-(E30*(1-Drivers!$D$153)+Drivers!$D$154+(1-Drivers!$D$80)*E18) | F47: =-(F30*(1-Drivers!$D$153)+Drivers!$D$154+(1-Drivers!$D$80)*F18) | G47: =-(G30*(1-Drivers!$D$153)+Drivers!$D$154+(1-Drivers!$D$80)*G18) | H47: =-(H30*(1-Drivers!$D$153)+Drivers!$D$154+(1-Drivers!$D$80)*H18) | I47: =-(I30*(1-Drivers!$D$153)+Drivers!$D$154+(1-Drivers!$D$80)*I18) | J47: =SUM(B47:E47) | K47: =SUM(F47:I47) | L47: Actual = reported pretax less (EBITDA - D&A - interest); calibration 1H26 on Drivers tab
A48: Pre-tax income | B48: =Historical!$M$25 | C48: =Historical!$N$25 | D48: =D37-D43-D46+D47 | E48: =E37-E43-E46+E47 | F48: =F37-F43-F46+F47 | G48: =G37-G43-G46+G47 | H48: =H37-H43-H46+H47 | I48: =I37-I43-I46+I47 | J48: =SUM(B48:E48) | K48: =SUM(F48:I48)
A49: Income taxes | B49: =Historical!$M$26 | C49: =Historical!$N$26 | D49: =D48*Drivers!$D$133 | E49: =E48*Drivers!$D$133 | F49: =F48*Drivers!$D$133 | G49: =G48*Drivers!$D$133 | H49: =H48*Drivers!$D$133 | I49: =I48*Drivers!$D$133 | J49: =SUM(B49:E49) | K49: =SUM(F49:I49)
A50: Net income | B50: =Historical!$M$27 | C50: =Historical!$N$27 | D50: =D48-D49 | E50: =E48-E49 | F50: =F48-F49 | G50: =G48-G49 | H50: =H48-H49 | I50: =I48-I49 | J50: =SUM(B50:E50) | K50: =SUM(F50:I50)
A51: less: preferred dividends and NCI | B51: =Historical!$M$29 | C51: =Historical!$N$29 | D51: =Drivers!$D$134 | E51: =Drivers!$D$134 | F51: =Drivers!$D$134 | G51: =Drivers!$D$134 | H51: =Drivers!$D$134 | I51: =Drivers!$D$134 | J51: =SUM(B51:E51) | K51: =SUM(F51:I51)
A52: Net income attributable to common | B52: =Historical!$M$28 | C52: =Historical!$N$28 | D52: =D50-D51 | E52: =E50-E51 | F52: =F50-F51 | G52: =G50-G51 | H52: =H50-H51 | I52: =I50-I51 | J52: =SUM(B52:E52) | K52: =SUM(F52:I52)
A53: Diluted shares (M) | B53: =Historical!$M$31 | C53: =Historical!$N$31 | D53: =Drivers!$D$135-Drivers!$D$136*Drivers!$D$137/Drivers!$D$138/Drivers!$D$180 | E53: =D53-Drivers!$D$136*Drivers!$D$137/Drivers!$D$138/Drivers!$D$180 | F53: =E53-Drivers!$D$136*Drivers!$D$137/Drivers!$D$138/Drivers!$D$180 | G53: =F53-Drivers!$D$136*Drivers!$D$137/Drivers!$D$138/Drivers!$D$180 | H53: =G53-Drivers!$D$136*Drivers!$D$137/Drivers!$D$138/Drivers!$D$180 | I53: =H53-Drivers!$D$136*Drivers!$D$137/Drivers!$D$138/Drivers!$D$180 | J53: =AVERAGE(B53:E53) | K53: =AVERAGE(F53:I53) | L53: Buyback toggle default OFF
A54: Diluted EPS ($) | B54: =Historical!$M$30 | C54: =Historical!$N$30 | D54: =D52/D53 | E54: =E52/E53 | F54: =F52/F53 | G54: =G52/G53 | H54: =H52/H53 | I54: =I52/I53 | J54: =J52/J53 | K54: =K52/K53 | L54: Actual = reported diluted EPS
A55: CASH FLOW BUILD (CFO + CFI, GAAP classification combined)
A56: Total Adjusted EBITDA | D56: =D37 | E56: =E37 | F56: =F37 | G56: =G37 | H56: =H37 | I56: =I37 | J56: =SUM(B56:E56) | K56: =SUM(F56:I56)
A57: less: gains in EBITDA (proceeds sit in CFI) | D57: =-(D27+D31) | E57: =-(E27+E31) | F57: =-(F27+F31) | G57: =-(G27+G31) | H57: =-(H27+H31) | I57: =-(I27+I31) | J57: =SUM(B57:E57) | K57: =SUM(F57:I57)
A58: less: pro-rata SCI EBITDA (non-cash) | D58: =-D30 | E58: =-E30 | F58: =-F30 | G58: =-G30 | H58: =-H30 | I58: =-I30 | J58: =SUM(B58:E58) | K58: =SUM(F58:I58)
A59: plus: SCI cash distributions (return of capital) | D59: =Drivers!$D$119*D30 | E59: =Drivers!$D$119*E30 | F59: =Drivers!$D$119*F30 | G59: =Drivers!$D$119*G30 | H59: =Drivers!$D$119*H30 | I59: =Drivers!$D$119*I30 | J59: =SUM(B59:E59) | K59: =SUM(F59:I59)
A60: less: Power EBITDA not converted to cash | D60: =-(1-Drivers!$D$79)*D18 | E60: =-(1-Drivers!$D$79)*E18 | F60: =-(1-Drivers!$D$79)*F18 | G60: =-(1-Drivers!$D$79)*G18 | H60: =-(1-Drivers!$D$79)*H18 | I60: =-(1-Drivers!$D$79)*I18 | J60: =SUM(B60:E60) | K60: =SUM(F60:I60)
A61: less: cash interest | D61: =-D46 | E61: =-E46 | F61: =-F46 | G61: =-G46 | H61: =-H46 | I61: =-I46 | J61: =SUM(B61:E61) | K61: =SUM(F61:I61)
A62: less: cash taxes (= book taxes) | D62: =-D49 | E62: =-E49 | F62: =-F49 | G62: =-G49 | H62: =-H49 | I62: =-I49 | J62: =SUM(B62:E62) | K62: =SUM(F62:I62)
A63: less: increase in Aerospace inventory [KEY #2] | D63: =-(D86-C86) | E63: =-(E86-D86) | F63: =-(F86-E86) | G63: =-(G86-F86) | H63: =-(H86-G86) | I63: =-(I86-H86) | J63: =SUM(B63:E63) | K63: =SUM(F63:I63) | L63: KEY #2: days-based inventory, driven by conversion %
A64: less: Power turbine working-capital investment (next quarter's units) | D64: =-Drivers!$D$78*E16 | E64: =-Drivers!$D$78*F16 | F64: =-Drivers!$D$78*G16 | G64: =-Drivers!$D$78*H16 | H64: =-Drivers!$D$78*I16 | I64: =-Drivers!$D$78*Drivers!J$68/Drivers!$D$18 | J64: =SUM(B64:E64) | K64: =SUM(F64:I64)
A65: plus: Power working-capital release on delivery | D65: =Drivers!$D$78*D16 | E65: =Drivers!$D$78*E16 | F65: =Drivers!$D$78*F16 | G65: =Drivers!$D$78*G16 | H65: =Drivers!$D$78*H16 | I65: =Drivers!$D$78*I16 | J65: =SUM(B65:E65) | K65: =SUM(F65:I65)
A66: plus: leasing book sold (at book value; gain already in EBITDA) | D66: =D22 | E66: =E22 | F66: =F22 | G66: =G22 | H66: =H22 | I66: =I22 | J66: =SUM(B66:E66) | K66: =SUM(F66:I66)
A67: less: leasing equipment acquisitions | D67: =-D24 | E67: =-E24 | F67: =-F24 | G67: =-G24 | H67: =-H24 | I67: =-I24 | J67: =SUM(B67:E67) | K67: =SUM(F67:I67)
A68: less: SCI co-investment | D68: =-Drivers!$D$120*(D28-C28) | E68: =-Drivers!$D$120*(E28-D28) | F68: =-Drivers!$D$120*(F28-E28) | G68: =-Drivers!$D$120*(G28-F28) | H68: =-Drivers!$D$120*(H28-G28) | I68: =-Drivers!$D$120*(I28-H28) | J68: =SUM(B68:E68) | K68: =SUM(F68:I68)
A69: less: PP&E capex | D69: =-D45 | E69: =-E45 | F69: =-F45 | G69: =-G45 | H69: =-H45 | I69: =-I45 | J69: =SUM(B69:E69) | K69: =SUM(F69:I69)
A70: plus: insurance proceeds | D70: =D31 | E70: =E31 | F70: =F31 | G70: =G31 | H70: =H31 | I70: =I31 | J70: =SUM(B70:E70) | K70: =SUM(F70:I70)
A71: CFO + CFI (GAAP basis, model) | B71: =Historical!$M$50 | C71: =Historical!$N$50 | D71: =SUM(D56:D70) | E71: =SUM(E56:E70) | F71: =SUM(F56:F70) | G71: =SUM(G56:G70) | H71: =SUM(H56:H70) | I71: =SUM(I56:I70) | J71: =SUM(B71:E71) | K71: =SUM(F71:I71) | L71: Actual = reported CFO + CFI (Q1 157.0, Q2 93.5)
A72: memo: seed-sale proceeds to SCI (one-off) | B72: =Historical!$M$52 | C72: =Historical!$N$52 | D72: =Drivers!$D$121*D22*(1+Drivers!$D$90) | E72: =Drivers!$D$121*E22*(1+Drivers!$D$90) | F72: =Drivers!$D$121*F22*(1+Drivers!$D$90) | G72: =Drivers!$D$121*G22*(1+Drivers!$D$90) | H72: =Drivers!$D$121*H22*(1+Drivers!$D$90) | I72: =Drivers!$D$121*I22*(1+Drivers!$D$90) | J72: =SUM(B72:E72) | K72: =SUM(F72:I72)
A73: memo: insurance proceeds (one-off) | B73: =Historical!$M$53 | C73: =Historical!$N$53 | D73: =D31 | E73: =E31 | F73: =F31 | G73: =G31 | H73: =H31 | I73: =I31 | J73: =SUM(B73:E73) | K73: =SUM(F73:I73)
A74: Clean CFO + CFI (excl. seed-sale and insurance proceeds) | B74: =B71-B72-B73 | C74: =C71-C72-C73 | D74: =D71-D72-D73 | E74: =E71-E72-E73 | F74: =F71-F72-F73 | G74: =G71-G72-G73 | H74: =H71-H72-H73 | I74: =I71-I72-I73 | J74: =SUM(B74:E74) | K74: =SUM(F74:I74) | L74: Actual 1H26: 250.4 - 175.7 seed - 48.3 insurance = 26.4
A75: Company-defined Adjusted FCF (adds back SCI co-invest, NET Power turbine investment, hot-section parts) | B75: =Historical!$M$60 | C75: =Historical!$N$60 | D75: =D71-D68+MAX(0,-(D64+D65))+Drivers!$D$177 | E75: =E71-E68+MAX(0,-(E64+E65))+Drivers!$D$177 | F75: =F71-F68+MAX(0,-(F64+F65))+Drivers!$D$177 | G75: =G71-G68+MAX(0,-(G64+G65))+Drivers!$D$177 | H75: =H71-H68+MAX(0,-(H64+H65))+Drivers!$D$177 | I75: =I71-I68+MAX(0,-(I64+I65))+Drivers!$D$177 | J75: =SUM(B75:E75) | K75: =SUM(F75:I75) | L75: Actual: Q1 158, Q2 97 (1H26 255) per company; forecast uses FY25-style add-backs
A76: FINANCING AND BALANCE SHEET ITEMS
A77: Common dividends | D77: =-Drivers!$D$139*D53 | E77: =-Drivers!$D$139*E53 | F77: =-Drivers!$D$139*F53 | G77: =-Drivers!$D$139*G53 | H77: =-Drivers!$D$139*H53 | I77: =-Drivers!$D$139*I53 | J77: =SUM(B77:E77) | K77: =SUM(F77:I77)
A78: Preferred dividends and NCI (cash) | D78: =-D51 | E78: =-E51 | F78: =-F51 | G78: =-G51 | H78: =-H51 | I78: =-I51 | J78: =SUM(B78:E78) | K78: =SUM(F78:I78)
A79: Share buybacks (toggle) | D79: =-Drivers!$D$136*Drivers!$D$137/Drivers!$D$138 | E79: =-Drivers!$D$136*Drivers!$D$137/Drivers!$D$138 | F79: =-Drivers!$D$136*Drivers!$D$137/Drivers!$D$138 | G79: =-Drivers!$D$136*Drivers!$D$137/Drivers!$D$138 | H79: =-Drivers!$D$136*Drivers!$D$137/Drivers!$D$138 | I79: =-Drivers!$D$136*Drivers!$D$137/Drivers!$D$138 | J79: =SUM(B79:E79) | K79: =SUM(F79:I79)
A80: Cash before revolver | D80: =C82+D71+D77+D78+D79 | E80: =D82+E71+E77+E78+E79 | F80: =E82+F71+F77+F78+F79 | G80: =F82+G71+G77+G78+G79 | H80: =G82+H71+H77+H78+H79 | I80: =H82+I71+I77+I78+I79 | J80: =E80 | K80: =I80
A81: Revolver draw / (repayment) | D81: =MAX(-C83,Drivers!$D$140-D80) | E81: =MAX(-D83,Drivers!$D$140-E80) | F81: =MAX(-E83,Drivers!$D$140-F80) | G81: =MAX(-F83,Drivers!$D$140-G80) | H81: =MAX(-G83,Drivers!$D$140-H80) | I81: =MAX(-H83,Drivers!$D$140-I80) | J81: =SUM(B81:E81) | K81: =SUM(F81:I81)
A82: Cash, end | B82: =Historical!$M$62 | C82: =Historical!$N$62 | D82: =D80+D81 | E82: =E80+E81 | F82: =F80+F81 | G82: =G80+G81 | H82: =H80+H81 | I82: =I80+I81 | J82: =E82 | K82: =I82
A83: Revolver balance, end | B83: 0 | C83: 0 | D83: =C83+D81 | E83: =D83+E81 | F83: =E83+F81 | G83: =F83+G81 | H83: =G83+H81 | I83: =H83+I81 | J83: =E83 | K83: =I83 | L83: Revolver undrawn at 6/30/26
A84: Senior notes (carrying, before issuance costs) | B84: =Historical!$M$68 | C84: =Historical!$N$68 | D84: =C84 | E84: =D84 | F84: =E84 | G84: =F84 | H84: =G84 | I84: =H84 | J84: =E84 | K84: =I84
A85: Net debt | B85: =B84+B83-B82 | C85: =C84+C83-C82 | D85: =D84+D83-D82 | E85: =E84+E83-E82 | F85: =F84+F83-F82 | G85: =G84+G83-G82 | H85: =H84+H83-H82 | I85: =I84+I83-I82 | J85: =E85 | K85: =I85
A86: Inventory, end | B86: =Historical!$M$63 | C86: =Historical!$N$63 | D86: =Drivers!D$173*D14/Drivers!$D$19 | E86: =Drivers!E$173*E14/Drivers!$D$19 | F86: =Drivers!F$173*F14/Drivers!$D$19 | G86: =Drivers!G$173*G14/Drivers!$D$19 | H86: =Drivers!H$173*H14/Drivers!$D$19 | I86: =Drivers!I$173*I14/Drivers!$D$19 | J86: =E86 | K86: =I86
A87: Inventory days (Aerospace cost-of-sales basis) | B87: =IF(B14=0,"",B86/B14*Drivers!$D$19) | C87: =IF(C14=0,"",C86/C14*Drivers!$D$19) | D87: =D86/D14*Drivers!$D$19 | E87: =E86/E14*Drivers!$D$19 | F87: =F86/F14*Drivers!$D$19 | G87: =G86/G14*Drivers!$D$19 | H87: =H86/H14*Drivers!$D$19 | I87: =I86/I14*Drivers!$D$19 | J87: =J86/J14*Drivers!$D$20 | K87: =K86/K14*Drivers!$D$20
A89: BACK-TEST of the EPS bridge on actual quarters (driver-based pretax vs reported)
A90: Predicted pre-tax (EBITDA - D&A - interest - [pro-rata x (1 - equity conv.) + other adj.]) | B90: =B37-B43-B46-(B30*(1-Drivers!$D$153)+Drivers!$D$154) | C90: =C37-C43-C46-(C30*(1-Drivers!$D$153)+Drivers!$D$154) | L90: Pro-rata for Q1'26 is assumed equal to Q2'26 (components not disclosed). Calibrated on 1H26 combined, so each quarter is an out-of-sample test
A91: Predicted net income attributable | B91: =B90*(1-Drivers!$D$133)-B51 | C91: =C90*(1-Drivers!$D$133)-C51
A92: Predicted diluted EPS ($) | B92: =B91/B53 | C92: =C91/C53
A93: Reported diluted EPS ($) | B93: =B54 | C93: =C54
A94: Difference ($) | B94: =B92-B93 | C94: =C92-C93

Sheet Annual
A1: Annual model: FY2023A - FY2025A history, FY2026E - FY2030E projections (5 years)
A2: FY26 and FY27 are summed from Quarterly; FY28-FY30 are driven by annual growth, margin-scale (capped) and unit drivers on the Drivers tab. USD m except per-share.
A4: USD m | B4: FY2023A | C4: FY2024A | D4: FY2025A | E4: FY2026E | F4: FY2027E | G4: FY2028E | H4: FY2029E | I4: FY2030E | J4: Notes
A5: AEROSPACE
A6: Modules produced / sold (units) | E6: =SUM(Quarterly!B6:E6) | F6: =SUM(Quarterly!F6:I6) | G6: =F6*(1+Drivers!J$38) | H6: =G6*(1+Drivers!K$38) | I6: =H6*(1+Drivers!L$38)
A7: Revenue per module ($M) | E7: =IF(E6=0,"",E8/E6) | F7: =IF(F6=0,"",F8/F6) | G7: =F7*(1+Drivers!J$42) | H7: =G7*(1+Drivers!K$42) | I7: =H7*(1+Drivers!L$42)
A8: Aerospace segment revenue | B8: =Historical!$B$14 | C8: =Historical!$C$14 | D8: =Historical!$D$14 | E8: =SUM(Quarterly!B8:E8) | F8: =SUM(Quarterly!F8:I8) | G8: =G6*G7 | H8: =H6*H7 | I8: =I6*I7
A9: MRE share of Aerospace revenue | D9: =IF(D8=0,"",D10/D8) | E9: =IF(E8=0,"",E10/E8) | F9: =IF(F8=0,"",F10/F8) | G9: =Drivers!J$51 | H9: =Drivers!K$51 | I9: =Drivers!L$51
A10: MRE Contract revenue (to 2025 Partnership) | D10: =Historical!$D$7 | E10: =SUM(Quarterly!B10:E10) | F10: =SUM(Quarterly!F10:I10) | G10: =G8*G9 | H10: =H8*H9 | I10: =I8*I9
A11: EBITDA per module ($M) | E11: =IF(E6=0,"",E12/E6) | F11: =IF(F6=0,"",F12/F6) | G11: =G12/G6 | H11: =H12/H6 | I11: =I12/I6
A12: Aerospace Adj. EBITDA [KEY #1 = modules x EBITDA per module] | B12: =Historical!$B$33 | C12: =Historical!$C$33 | D12: =Historical!$D$33 | E12: =SUM(Quarterly!B12:E12) | F12: =SUM(Quarterly!F12:I12) | G12: =G8*G13 | H12: =H8*H13 | I12: =I8*I13 | J12: FY26/27 = sum of Quarterly. History: segment Adj. EBITDA
A13: Aerospace EBITDA margin | B13: =IF(B8=0,"",B12/B8) | C13: =IF(C8=0,"",C12/C8) | D13: =IF(D8=0,"",D12/D8) | E13: =IF(E8=0,"",E12/E8) | F13: =IF(F8=0,"",F12/F8) | G13: =MIN(Drivers!D$58,F13+Drivers!$D$60*Drivers!J$38) | H13: =MIN(Drivers!D$58,G13+Drivers!$D$60*Drivers!K$38) | I13: =MIN(Drivers!D$58,H13+Drivers!$D$60*Drivers!L$38) | J13: FY28+: margin = MIN(cap, prior + elasticity x volume growth): economies of scale up to a cap
A14: Aerospace cost of sales (actual; forecast proxy = revenue less EBITDA) | B14: =Historical!$B$17 | C14: =Historical!$C$17 | D14: =Historical!$D$17 | E14: =SUM(Quarterly!B14:E14) | F14: =SUM(Quarterly!F14:I14) | G14: =G8-G12 | H14: =H8-H12 | I14: =I8-I12
A15: POWER (J&F JV; pro-rata Adj. EBITDA)
A16: Power units delivered | E16: =SUM(Quarterly!B16:E16) | F16: =SUM(Quarterly!F16:I16) | G16: =Drivers!J$68 | H16: =Drivers!K$68 | I16: =Drivers!L$68
A17: EBITDA per unit ($M) | G17: =Drivers!J$75 | H17: =Drivers!K$75 | I17: =Drivers!L$75
A18: Power Adj. EBITDA [KEY #3 = units x EBITDA per unit] | E18: =SUM(Quarterly!B18:E18) | F18: =SUM(Quarterly!F18:I18) | G18: =G16*G17 | H18: =H16*H17 | I18: =I16*I17
A19: Power revenue to FTAI (memo, unverified price) | E19: =SUM(Quarterly!B19:E19) | F19: =SUM(Quarterly!F19:I19) | G19: =G16*Drivers!$D$77 | H19: =H16*Drivers!$D$77 | I19: =I16*Drivers!$D$77
A20: LEASING
A21: Leasing book, beginning | E21: =Quarterly!B21 | F21: =Quarterly!F21 | G21: =F25 | H21: =G25 | I21: =H25
A22: less: book value sold (run-off) | E22: =SUM(Quarterly!B22:E22) | F22: =SUM(Quarterly!F22:I22) | G22: =Drivers!J$88 | H22: =Drivers!K$88 | I22: =Drivers!L$88
A23: less: depreciation on book | E23: =SUM(Quarterly!B23:E23) | F23: =SUM(Quarterly!F23:I23) | G23: =Drivers!$D$129*Drivers!$D$18*G21 | H23: =Drivers!$D$129*Drivers!$D$18*H21 | I23: =Drivers!$D$129*Drivers!$D$18*I21
A24: plus: leasing equipment acquisitions | E24: =SUM(Quarterly!B24:E24) | F24: =SUM(Quarterly!F24:I24) | G24: =Drivers!J$117 | H24: =Drivers!K$117 | I24: =Drivers!L$117
A25: Leasing book, end | B25: =Historical!$B$64 | C25: =Historical!$C$64 | D25: =Historical!$D$64 | E25: =Quarterly!E25 | F25: =Quarterly!I25 | G25: =G21-G22-G23+G24 | H25: =H21-H22-H23+H24 | I25: =I21-I22-I23+I24
A26: Lease EBITDA on beginning book (yield) | E26: =SUM(Quarterly!B26:E26) | F26: =SUM(Quarterly!F26:I26)
A27: Gains on sale (% of book sold) | B27: =Historical!$B$46 | C27: =Historical!$C$46 | D27: =Historical!$D$46 | E27: =SUM(Quarterly!B27:E27) | F27: =SUM(Quarterly!F27:I27) | G27: =Drivers!$D$90*G22 | H27: =Drivers!$D$90*H22 | I27: =Drivers!$D$90*I22
A28: SCI AUM, end ($M) | E28: =Quarterly!E28 | F28: =Quarterly!I28 | G28: =Drivers!J$97 | H28: =Drivers!K$97 | I28: =Drivers!L$97
A29: SCI servicing fees (grow with AUM) | E29: =SUM(Quarterly!B29:E29) | F29: =SUM(Quarterly!F29:I29)
A30: Pro-rata SCI EBITDA and co-invest returns (non-cash) | E30: =SUM(Quarterly!B30:E30) | F30: =SUM(Quarterly!F30:I30) | G30: =G32*F30/F32 | H30: =H32*G30/G32 | I30: =I32*H30/H32
A31: Insurance recoveries | E31: =SUM(Quarterly!B31:E31) | F31: =SUM(Quarterly!F31:I31)
A32: Leasing Adj. EBITDA | B32: =Historical!$B$34 | C32: =Historical!$C$34 | D32: =Historical!$D$34 | E32: =SUM(Quarterly!B32:E32) | F32: =SUM(Quarterly!F32:I32) | G32: =F32*(1+Drivers!J$115) | H32: =G32*(1+Drivers!K$115) | I32: =H32*(1+Drivers!L$115)
A33: Leasing segment revenue | B33: =Historical!$B$15 | C33: =Historical!$C$15 | D33: =Historical!$D$15 | E33: =SUM(Quarterly!B33:E33) | F33: =SUM(Quarterly!F33:I33) | G33: =G32*Drivers!$D$122 | H33: =H32*Drivers!$D$122 | I33: =I32*Drivers!$D$122
A34: CORPORATE AND TOTALS
A35: Corporate and Other EBITDA | B35: =Historical!$B$35 | C35: =Historical!$C$35 | D35: =Historical!$D$35 | E35: =SUM(Quarterly!B35:E35) | F35: =SUM(Quarterly!F35:I35) | G35: =F35*(1+Drivers!J$125) | H35: =G35*(1+Drivers!K$125) | I35: =H35*(1+Drivers!L$125)
A36: Eliminations (profit on sales to 2025 Partnership) | B36: =Historical!$B$36 | C36: =Historical!$C$36 | D36: =Historical!$D$36 | E36: =SUM(Quarterly!B36:E36) | F36: =SUM(Quarterly!F36:I36) | G36: =-Drivers!$D$127*G10 | H36: =-Drivers!$D$127*H10 | I36: =-Drivers!$D$127*I10
A37: Total Adjusted EBITDA (company basis) | B37: =B12+B32+B35+B36 | C37: =C12+C32+C35+C36 | D37: =D12+D32+D35+D36 | E37: =SUM(Quarterly!B37:E37) | F37: =SUM(Quarterly!F37:I37) | G37: =G12+G18+G32+G35+G36 | H37: =H12+H18+H32+H35+H36 | I37: =I12+I18+I32+I35+I36
A38: Segment-basis EBITDA (Aero + Power + Leasing; guide basis) | B38: =B12+B32 | C38: =C12+C32 | D38: =D12+D32 | E38: =SUM(Quarterly!B38:E38) | F38: =SUM(Quarterly!F38:I38) | G38: =G12+G18+G32 | H38: =H12+H18+H32 | I38: =I12+I18+I32 | J38: FY26 guide 1,525; FY27 guide 2,300
A39: Total revenues | B39: =Historical!$B$12 | C39: =Historical!$C$12 | D39: =Historical!$D$12 | E39: =SUM(Quarterly!B39:E39) | F39: =SUM(Quarterly!F39:I39) | G39: =G8+G19+G33 | H39: =H8+H19+H33 | I39: =I8+I19+I33
A40: Adj. EBITDA margin on revenue | B40: =IF(B39=0,"",B37/B39) | C40: =IF(C39=0,"",C37/C39) | D40: =IF(D39=0,"",D37/D39) | E40: =IF(E39=0,"",E37/E39) | F40: =IF(F39=0,"",F37/F39) | G40: =G37/G39 | H40: =H37/H39 | I40: =I37/I39
A41: EPS BRIDGE
A42: Total Adjusted EBITDA | B42: =B37 | C42: =C37 | D42: =D37 | E42: =SUM(Quarterly!B42:E42) | F42: =SUM(Quarterly!F42:I42) | G42: =G37 | H42: =H37 | I42: =I37
A43: less: D&A (leasing book + Aerospace capex base) | B43: =Historical!$B$21 | C43: =Historical!$C$21 | D43: =Historical!$D$21 | E43: =SUM(Quarterly!B43:E43) | F43: =SUM(Quarterly!F43:I43) | G43: =G23+G44 | H43: =H23+H44 | I43: =I23+I44
A44: memo: other (non-leasing) D&A | F44: =SUM(Quarterly!F44:I44) | G44: =F44+G45/Drivers!$D$130 | H44: =G44+H45/Drivers!$D$130 | I44: =H44+I45/Drivers!$D$130
A45: memo: PP&E capex | E45: =SUM(Quarterly!B45:E45) | F45: =SUM(Quarterly!F45:I45) | G45: =Drivers!J$131 | H45: =Drivers!K$131 | I45: =Drivers!L$131
A46: less: interest expense (debt schedule) | B46: =Historical!$B$22 | C46: =Historical!$C$22 | D46: =Historical!$D$22 | E46: =SUM(Quarterly!B46:E46) | F46: =SUM(Quarterly!F46:I46) | G46: =(Drivers!$D$150-Drivers!$D$145*Drivers!$E$145)+Drivers!$D$145*(Drivers!$E$145*Drivers!$D$143+Drivers!$D$142*(Drivers!$D$21-Drivers!$D$143))/Drivers!$D$21+Drivers!$D$151*Drivers!$D$18+F83*Drivers!$D$141 | H46: =(Drivers!$D$150-Drivers!$D$145*Drivers!$E$145)+Drivers!$D$145*Drivers!$D$142+Drivers!$D$151*Drivers!$D$18+G83*Drivers!$D$141 | I46: =(Drivers!$D$150-Drivers!$D$145*Drivers!$E$145)+Drivers!$D$145*Drivers!$D$142+Drivers!$D$151*Drivers!$D$18+H83*Drivers!$D$141 | J46: FY28: 2028 notes ($1.0B, 5.5%) mature 5/1/28 and are refinanced at the refi coupon
A47: less: EBITDA-to-pretax adjustments (SCI/Power pro-rata not in pretax, SBC, other) | D47: =D48-(D37-D43-D46) | E47: =SUM(Quarterly!B47:E47) | F47: =SUM(Quarterly!F47:I47) | G47: =-(G30*(1-Drivers!$D$153)+Drivers!$D$154*Drivers!$D$18+(1-Drivers!$D$80)*G18) | H47: =-(H30*(1-Drivers!$D$153)+Drivers!$D$154*Drivers!$D$18+(1-Drivers!$D$80)*H18) | I47: =-(I30*(1-Drivers!$D$153)+Drivers!$D$154*Drivers!$D$18+(1-Drivers!$D$80)*I18)
A48: Pre-tax income | D48: =Historical!$D$25 | E48: =SUM(Quarterly!B48:E48) | F48: =SUM(Quarterly!F48:I48) | G48: =G37-G43-G46+G47 | H48: =H37-H43-H46+H47 | I48: =I37-I43-I46+I47 | J48: History FY23/FY24 not parsed
A49: Income taxes | D49: =Historical!$D$26 | E49: =SUM(Quarterly!B49:E49) | F49: =SUM(Quarterly!F49:I49) | G49: =G48*Drivers!$D$133 | H49: =H48*Drivers!$D$133 | I49: =I48*Drivers!$D$133
A50: Net income | D50: =Historical!$D$27 | E50: =SUM(Quarterly!B50:E50) | F50: =SUM(Quarterly!F50:I50) | G50: =G48-G49 | H50: =H48-H49 | I50: =I48-I49
A51: less: preferred dividends and NCI | D51: =Historical!$D$29 | E51: =SUM(Quarterly!B51:E51) | F51: =SUM(Quarterly!F51:I51) | G51: =Drivers!$D$134*Drivers!$D$18 | H51: =Drivers!$D$134*Drivers!$D$18 | I51: =Drivers!$D$134*Drivers!$D$18
A52: Net income attributable to common | B52: =Historical!$B$28 | C52: =Historical!$C$28 | D52: =Historical!$D$28 | E52: =SUM(Quarterly!B52:E52) | F52: =SUM(Quarterly!F52:I52) | G52: =G50-G51 | H52: =H50-H51 | I52: =I50-I51
A53: Diluted shares (M) | B53: =Historical!$B$31 | C53: =Historical!$C$31 | D53: =Historical!$D$31 | E53: =AVERAGE(Quarterly!B53:E53) | F53: =AVERAGE(Quarterly!F53:I53) | G53: =Quarterly!I53 | H53: =G53 | I53: =H53
A54: Diluted EPS ($) | B54: =Historical!$B$30 | C54: =Historical!$C$30 | D54: =Historical!$D$30 | E54: =E52/E53 | F54: =F52/F53 | G54: =G52/G53 | H54: =H52/H53 | I54: =I52/I53
A55: CASH FLOW BUILD (CFO + CFI, GAAP classification combined)
A56: Total Adjusted EBITDA | E56: =SUM(Quarterly!B56:E56) | F56: =SUM(Quarterly!F56:I56) | G56: =G37 | H56: =H37 | I56: =I37
A57: less: gains in EBITDA (proceeds sit in CFI) | E57: =SUM(Quarterly!B57:E57) | F57: =SUM(Quarterly!F57:I57) | G57: =-G27 | H57: =-H27 | I57: =-I27
A58: less: pro-rata SCI EBITDA (non-cash) | E58: =SUM(Quarterly!B58:E58) | F58: =SUM(Quarterly!F58:I58) | G58: =-G30 | H58: =-H30 | I58: =-I30
A59: plus: SCI cash distributions (return of capital) | E59: =SUM(Quarterly!B59:E59) | F59: =SUM(Quarterly!F59:I59) | G59: =Drivers!$D$119*G30 | H59: =Drivers!$D$119*H30 | I59: =Drivers!$D$119*I30
A60: less: Power EBITDA not converted to cash | E60: =SUM(Quarterly!B60:E60) | F60: =SUM(Quarterly!F60:I60) | G60: =-(1-Drivers!$D$79)*G18 | H60: =-(1-Drivers!$D$79)*H18 | I60: =-(1-Drivers!$D$79)*I18
A61: less: cash interest | E61: =SUM(Quarterly!B61:E61) | F61: =SUM(Quarterly!F61:I61) | G61: =-G46 | H61: =-H46 | I61: =-I46
A62: less: cash taxes (= book taxes) | E62: =SUM(Quarterly!B62:E62) | F62: =SUM(Quarterly!F62:I62) | G62: =-G49 | H62: =-H49 | I62: =-I49
A63: less: increase in Aerospace inventory [KEY #2] | E63: =SUM(Quarterly!B63:E63) | F63: =SUM(Quarterly!F63:I63) | G63: =-(G86-F86) | H63: =-(H86-G86) | I63: =-(I86-H86)
A64: less: Power turbine working-capital investment (next quarter's units) | E64: =SUM(Quarterly!B64:E64) | F64: =SUM(Quarterly!F64:I64) | G64: =-Drivers!$D$78*H16 | H64: =-Drivers!$D$78*I16 | I64: =-Drivers!$D$78*I16
A65: plus: Power working-capital release on delivery | E65: =SUM(Quarterly!B65:E65) | F65: =SUM(Quarterly!F65:I65) | G65: =Drivers!$D$78*G16 | H65: =Drivers!$D$78*H16 | I65: =Drivers!$D$78*I16
A66: plus: leasing book sold (at book value; gain already in EBITDA) | E66: =SUM(Quarterly!B66:E66) | F66: =SUM(Quarterly!F66:I66) | G66: =G22 | H66: =H22 | I66: =I22
A67: less: leasing equipment acquisitions | E67: =SUM(Quarterly!B67:E67) | F67: =SUM(Quarterly!F67:I67) | G67: =-G24 | H67: =-H24 | I67: =-I24
A68: less: SCI co-investment | E68: =SUM(Quarterly!B68:E68) | F68: =SUM(Quarterly!F68:I68) | G68: =-Drivers!$D$120*(G28-F28) | H68: =-Drivers!$D$120*(H28-G28) | I68: =-Drivers!$D$120*(I28-H28)
A69: less: PP&E capex | E69: =SUM(Quarterly!B69:E69) | F69: =SUM(Quarterly!F69:I69) | G69: =-G45 | H69: =-H45 | I69: =-I45
A70: plus: insurance proceeds | E70: =SUM(Quarterly!B70:E70) | F70: =SUM(Quarterly!F70:I70)
A71: CFO + CFI (GAAP basis, model) | B71: =Historical!$B$50 | C71: =Historical!$C$50 | D71: =Historical!$D$50 | E71: =SUM(Quarterly!B71:E71) | F71: =SUM(Quarterly!F71:I71) | G71: =SUM(G56:G70) | H71: =SUM(H56:H70) | I71: =SUM(I56:I70) | J71: History: reported CFO + CFI. Projection: model build (no financing lines)
A72: memo: seed-sale proceeds to SCI (one-off) | B72: =Historical!$B$52 | C72: =Historical!$C$52 | D72: =Historical!$D$52 | E72: =SUM(Quarterly!B72:E72) | F72: =SUM(Quarterly!F72:I72) | G72: =Drivers!$D$121*G22*(1+Drivers!$D$90) | H72: =Drivers!$D$121*H22*(1+Drivers!$D$90) | I72: =Drivers!$D$121*I22*(1+Drivers!$D$90)
A73: memo: insurance proceeds (one-off) | B73: =Historical!$B$53 | C73: =Historical!$C$53 | D73: =Historical!$D$53 | E73: =SUM(Quarterly!B73:E73) | F73: =SUM(Quarterly!F73:I73)
A74: Clean CFO + CFI (excl. seed-sale and insurance proceeds) | B74: =B71-N(B72)-N(B73) | C74: =C71-N(C72)-N(C73) | D74: =D71-N(D72)-N(D73) | E74: =SUM(Quarterly!B74:E74) | F74: =SUM(Quarterly!F74:I74) | G74: =G71-N(G72)-N(G73) | H74: =H71-N(H72)-N(H73) | I74: =I71-N(I72)-N(I73)
A75: Company-defined Adjusted FCF (adds back SCI co-invest, NET Power turbine investment, hot-section parts) | D75: =Historical!$D$60 | E75: =SUM(Quarterly!B75:E75) | F75: =SUM(Quarterly!F75:I75) | G75: =G71-G68+MAX(0,-(G64+G65))+Drivers!$D$177*Drivers!$D$18 | H75: =H71-H68+MAX(0,-(H64+H65))+Drivers!$D$177*Drivers!$D$18 | I75: =I71-I68+MAX(0,-(I64+I65))+Drivers!$D$177*Drivers!$D$18 | J75: FY25 reported 724 vs CFO+CFI 412.6 (see FCF_Quality). FY26 = model (1H26 reported 255 + 2H26 model: see FCF_Quality)
A76: FINANCING AND BALANCE SHEET ITEMS
A77: Common dividends | E77: =SUM(Quarterly!B77:E77) | F77: =SUM(Quarterly!F77:I77) | G77: =-Drivers!$D$139*Drivers!$D$18*G53 | H77: =-Drivers!$D$139*Drivers!$D$18*H53 | I77: =-Drivers!$D$139*Drivers!$D$18*I53
A78: Preferred dividends and NCI (cash) | E78: =SUM(Quarterly!B78:E78) | F78: =SUM(Quarterly!F78:I78) | G78: =-G51 | H78: =-H51 | I78: =-I51
A79: Share buybacks (toggle) | E79: =SUM(Quarterly!B79:E79) | F79: =SUM(Quarterly!F79:I79)
A80: Cash before revolver | E80: =Quarterly!E80 | F80: =Quarterly!I80 | G80: =F82+G71+G77+G78 | H80: =G82+H71+H77+H78 | I80: =H82+I71+I77+I78
A81: Revolver draw / (repayment) | E81: =SUM(Quarterly!B81:E81) | F81: =SUM(Quarterly!F81:I81) | G81: =MAX(-F83,Drivers!$D$140-G80) | H81: =MAX(-G83,Drivers!$D$140-H80) | I81: =MAX(-H83,Drivers!$D$140-I80)
A82: Cash, end | B82: =Historical!$B$62 | C82: =Historical!$C$62 | D82: =Historical!$D$62 | E82: =Quarterly!E82 | F82: =Quarterly!I82 | G82: =G80+G81 | H82: =H80+H81 | I82: =I80+I81
A83: Revolver balance, end | E83: =Quarterly!E83 | F83: =Quarterly!I83 | G83: =F83+G81 | H83: =G83+H81 | I83: =H83+I81
A84: Senior notes (carrying, before issuance costs) | B84: =Historical!$B$68 | C84: =Historical!$C$68 | D84: =Historical!$D$68 | E84: =Quarterly!E84 | F84: =Quarterly!I84 | G84: =F84 | H84: =G84 | I84: =H84
A85: Net debt | B85: =B84-B82 | C85: =C84-C82 | D85: =D84-D82 | E85: =Quarterly!E85 | F85: =Quarterly!I85 | G85: =G84+G83-G82 | H85: =H84+H83-H82 | I85: =I84+I83-I82
A86: Inventory, end | B86: =Historical!$B$63 | C86: =Historical!$C$63 | D86: =Historical!$D$63 | E86: =Quarterly!E86 | F86: =Quarterly!I86 | G86: =G87*G14/Drivers!$D$20 | H86: =H87*H14/Drivers!$D$20 | I86: =I87*I14/Drivers!$D$20
A87: Inventory days (Aerospace cost-of-sales basis) | B87: =B86/B14*Drivers!$D$20 | C87: =C86/C14*Drivers!$D$20 | D87: =D86/D14*Drivers!$D$20 | E87: =E86/E14*Drivers!$D$20 | F87: =F86/F14*Drivers!$D$20 | G87: =F87+Drivers!J$175 | H87: =G87+Drivers!K$175 | I87: =H87+Drivers!L$175

Sheet FCF_Quality
A1: FCF quality: the thesis tab (three ways to count cash)
A2: (a) company 'Adjusted FCF'; (b) GAAP CFO + CFI; (c) clean CFO + CFI excluding seed-sale proceeds and insurance recoveries. Projection columns follow the selected scenario.
A4: USD m | B4: FY2023A | C4: FY2024A | D4: FY2025A | E4: FY2026E | F4: FY2027E | G4: FY2028E | H4: FY2029E | I4: FY2030E | J4: Notes
A5: Three definitions by year
A6: Reported CFO (history) / n.a. in projections (model builds CFO + CFI combined) | B6: =Historical!$B$48 | C6: =Historical!$C$48 | D6: =Historical!$D$48
A7: Reported CFI (history) | B7: =Historical!$B$49 | C7: =Historical!$C$49 | D7: =Historical!$D$49
A8: (b) GAAP CFO + CFI | B8: =Annual!B71 | C8: =Annual!C71 | D8: =Annual!D71 | E8: =Annual!E71 | F8: =Annual!F71 | G8: =Annual!G71 | H8: =Annual!H71 | I8: =Annual!I71 | J8: FY25 CFO -310.7 and CFI +723.3 tie to filings
A9: less: seed-sale proceeds to 2025 Partnership / SCI | B9: =-N(Annual!B72) | C9: =-N(Annual!C72) | D9: =-N(Annual!D72) | E9: =-N(Annual!E72) | F9: =-N(Annual!F72) | G9: =-N(Annual!G72) | H9: =-N(Annual!H72) | I9: =-N(Annual!I72)
A10: less: insurance proceeds (Russia) | B10: =-N(Annual!B73) | C10: =-N(Annual!C73) | D10: =-N(Annual!D73) | E10: =-N(Annual!E73) | F10: =-N(Annual!F73) | G10: =-N(Annual!G73) | H10: =-N(Annual!H73) | I10: =-N(Annual!I73)
A11: (c) Clean CFO + CFI | B11: =B8+B9+B10 | C11: =C8+C9+C10 | D11: =D8+D9+D10 | E11: =E8+E9+E10 | F11: =F8+F9+F10 | G11: =G8+G9+G10 | H11: =H8+H9+H10 | I11: =I8+I9+I10
A12: (a) Company-defined Adjusted FCF | D12: =Annual!D75 | E12: =Annual!E75 | F12: =Annual!F75 | G12: =Annual!G75 | H12: =Annual!H75 | I12: =Annual!I75 | J12: FY25 724 reported (call). FY26 = 1H26 reported 255 + 2H26 model on FY25-style add-backs
A13: Gap: (a) less (b) = add-backs of growth investment | D13: =D12-D8 | E13: =E12-E8 | F13: =F12-F8 | G13: =G12-G8 | H13: =H12-H8 | I13: =I12-I8
A14: Gap: (a) less (c) | D14: =D12-D11 | E14: =E12-E11 | F14: =F12-F11 | G14: =G12-G11 | H14: =H12-H11 | I14: =I12-I11
A15: Total Adjusted EBITDA (company basis) | B15: =Annual!B37 | C15: =Annual!C37 | D15: =Annual!D37 | E15: =Annual!E37 | F15: =Annual!F37 | G15: =Annual!G37 | H15: =Annual!H37 | I15: =Annual!I37
A16: (b) / Adjusted EBITDA | B16: =B8/B15 | C16: =C8/C15 | D16: =D8/D15 | E16: =E8/E15 | F16: =F8/F15 | G16: =G8/G15 | H16: =H8/H15 | I16: =I8/I15
A17: (c) / Adjusted EBITDA | B17: =B11/B15 | C17: =C11/C15 | D17: =D11/D15 | E17: =E11/E15 | F17: =F11/F15 | G17: =G11/G15 | H17: =H11/H15 | I17: =I11/I15
A18: (a) / Adjusted EBITDA | D18: =D12/D15 | E18: =E12/E15 | F18: =F12/F15 | G18: =G12/G15 | H18: =H12/H15 | I18: =I12/I15
A19: (a) yield on market cap | D19: =D12/Drivers!$D$182 | E19: =E12/Drivers!$D$182 | F19: =F12/Drivers!$D$182 | G19: =G12/Drivers!$D$182 | H19: =H12/Drivers!$D$182 | I19: =I12/Drivers!$D$182 | J19: Management guide 878 / market cap 18,430 = 4.8% (vs peers 2.4-3.3%)
A20: (c) yield on market cap | B20: =B11/Drivers!$D$182 | C20: =C11/Drivers!$D$182 | D20: =D11/Drivers!$D$182 | E20: =E11/Drivers!$D$182 | F20: =F11/Drivers!$D$182 | G20: =G11/Drivers!$D$182 | H20: =H11/Drivers!$D$182 | I20: =I11/Drivers!$D$182
A22: SCI: pro-rata EBITDA counted in Adj. EBITDA vs cash actually distributed
A23: Pro-rata SCI EBITDA and co-invest returns (non-cash) | E23: =Annual!E30 | F23: =Annual!F30 | G23: =Annual!G30 | H23: =Annual!H30 | I23: =Annual!I30 | J23: FY26 includes 1H26 assumed 28.0/qtr (call 35 less 7.0 fees)
A24: Cash distributions from SCI (return of capital, CFI) | D24: =Historical!$D$57 | E24: =Historical!$M$57+Historical!$N$57+SUM(Quarterly!D59:E59) | F24: =Annual!F59 | G24: =Annual!G59 | H24: =Annual!H59 | I24: =Annual!I59 | J24: FY25 27.1 'return of capital' (carried from prior research). Pro-rata EBITDA for FY25 not disclosed by component
A25: Gap: EBITDA counted but not received in cash | E25: =E23-E24 | F25: =F23-F24 | G25: =G23-G24 | H25: =H23-H24 | I25: =I23-I24
A26: Cash distributions as % of pro-rata EBITDA | E26: =E24/E23 | F26: =F24/F23 | G26: =G24/G23 | H26: =H24/H23 | I26: =I24/I23
A28: FY25 reconciliation: $724M Adjusted FCF to $412.6M CFO + CFI
A29: Company Adjusted FCF, FY25 | B29: =Historical!$D$60 | J29: Q4-25 call (Motley Fool transcript 2026-02-26), secondary
A30: less: GAAP CFO + CFI | B30: =-Historical!$D$50 | J30: CFO -310.7 + CFI +723.3 (10-K FY25)
A31: Gap to explain | B31: =B29+B30
A32: named by CFO: increase in SCI co-investment | B32: 52 | J32: Q4-25 call: 'further adjusted for 3 key investments'
A33: named by CFO: Power turbines | B33: 150 | J33: Q4-25 call
A34: named by CFO: hot-section parts | B34: 50 | J34: Q4-25 call
A35: subtotal named by the CFO | B35: =SUM(B32:B34)
A36: residual: INFERRED (probably acquisitions 49.1 + ~10 JV item), NOT CONFIRMED | B36: =B31-B35
A37: of the gap, inventory-type purchases (Power turbines + hot-section parts) | B37: =B33+B34 | J37: ~$200M of the add-backs are the same inventory-type items that drive negative GAAP CFO
A39: 1H26: what cash looks like without the one-offs
A40: 1H26 CFO | B40: =Historical!$M$48+Historical!$N$48 | J40: -160.1 + -105.2 = -265.3
A41: 1H26 CFI | B41: =Historical!$M$49+Historical!$N$49 | J41: 317.0 + 198.7 = 515.7
A42: 1H26 CFO + CFI | B42: =B40+B41 | J42: 250.4
A43: less: seed-sale proceeds (15 aircraft to 2025 Partnership) | B43: =-(Historical!$M$52+Historical!$N$52) | J43: 175.7; 10-Q: sales 'non-recurring in nature'
A44: less: Russia insurance proceeds | B44: =-(Historical!$M$53+Historical!$N$53) | J44: 48.3 (CFI proceeds, not the CFO gain add-back of 49.5)
A45: 1H26 clean CFO + CFI | B45: =B42+B43+B44 | J45: ~26.4, AFTER the inventory build below
A46: memo: inventory build 1H26 (balance sheet) | B46: =Historical!$N$63-Historical!$L$63 | J46: 1,544.6 - 1,193.8 = 350.8. Includes 63 engines transferred in from leasing (non-cash)
A47: Company-reported Adjusted FCF, 1H26 | B47: 255 | J47: Q2-26 call (secondary): 255; Q1 158
A48: Adjusted FCF less CFO + CFI in 1H26 (add-backs actually applied) | B48: =B47-B42 | J48: Only ~4.6 in 1H26 despite ~99 of SCI investment: the add-back definition is NOT consistent with FY25's
A49: FY26 Adjusted FCF guide (cut from 915 on 7/29/26) | B49: 878 | J49: Q2-26 call (secondary)
A50: 2H26 Adjusted FCF required to hit the guide | B50: =B49-B47 | J50: ~623
A51: Q2'26 Adjusted FCF run-rate x 2 | B51: =Drivers!$D$22*Historical!$N$60 | J51: ~194: the guide needs ~3.2x the Q2 run-rate
A52: Required / run-rate | B52: =B50/B51
A53: Model 2H26: company-defined Adjusted FCF (FY25-style add-backs) [selected scenario] | B53: =SUM(Quarterly!D75:E75) | J53: Back-solved to hit 878 in the Mgmt Guide scenario via KEY #2 (inventory conversion)
A54: Model 2H26: GAAP CFO + CFI [selected scenario] | B54: =SUM(Quarterly!D71:E71) | J54: Compare with the 623 required: on the narrow 1H26-style definition (add-backs ~5) the guide needs ~619-623 of GAAP CFO + CFI in 2H
A55: Model 2H26: clean CFO + CFI [selected scenario] | B55: =SUM(Quarterly!D74:E74)
A56: 2H26 GAAP CFO + CFI required if add-backs stay at the 1H26 level | B56: =B49-B48-B42 | J56: Narrow basis: 878 less 4.6 less 250.4 = ~623

Sheet Valuation
A1: Valuation: SOTP, P/E cross-check, DCF, blended price target
A2: SOTP is live for all four scenarios (Leasing at book). P/E, DCF and blended are live for the SELECTED scenario; the snapshot block stores all four (regenerated by build_model.py).
A4: 1. Market data and equity bridge
A5: Share price 10/6/26 ($) | B5: =Drivers!$D$180
A6: Shares (M) | B6: =Drivers!$D$181
A7: Market cap (stockanalysis) | B7: =Drivers!$D$182
A8: Enterprise value (stockanalysis) | B8: =Drivers!$D$183
A9: Net debt per stockanalysis (EV - market cap) | B9: =Drivers!$D$184
A10: Net debt per balance sheet 6/30/26 (debt 3,496.4 - cash 337.2) | B10: =Drivers!$D$185 | G10: Used in all bridges
A11: Reconciliation difference | B11: =B10-B9 | G11: Within ~1: stockanalysis uses face debt 3,500
A12: Preferred at liquidation (deducted) | B12: =Drivers!$D$187*Drivers!$D$186
A13: Leasing book: equipment net 1,146.4 + SCI I stake 365.5 | B13: =Drivers!$D$188
A15: 2. Sum-of-the-parts on 2027E (TTM peer multiples applied to 2027E: 2027 is the trailing year at a 12-month horizon)
A16: USD m | B16: Bear | C16: Base | D16: Bull | E16: Mgmt Guide | F16: Selected | G16: Notes
A17: 2027E Aerospace EBITDA | B17: =Drivers!$D$263 | C17: =Drivers!$E$263 | D17: =Drivers!$F$263 | E17: =Drivers!$G$263 | F17: =INDEX(B17:E17,Drivers!$E$4)
A18: x multiple | B18: =Drivers!D$190 | C18: =Drivers!D$191 | D18: =Drivers!D$192 | E18: =Drivers!D$193 | F18: =INDEX(B18:E18,Drivers!$E$4)
A19: Aerospace EV | B19: =B17*B18 | C19: =C17*C18 | D19: =D17*D18 | E19: =E17*E18 | F19: =INDEX(B19:E19,Drivers!$E$4)
A20: 2027E Power EBITDA (pro-rata) | B20: =Drivers!$D$264 | C20: =Drivers!$E$264 | D20: =Drivers!$F$264 | E20: =Drivers!$G$264 | F20: =INDEX(B20:E20,Drivers!$E$4)
A21: x multiple | B21: =Drivers!D$197 | C21: =Drivers!D$198 | D21: =Drivers!D$199 | E21: =Drivers!D$200 | F21: =INDEX(B21:E21,Drivers!$E$4)
A22: Power EV | B22: =B20*B21 | C22: =C20*C21 | D22: =D20*D21 | E22: =E20*E21 | F22: =INDEX(B22:E22,Drivers!$E$4)
A23: Leasing book value | B23: =Drivers!$D$188 | C23: =Drivers!$D$188 | D23: =Drivers!$D$188 | E23: =Drivers!$D$188 | F23: =INDEX(B23:E23,Drivers!$E$4)
A24: x book multiple | B24: =Drivers!D$204 | C24: =Drivers!D$205 | D24: =Drivers!D$206 | E24: =Drivers!D$207 | F24: =INDEX(B24:E24,Drivers!$E$4) | G24: Leasing valued at book because the book is being sold down and EBITDA is gain-heavy
A25: Leasing value | B25: =B23*B24 | C25: =C23*C24 | D25: =D23*D24 | E25: =E23*E24 | F25: =INDEX(B25:E25,Drivers!$E$4)
A26: Corporate costs capitalised (2027E x blended multiple) | B26: =Drivers!$D$210*SUM(Drivers!F$125:I$125)*B35 | C26: =Drivers!$D$210*SUM(Drivers!F$125:I$125)*C35 | D26: =Drivers!$D$210*SUM(Drivers!F$125:I$125)*D35 | E26: =Drivers!$D$210*SUM(Drivers!F$125:I$125)*E35 | F26: =INDEX(B26:E26,Drivers!$E$4) | G26: 2027E corporate costs x blended Aero+Power multiple (memo row below)
A27: Enterprise value | B27: =B19+B22+B25+B26 | C27: =C19+C22+C25+C26 | D27: =D19+D22+D25+D26 | E27: =E19+E22+E25+E26 | F27: =INDEX(B27:E27,Drivers!$E$4)
A28: less: net debt | B28: =-Drivers!$D$185 | C28: =-Drivers!$D$185 | D28: =-Drivers!$D$185 | E28: =-Drivers!$D$185 | F28: =INDEX(B28:E28,Drivers!$E$4)
A29: less: preferred | B29: =-Drivers!$D$187*Drivers!$D$186 | C29: =-Drivers!$D$187*Drivers!$D$186 | D29: =-Drivers!$D$187*Drivers!$D$186 | E29: =-Drivers!$D$187*Drivers!$D$186 | F29: =INDEX(B29:E29,Drivers!$E$4)
A30: Equity value | B30: =B27+B28+B29 | C30: =C27+C28+C29 | D30: =D27+D28+D29 | E30: =E27+E28+E29 | F30: =INDEX(B30:E30,Drivers!$E$4)
A31: SOTP value per share ($) | B31: =B30/Drivers!$D$181 | C31: =C30/Drivers!$D$181 | D31: =D30/Drivers!$D$181 | E31: =E30/Drivers!$D$181 | F31: =INDEX(B31:E31,Drivers!$E$4)
A32: Spec / thesis target ($) | B32: 115 | C32: 172 | D32: 280 | G32: thesis.md section 2 (Bear ~115, Base ~172, Bull ~280); thesis excludes preferred and uses book ~1.5B
A33: Difference vs target ($) | B33: =B36-B32 | C33: =C36-C32 | D33: =D36-D32
A34: Upside vs current price | B34: =B31/Drivers!$D$180-1 | C34: =C31/Drivers!$D$180-1 | D34: =D31/Drivers!$D$180-1 | E34: =E31/Drivers!$D$180-1 | F34: =INDEX(B34:E34,Drivers!$E$4)
A35: Memo: blended Aero+Power multiple | B35: =(B19+B22)/(B17+B20) | C35: =(C19+C22)/(C17+C20) | D35: =(D19+D22)/(D17+D20) | E35: =(E19+E22)/(E17+E20)
A36: Memo: SOTP value/share EXCLUDING corporate costs (ties to thesis.md v0.2 targets) ($) | B36: =B31-B26/Drivers!$D$181 | C36: =C31-C26/Drivers!$D$181 | D36: =D31-D26/Drivers!$D$181 | E36: =E31-E26/Drivers!$D$181 | G36: Headline SOTP includes corporate costs. This memo excludes them, for comparison with the thesis.md v0.2 targets
A38: 3. Forward P/E cross-check (selected scenario)
A39: Model FY2027E diluted EPS ($) | B39: =Annual!F54
A40: at low P/E | B40: =B39*Drivers!$D$211
A41: at midpoint P/E | B41: =B39*AVERAGE(Drivers!$D$211,Drivers!$D$212)
A42: at high P/E | B42: =B39*Drivers!$D$212
A43: Consensus FY2027E EPS implied (price / 20.2x) ($) | B43: =Drivers!$D$214 | G43: CAVEAT: stockanalysis forward P/E 20.2x conflicts with its own FY26 EPS (30.8x); the $8.87 is an implied, not published, figure
A44: consensus at low P/E ($) | B44: =B43*Drivers!$D$211
A45: consensus at high P/E ($) | B45: =B43*Drivers!$D$212
A46: Model EPS vs consensus-implied | B46: =B39/B43-1
A48: 4. DCF on clean FCF (selected scenario). Valuation date 6/30/26 balance sheet; mid-period discounting
A49: USD m | B49: 2H FY2026E | C49: FY2027E | D49: FY2028E | E49: FY2029E | F49: FY2030E | G49: Terminal
A50: Clean CFO + CFI (after interest) | B50: =SUM(Quarterly!D74:E74) | C50: =Annual!F74 | D50: =Annual!G74 | E50: =Annual!H74 | F50: =Annual!I74
A51: plus: interest expense | B51: =SUM(Quarterly!D46:E46) | C51: =Annual!F46 | D51: =Annual!G46 | E51: =Annual!H46 | F51: =Annual!I46
A52: plus: after-tax interest add-back = interest x (1 - tax) | B52: =B51*(1-Drivers!$D$133) | C52: =C51*(1-Drivers!$D$133) | D52: =D51*(1-Drivers!$D$133) | E52: =E51*(1-Drivers!$D$133) | F52: =F51*(1-Drivers!$D$133)
A53: Unlevered clean FCF | B53: =B50+B52 | C53: =C50+C52 | D53: =D50+D52 | E53: =E50+E52 | F53: =F50+F52 | G53: =G54*(1+Drivers!$D$217)/(Drivers!$D$216-Drivers!$D$217) | H53: Terminal value = normalised FCF x (1+g) / (WACC - g)
A54: Terminal normalisation (see note) | G54: =F53-Annual!I63-Annual!I64-Annual!I65-Drivers!$D$217*Annual!I86 | H54: Fixed before viewing output: terminal FCF = FY30 unlevered FCF with the FY30 inventory change replaced by a growth-consistent build (g x inventory) and Power WC net set to zero (flat units)
A55: Discount period (years from 6/30/26, mid-period) | B55: 0.25 | C55: 1 | D55: 2 | E55: 3 | F55: 4 | G55: 4.5 | H55: ASSUMPTION: 2H26 cash mid-point 0.25y; FY27 mid-year 1.0y ... FY30 4.0y; terminal at end FY30 (4.5y)
A56: Discount factor | B56: =1/(1+Drivers!$D$216)^B55 | C56: =1/(1+Drivers!$D$216)^C55 | D56: =1/(1+Drivers!$D$216)^D55 | E56: =1/(1+Drivers!$D$216)^E55 | F56: =1/(1+Drivers!$D$216)^F55 | G56: =1/(1+Drivers!$D$216)^G55
A57: Present value | B57: =B53*B56 | C57: =C53*C56 | D57: =D53*D56 | E57: =E53*E56 | F57: =F53*F56 | G57: =G53*G56
A59: DCF enterprise value | B59: =SUM(B57:G57)
A60: terminal value share of EV | B60: =G57/B59
A61: less: net debt (6/30/26) | B61: =-Drivers!$D$185
A62: less: preferred | B62: =-Drivers!$D$187*Drivers!$D$186
A63: DCF equity value | B63: =B59+B61+B62
A64: DCF value per share ($) | B64: =B63/Drivers!$D$181
A66: 5. Blended price target (selected scenario)
A67: Method | B67: Value / share | C67: Weight | D67: Contribution
A68: SOTP | B68: =F31 | C68: =Drivers!$D$218 | D68: =B68*C68
A69: P/E at midpoint multiple | B69: =B41 | C69: =Drivers!$D$219 | D69: =B69*C69
A70: DCF | B70: =B64 | C70: =Drivers!$D$220 | D70: =B70*C70
A71: Blended value per share ($) | C71: =SUM(C68:C70) | D71: =SUM(D68:D70)/C71
A72: Upside / (downside) vs current price | D72: =D71/Drivers!$D$180-1
A74: 6. Peer table (stockanalysis, 10/6/26)
A75: Company | B75: EV/EBITDA TTM | C75: Forward P/E | D75: FCF yield
A76: HEICO | B76: 30.2 | C76: 44 | D76: 0.024 | G76: Source: stockanalysis.com per thesis.md section 2 (10/6/26)
A77: AAR | B77: 13.8 | C77: 17.7 | D77: 0.033
A78: StandardAero | B78: 11.7 | C78: 15.9 | D78: 0.032
A79: AerSale | B79: 17.4 | C79: 18.1 | D79: -0.167
A80: AerCap | B80: 12.4 | C80: 8.5 | D80: -0.014
A81: FTAI (at $179.44) | B81: 21.7 | C81: 20.2
A83: 7. Scenario snapshot: all four scenarios (static values regenerated by build_model.py from four full recalculations)
A84: Output | B84: Bear | C84: Base | D84: Bull | E84: Mgmt Guide | G84: Notes
A85: FY26E segment-basis EBITDA ($M) | B85: 1321.471 | C85: 1406.4832 | D85: 1502.9329 | E85: 1525.0609 | G85: STATIC: re-run `python -I build_model.py` after changing any driver
A86: FY27E segment-basis EBITDA ($M) | B86: 1470.0041 | C86: 1920.027 | D86: 2480.0576 | E86: 2299.9676
A87: FY27E total Adj. EBITDA, company basis ($M) | B87: 1273.891 | C87: 1719.9013 | D87: 2274.5818 | E87: 2094.4918
A88: FY26E diluted EPS ($) | B88: 4.07 | C88: 4.6769 | D88: 5.1544 | E88: 5.2042
A89: FY27E diluted EPS ($) | B89: 5.0678 | C89: 7.8776 | D89: 11.2388 | E89: 10.115
A90: SOTP value per share ($) | B90: 97.1183 | C90: 151.8763 | D90: 256.0592 | E90: 185.2184
A91: P/E value per share, midpoint multiple ($) | B91: 86.1525 | C91: 133.9184 | D91: 191.0597 | E91: 171.9553
A92: DCF value per share ($) | B92: 86.5062 | C92: 143.4111 | D92: 199.9359 | E92: 190.779
A93: Blended value per share ($) | B93: 90.6449 | C93: 143.9494 | D93: 219.7224 | E93: 182.9077
A94: FY26E company-defined Adjusted FCF ($M) | B94: 647.0842 | C94: 752.8476 | D94: 852.3806 | E94: 878.0155
A95: FY26E clean CFO + CFI ($M) | B95: 286.4052 | C95: 242.6686 | D95: 178.4016 | E95: 274.0365
A96: FY27E clean CFO + CFI ($M) | B96: 156.6579 | C96: 362.9396 | D96: 532.1083 | E96: 296.5053
A97: Scenario probability weight (input on Drivers) | B97: =Drivers!D$222 | C97: =Drivers!D$223 | D97: =Drivers!D$224 | E97: =Drivers!D$225 | F97: =SUM(B97:E97)
A98: Probability-weighted blended value per share ($) | B98: =SUMPRODUCT(B93:E93,B97:E97)/F97
A99: Probability-weighted SOTP (live) ($) | B99: =SUMPRODUCT(B31:E31,B97:E97)/F97
A100: Probability-weighted upside vs current price | B100: =B98/Drivers!$D$180-1
A101: Snapshot freshness: live blended (selected) vs snapshot for the same scenario | B101: =IF(ABS(D71-INDEX(B93:E93,Drivers!$E$4))<0.05,"OK: snapshot current","STALE: re-run build_model.py")

Sheet Bridge
A1: Bridge: Management guide ($2,300M 2027E EBITDA) to our Base case
A2: Live formulas independent of the scenario selector (read the scenario engine and SOTP columns). Leasing is valued at book in the SOTP, so its EBITDA gap lowers EPS and FCF but not SOTP value.
A4: Segment (2027E) | B4: Mgmt Guide EBITDA | C4: Our Base EBITDA | D4: Delta EBITDA | E4: Multiple (Base) | F4: Value impact ($/share) | G4: Notes
A5: Aerospace | B5: =Drivers!$G$263 | C5: =Drivers!$E$263 | D5: =C5-B5 | E5: =Drivers!D$191 | F5: =D5*E5/Drivers!$D$181
A6: Power | B6: =Drivers!$G$264 | C6: =Drivers!$E$264 | D6: =C6-B6 | E6: =Drivers!D$198 | F6: =D6*E6/Drivers!$D$181
A7: Leasing | B7: =Drivers!$G$265 | C7: =Drivers!$E$265 | D7: =C7-B7 | E7: book | F7: 0 | G7: Valued at book: EBITDA gap hits EPS/FCF (see bottom), not SOTP. Guide equals Bull on Leasing
A8: Total 2027E segment EBITDA | B8: =SUM(B5:B7) | C8: =SUM(C5:C7) | D8: =SUM(D5:D7) | F8: =SUM(F5:F7)
A10: Value per share: guide to our Base (SOTP)
A11: SOTP value per share at the Mgmt guide ($) | B11: =Valuation!E31
A12: less: Aerospace EBITDA shortfall impact | B12: =F5
A13: less: Power EBITDA shortfall impact | B13: =F6
A14: less: Leasing EBITDA shortfall impact (valued at book) | B14: =F7
A15: Our Base SOTP value per share ($) | B15: =SUM(B11:B14)
A16: check vs Valuation tab Base SOTP (should be 0) | B16: =B15-Valuation!C31
A18: EBITDA waterfall data (for chart): 2027E segment EBITDA, Mgmt guide to Base
A19: Step | B19: Invisible base | C19: Amount
A20: Mgmt guide | B20: 0 | C20: =B8
A21: Aerospace | B21: =B8+D5 | C21: =-D5
A22: Power | B22: =B8+D5+D6 | C22: =-D6
A23: Leasing | B23: =C8 | C23: =-D7
A24: Our Base | B24: 0 | C24: =C8
A33: From the guide to our numbers (snapshot values, all four scenarios)
A34: Metric | B34: Bear | C34: Base | D34: Bull | E34: Mgmt Guide
A35: FY27E total Adj. EBITDA (company basis) | B35: =Valuation!B87 | C35: =Valuation!C87 | D35: =Valuation!D87 | E35: =Valuation!E87
A36: FY27E diluted EPS ($) | B36: =Valuation!B89 | C36: =Valuation!C89 | D36: =Valuation!D89 | E36: =Valuation!E89
A37: SOTP value per share ($) | B37: =Valuation!B90 | C37: =Valuation!C90 | D37: =Valuation!D90 | E37: =Valuation!E90
A38: P/E value per share ($) | B38: =Valuation!B91 | C38: =Valuation!C91 | D38: =Valuation!D91 | E38: =Valuation!E91
A39: DCF value per share ($) | B39: =Valuation!B92 | C39: =Valuation!C92 | D39: =Valuation!D92 | E39: =Valuation!E92
A40: Blended value per share ($) | B40: =Valuation!B93 | C40: =Valuation!C93 | D40: =Valuation!D93 | E40: =Valuation!E93
A42: Second bridge: Street mean PT (~$330, methodology not public) to our price target (narrative table)
A43: Step | B43: $/share | C43: Explanation
A44: Street mean price target (7 dated post-June PTs) | B44: =Drivers!$D$215 | C44: Mean of 290/300/310/350/360/375/325. All Buy-rated; methodology not public
A45: SOTP at the full 2027 guide (our multiples) | B45: =B11 | C45: What management's $2.3B is worth on our peer-based multiples and book-value Leasing
A46: Street premium to guide-SOTP: not explained by any public methodology | B46: =B45-B44 | C46: Implies a premium multiple, 2028+ growth, or Power/SCI franchise value beyond the 2027 guide. Cannot be reproduced from sourced data
A47: Our haircut: guide to Base EBITDA (Aerospace volume, Power timing, Leasing run-rate) | B47: =B15-B11 | C47: Aerospace 1,500 vs 1,700 modules; Power 44 vs 60 units; Leasing at Q2 run-rate plus partial SCI II
A48: Our Base SOTP | B48: =B15
A49: Our probability-weighted blended value | B49: =Valuation!B98 | C49: SOTP / P/E / DCF blend, weighted over Bear/Base/Bull/Mgmt scenarios
A50: Total gap: Street mean PT to our probability-weighted value | B50: =B49-B44

Sheet Sensitivity
A1: Sensitivity: explicit formula grids (Excel Data Tables are not available from openpyxl)
A2: Grids 1-2 use the Base scenario's other segments and the SOTP bridge. Grid 3 recomputes FY26 clean FCF analytically around the selected scenario. Green = above current price (grids 1-2) / above zero (grid 3); red = below.
A4: Grid 1: SOTP value per share ($): 2027E Aerospace EBITDA (rows) x Aerospace EV/EBITDA multiple (columns); Base Power and Leasing
A5: Aerospace EBITDA ($M) \ multiple | B5: 10 | C5: 11.7 | D5: 13 | E5: 14.5 | F5: 16 | G5: 18
A6: 900 | B6: =($A6*B$5+Drivers!$E$264*Drivers!D$198+Drivers!$D$188*Drivers!D$205-(Drivers!$D$185+Drivers!$D$187*Drivers!$D$186))/Drivers!$D$181 | C6: =($A6*C$5+Drivers!$E$264*Drivers!D$198+Drivers!$D$188*Drivers!D$205-(Drivers!$D$185+Drivers!$D$187*Drivers!$D$186))/Drivers!$D$181 | D6: =($A6*D$5+Drivers!$E$264*Drivers!D$198+Drivers!$D$188*Drivers!D$205-(Drivers!$D$185+Drivers!$D$187*Drivers!$D$186))/Drivers!$D$181 | E6: =($A6*E$5+Drivers!$E$264*Drivers!D$198+Drivers!$D$188*Drivers!D$205-(Drivers!$D$185+Drivers!$D$187*Drivers!$D$186))/Drivers!$D$181 | F6: =($A6*F$5+Drivers!$E$264*Drivers!D$198+Drivers!$D$188*Drivers!D$205-(Drivers!$D$185+Drivers!$D$187*Drivers!$D$186))/Drivers!$D$181 | G6: =($A6*G$5+Drivers!$E$264*Drivers!D$198+Drivers!$D$188*Drivers!D$205-(Drivers!$D$185+Drivers!$D$187*Drivers!$D$186))/Drivers!$D$181
A7: 1050 | B7: =($A7*B$5+Drivers!$E$264*Drivers!D$198+Drivers!$D$188*Drivers!D$205-(Drivers!$D$185+Drivers!$D$187*Drivers!$D$186))/Drivers!$D$181 | C7: =($A7*C$5+Drivers!$E$264*Drivers!D$198+Drivers!$D$188*Drivers!D$205-(Drivers!$D$185+Drivers!$D$187*Drivers!$D$186))/Drivers!$D$181 | D7: =($A7*D$5+Drivers!$E$264*Drivers!D$198+Drivers!$D$188*Drivers!D$205-(Drivers!$D$185+Drivers!$D$187*Drivers!$D$186))/Drivers!$D$181 | E7: =($A7*E$5+Drivers!$E$264*Drivers!D$198+Drivers!$D$188*Drivers!D$205-(Drivers!$D$185+Drivers!$D$187*Drivers!$D$186))/Drivers!$D$181 | F7: =($A7*F$5+Drivers!$E$264*Drivers!D$198+Drivers!$D$188*Drivers!D$205-(Drivers!$D$185+Drivers!$D$187*Drivers!$D$186))/Drivers!$D$181 | G7: =($A7*G$5+Drivers!$E$264*Drivers!D$198+Drivers!$D$188*Drivers!D$205-(Drivers!$D$185+Drivers!$D$187*Drivers!$D$186))/Drivers!$D$181
A8: 1150 | B8: =($A8*B$5+Drivers!$E$264*Drivers!D$198+Drivers!$D$188*Drivers!D$205-(Drivers!$D$185+Drivers!$D$187*Drivers!$D$186))/Drivers!$D$181 | C8: =($A8*C$5+Drivers!$E$264*Drivers!D$198+Drivers!$D$188*Drivers!D$205-(Drivers!$D$185+Drivers!$D$187*Drivers!$D$186))/Drivers!$D$181 | D8: =($A8*D$5+Drivers!$E$264*Drivers!D$198+Drivers!$D$188*Drivers!D$205-(Drivers!$D$185+Drivers!$D$187*Drivers!$D$186))/Drivers!$D$181 | E8: =($A8*E$5+Drivers!$E$264*Drivers!D$198+Drivers!$D$188*Drivers!D$205-(Drivers!$D$185+Drivers!$D$187*Drivers!$D$186))/Drivers!$D$181 | F8: =($A8*F$5+Drivers!$E$264*Drivers!D$198+Drivers!$D$188*Drivers!D$205-(Drivers!$D$185+Drivers!$D$187*Drivers!$D$186))/Drivers!$D$181 | G8: =($A8*G$5+Drivers!$E$264*Drivers!D$198+Drivers!$D$188*Drivers!D$205-(Drivers!$D$185+Drivers!$D$187*Drivers!$D$186))/Drivers!$D$181
A9: 1230 | B9: =($A9*B$5+Drivers!$E$264*Drivers!D$198+Drivers!$D$188*Drivers!D$205-(Drivers!$D$185+Drivers!$D$187*Drivers!$D$186))/Drivers!$D$181 | C9: =($A9*C$5+Drivers!$E$264*Drivers!D$198+Drivers!$D$188*Drivers!D$205-(Drivers!$D$185+Drivers!$D$187*Drivers!$D$186))/Drivers!$D$181 | D9: =($A9*D$5+Drivers!$E$264*Drivers!D$198+Drivers!$D$188*Drivers!D$205-(Drivers!$D$185+Drivers!$D$187*Drivers!$D$186))/Drivers!$D$181 | E9: =($A9*E$5+Drivers!$E$264*Drivers!D$198+Drivers!$D$188*Drivers!D$205-(Drivers!$D$185+Drivers!$D$187*Drivers!$D$186))/Drivers!$D$181 | F9: =($A9*F$5+Drivers!$E$264*Drivers!D$198+Drivers!$D$188*Drivers!D$205-(Drivers!$D$185+Drivers!$D$187*Drivers!$D$186))/Drivers!$D$181 | G9: =($A9*G$5+Drivers!$E$264*Drivers!D$198+Drivers!$D$188*Drivers!D$205-(Drivers!$D$185+Drivers!$D$187*Drivers!$D$186))/Drivers!$D$181
A10: 1300 | B10: =($A10*B$5+Drivers!$E$264*Drivers!D$198+Drivers!$D$188*Drivers!D$205-(Drivers!$D$185+Drivers!$D$187*Drivers!$D$186))/Drivers!$D$181 | C10: =($A10*C$5+Drivers!$E$264*Drivers!D$198+Drivers!$D$188*Drivers!D$205-(Drivers!$D$185+Drivers!$D$187*Drivers!$D$186))/Drivers!$D$181 | D10: =($A10*D$5+Drivers!$E$264*Drivers!D$198+Drivers!$D$188*Drivers!D$205-(Drivers!$D$185+Drivers!$D$187*Drivers!$D$186))/Drivers!$D$181 | E10: =($A10*E$5+Drivers!$E$264*Drivers!D$198+Drivers!$D$188*Drivers!D$205-(Drivers!$D$185+Drivers!$D$187*Drivers!$D$186))/Drivers!$D$181 | F10: =($A10*F$5+Drivers!$E$264*Drivers!D$198+Drivers!$D$188*Drivers!D$205-(Drivers!$D$185+Drivers!$D$187*Drivers!$D$186))/Drivers!$D$181 | G10: =($A10*G$5+Drivers!$E$264*Drivers!D$198+Drivers!$D$188*Drivers!D$205-(Drivers!$D$185+Drivers!$D$187*Drivers!$D$186))/Drivers!$D$181
A11: 1400 | B11: =($A11*B$5+Drivers!$E$264*Drivers!D$198+Drivers!$D$188*Drivers!D$205-(Drivers!$D$185+Drivers!$D$187*Drivers!$D$186))/Drivers!$D$181 | C11: =($A11*C$5+Drivers!$E$264*Drivers!D$198+Drivers!$D$188*Drivers!D$205-(Drivers!$D$185+Drivers!$D$187*Drivers!$D$186))/Drivers!$D$181 | D11: =($A11*D$5+Drivers!$E$264*Drivers!D$198+Drivers!$D$188*Drivers!D$205-(Drivers!$D$185+Drivers!$D$187*Drivers!$D$186))/Drivers!$D$181 | E11: =($A11*E$5+Drivers!$E$264*Drivers!D$198+Drivers!$D$188*Drivers!D$205-(Drivers!$D$185+Drivers!$D$187*Drivers!$D$186))/Drivers!$D$181 | F11: =($A11*F$5+Drivers!$E$264*Drivers!D$198+Drivers!$D$188*Drivers!D$205-(Drivers!$D$185+Drivers!$D$187*Drivers!$D$186))/Drivers!$D$181 | G11: =($A11*G$5+Drivers!$E$264*Drivers!D$198+Drivers!$D$188*Drivers!D$205-(Drivers!$D$185+Drivers!$D$187*Drivers!$D$186))/Drivers!$D$181
A12: 1430 | B12: =($A12*B$5+Drivers!$E$264*Drivers!D$198+Drivers!$D$188*Drivers!D$205-(Drivers!$D$185+Drivers!$D$187*Drivers!$D$186))/Drivers!$D$181 | C12: =($A12*C$5+Drivers!$E$264*Drivers!D$198+Drivers!$D$188*Drivers!D$205-(Drivers!$D$185+Drivers!$D$187*Drivers!$D$186))/Drivers!$D$181 | D12: =($A12*D$5+Drivers!$E$264*Drivers!D$198+Drivers!$D$188*Drivers!D$205-(Drivers!$D$185+Drivers!$D$187*Drivers!$D$186))/Drivers!$D$181 | E12: =($A12*E$5+Drivers!$E$264*Drivers!D$198+Drivers!$D$188*Drivers!D$205-(Drivers!$D$185+Drivers!$D$187*Drivers!$D$186))/Drivers!$D$181 | F12: =($A12*F$5+Drivers!$E$264*Drivers!D$198+Drivers!$D$188*Drivers!D$205-(Drivers!$D$185+Drivers!$D$187*Drivers!$D$186))/Drivers!$D$181 | G12: =($A12*G$5+Drivers!$E$264*Drivers!D$198+Drivers!$D$188*Drivers!D$205-(Drivers!$D$185+Drivers!$D$187*Drivers!$D$186))/Drivers!$D$181
A13: 1550 | B13: =($A13*B$5+Drivers!$E$264*Drivers!D$198+Drivers!$D$188*Drivers!D$205-(Drivers!$D$185+Drivers!$D$187*Drivers!$D$186))/Drivers!$D$181 | C13: =($A13*C$5+Drivers!$E$264*Drivers!D$198+Drivers!$D$188*Drivers!D$205-(Drivers!$D$185+Drivers!$D$187*Drivers!$D$186))/Drivers!$D$181 | D13: =($A13*D$5+Drivers!$E$264*Drivers!D$198+Drivers!$D$188*Drivers!D$205-(Drivers!$D$185+Drivers!$D$187*Drivers!$D$186))/Drivers!$D$181 | E13: =($A13*E$5+Drivers!$E$264*Drivers!D$198+Drivers!$D$188*Drivers!D$205-(Drivers!$D$185+Drivers!$D$187*Drivers!$D$186))/Drivers!$D$181 | F13: =($A13*F$5+Drivers!$E$264*Drivers!D$198+Drivers!$D$188*Drivers!D$205-(Drivers!$D$185+Drivers!$D$187*Drivers!$D$186))/Drivers!$D$181 | G13: =($A13*G$5+Drivers!$E$264*Drivers!D$198+Drivers!$D$188*Drivers!D$205-(Drivers!$D$185+Drivers!$D$187*Drivers!$D$186))/Drivers!$D$181
A14: 1700 | B14: =($A14*B$5+Drivers!$E$264*Drivers!D$198+Drivers!$D$188*Drivers!D$205-(Drivers!$D$185+Drivers!$D$187*Drivers!$D$186))/Drivers!$D$181 | C14: =($A14*C$5+Drivers!$E$264*Drivers!D$198+Drivers!$D$188*Drivers!D$205-(Drivers!$D$185+Drivers!$D$187*Drivers!$D$186))/Drivers!$D$181 | D14: =($A14*D$5+Drivers!$E$264*Drivers!D$198+Drivers!$D$188*Drivers!D$205-(Drivers!$D$185+Drivers!$D$187*Drivers!$D$186))/Drivers!$D$181 | E14: =($A14*E$5+Drivers!$E$264*Drivers!D$198+Drivers!$D$188*Drivers!D$205-(Drivers!$D$185+Drivers!$D$187*Drivers!$D$186))/Drivers!$D$181 | F14: =($A14*F$5+Drivers!$E$264*Drivers!D$198+Drivers!$D$188*Drivers!D$205-(Drivers!$D$185+Drivers!$D$187*Drivers!$D$186))/Drivers!$D$181 | G14: =($A14*G$5+Drivers!$E$264*Drivers!D$198+Drivers!$D$188*Drivers!D$205-(Drivers!$D$185+Drivers!$D$187*Drivers!$D$186))/Drivers!$D$181
A16: Grid 2: SOTP value per share ($): 2027E Power units (rows) x EBITDA per unit $M (columns); Base Aerospace and Leasing
A17: Power units delivered in 2027 \ EBITDA per unit ($M) | B17: 4 | C17: 5 | D17: 6 | E17: 7.5 | F17: 9 | G17: 10
A18: 0 | B18: =(Drivers!$E$263*Drivers!D$191+$A18*B$17*Drivers!D$198+Drivers!$D$188*Drivers!D$205-(Drivers!$D$185+Drivers!$D$187*Drivers!$D$186))/Drivers!$D$181 | C18: =(Drivers!$E$263*Drivers!D$191+$A18*C$17*Drivers!D$198+Drivers!$D$188*Drivers!D$205-(Drivers!$D$185+Drivers!$D$187*Drivers!$D$186))/Drivers!$D$181 | D18: =(Drivers!$E$263*Drivers!D$191+$A18*D$17*Drivers!D$198+Drivers!$D$188*Drivers!D$205-(Drivers!$D$185+Drivers!$D$187*Drivers!$D$186))/Drivers!$D$181 | E18: =(Drivers!$E$263*Drivers!D$191+$A18*E$17*Drivers!D$198+Drivers!$D$188*Drivers!D$205-(Drivers!$D$185+Drivers!$D$187*Drivers!$D$186))/Drivers!$D$181 | F18: =(Drivers!$E$263*Drivers!D$191+$A18*F$17*Drivers!D$198+Drivers!$D$188*Drivers!D$205-(Drivers!$D$185+Drivers!$D$187*Drivers!$D$186))/Drivers!$D$181 | G18: =(Drivers!$E$263*Drivers!D$191+$A18*G$17*Drivers!D$198+Drivers!$D$188*Drivers!D$205-(Drivers!$D$185+Drivers!$D$187*Drivers!$D$186))/Drivers!$D$181
A19: 10 | B19: =(Drivers!$E$263*Drivers!D$191+$A19*B$17*Drivers!D$198+Drivers!$D$188*Drivers!D$205-(Drivers!$D$185+Drivers!$D$187*Drivers!$D$186))/Drivers!$D$181 | C19: =(Drivers!$E$263*Drivers!D$191+$A19*C$17*Drivers!D$198+Drivers!$D$188*Drivers!D$205-(Drivers!$D$185+Drivers!$D$187*Drivers!$D$186))/Drivers!$D$181 | D19: =(Drivers!$E$263*Drivers!D$191+$A19*D$17*Drivers!D$198+Drivers!$D$188*Drivers!D$205-(Drivers!$D$185+Drivers!$D$187*Drivers!$D$186))/Drivers!$D$181 | E19: =(Drivers!$E$263*Drivers!D$191+$A19*E$17*Drivers!D$198+Drivers!$D$188*Drivers!D$205-(Drivers!$D$185+Drivers!$D$187*Drivers!$D$186))/Drivers!$D$181 | F19: =(Drivers!$E$263*Drivers!D$191+$A19*F$17*Drivers!D$198+Drivers!$D$188*Drivers!D$205-(Drivers!$D$185+Drivers!$D$187*Drivers!$D$186))/Drivers!$D$181 | G19: =(Drivers!$E$263*Drivers!D$191+$A19*G$17*Drivers!D$198+Drivers!$D$188*Drivers!D$205-(Drivers!$D$185+Drivers!$D$187*Drivers!$D$186))/Drivers!$D$181
A20: 20 | B20: =(Drivers!$E$263*Drivers!D$191+$A20*B$17*Drivers!D$198+Drivers!$D$188*Drivers!D$205-(Drivers!$D$185+Drivers!$D$187*Drivers!$D$186))/Drivers!$D$181 | C20: =(Drivers!$E$263*Drivers!D$191+$A20*C$17*Drivers!D$198+Drivers!$D$188*Drivers!D$205-(Drivers!$D$185+Drivers!$D$187*Drivers!$D$186))/Drivers!$D$181 | D20: =(Drivers!$E$263*Drivers!D$191+$A20*D$17*Drivers!D$198+Drivers!$D$188*Drivers!D$205-(Drivers!$D$185+Drivers!$D$187*Drivers!$D$186))/Drivers!$D$181 | E20: =(Drivers!$E$263*Drivers!D$191+$A20*E$17*Drivers!D$198+Drivers!$D$188*Drivers!D$205-(Drivers!$D$185+Drivers!$D$187*Drivers!$D$186))/Drivers!$D$181 | F20: =(Drivers!$E$263*Drivers!D$191+$A20*F$17*Drivers!D$198+Drivers!$D$188*Drivers!D$205-(Drivers!$D$185+Drivers!$D$187*Drivers!$D$186))/Drivers!$D$181 | G20: =(Drivers!$E$263*Drivers!D$191+$A20*G$17*Drivers!D$198+Drivers!$D$188*Drivers!D$205-(Drivers!$D$185+Drivers!$D$187*Drivers!$D$186))/Drivers!$D$181
A21: 30 | B21: =(Drivers!$E$263*Drivers!D$191+$A21*B$17*Drivers!D$198+Drivers!$D$188*Drivers!D$205-(Drivers!$D$185+Drivers!$D$187*Drivers!$D$186))/Drivers!$D$181 | C21: =(Drivers!$E$263*Drivers!D$191+$A21*C$17*Drivers!D$198+Drivers!$D$188*Drivers!D$205-(Drivers!$D$185+Drivers!$D$187*Drivers!$D$186))/Drivers!$D$181 | D21: =(Drivers!$E$263*Drivers!D$191+$A21*D$17*Drivers!D$198+Drivers!$D$188*Drivers!D$205-(Drivers!$D$185+Drivers!$D$187*Drivers!$D$186))/Drivers!$D$181 | E21: =(Drivers!$E$263*Drivers!D$191+$A21*E$17*Drivers!D$198+Drivers!$D$188*Drivers!D$205-(Drivers!$D$185+Drivers!$D$187*Drivers!$D$186))/Drivers!$D$181 | F21: =(Drivers!$E$263*Drivers!D$191+$A21*F$17*Drivers!D$198+Drivers!$D$188*Drivers!D$205-(Drivers!$D$185+Drivers!$D$187*Drivers!$D$186))/Drivers!$D$181 | G21: =(Drivers!$E$263*Drivers!D$191+$A21*G$17*Drivers!D$198+Drivers!$D$188*Drivers!D$205-(Drivers!$D$185+Drivers!$D$187*Drivers!$D$186))/Drivers!$D$181
A22: 44 | B22: =(Drivers!$E$263*Drivers!D$191+$A22*B$17*Drivers!D$198+Drivers!$D$188*Drivers!D$205-(Drivers!$D$185+Drivers!$D$187*Drivers!$D$186))/Drivers!$D$181 | C22: =(Drivers!$E$263*Drivers!D$191+$A22*C$17*Drivers!D$198+Drivers!$D$188*Drivers!D$205-(Drivers!$D$185+Drivers!$D$187*Drivers!$D$186))/Drivers!$D$181 | D22: =(Drivers!$E$263*Drivers!D$191+$A22*D$17*Drivers!D$198+Drivers!$D$188*Drivers!D$205-(Drivers!$D$185+Drivers!$D$187*Drivers!$D$186))/Drivers!$D$181 | E22: =(Drivers!$E$263*Drivers!D$191+$A22*E$17*Drivers!D$198+Drivers!$D$188*Drivers!D$205-(Drivers!$D$185+Drivers!$D$187*Drivers!$D$186))/Drivers!$D$181 | F22: =(Drivers!$E$263*Drivers!D$191+$A22*F$17*Drivers!D$198+Drivers!$D$188*Drivers!D$205-(Drivers!$D$185+Drivers!$D$187*Drivers!$D$186))/Drivers!$D$181 | G22: =(Drivers!$E$263*Drivers!D$191+$A22*G$17*Drivers!D$198+Drivers!$D$188*Drivers!D$205-(Drivers!$D$185+Drivers!$D$187*Drivers!$D$186))/Drivers!$D$181
A23: 60 | B23: =(Drivers!$E$263*Drivers!D$191+$A23*B$17*Drivers!D$198+Drivers!$D$188*Drivers!D$205-(Drivers!$D$185+Drivers!$D$187*Drivers!$D$186))/Drivers!$D$181 | C23: =(Drivers!$E$263*Drivers!D$191+$A23*C$17*Drivers!D$198+Drivers!$D$188*Drivers!D$205-(Drivers!$D$185+Drivers!$D$187*Drivers!$D$186))/Drivers!$D$181 | D23: =(Drivers!$E$263*Drivers!D$191+$A23*D$17*Drivers!D$198+Drivers!$D$188*Drivers!D$205-(Drivers!$D$185+Drivers!$D$187*Drivers!$D$186))/Drivers!$D$181 | E23: =(Drivers!$E$263*Drivers!D$191+$A23*E$17*Drivers!D$198+Drivers!$D$188*Drivers!D$205-(Drivers!$D$185+Drivers!$D$187*Drivers!$D$186))/Drivers!$D$181 | F23: =(Drivers!$E$263*Drivers!D$191+$A23*F$17*Drivers!D$198+Drivers!$D$188*Drivers!D$205-(Drivers!$D$185+Drivers!$D$187*Drivers!$D$186))/Drivers!$D$181 | G23: =(Drivers!$E$263*Drivers!D$191+$A23*G$17*Drivers!D$198+Drivers!$D$188*Drivers!D$205-(Drivers!$D$185+Drivers!$D$187*Drivers!$D$186))/Drivers!$D$181
A24: 80 | B24: =(Drivers!$E$263*Drivers!D$191+$A24*B$17*Drivers!D$198+Drivers!$D$188*Drivers!D$205-(Drivers!$D$185+Drivers!$D$187*Drivers!$D$186))/Drivers!$D$181 | C24: =(Drivers!$E$263*Drivers!D$191+$A24*C$17*Drivers!D$198+Drivers!$D$188*Drivers!D$205-(Drivers!$D$185+Drivers!$D$187*Drivers!$D$186))/Drivers!$D$181 | D24: =(Drivers!$E$263*Drivers!D$191+$A24*D$17*Drivers!D$198+Drivers!$D$188*Drivers!D$205-(Drivers!$D$185+Drivers!$D$187*Drivers!$D$186))/Drivers!$D$181 | E24: =(Drivers!$E$263*Drivers!D$191+$A24*E$17*Drivers!D$198+Drivers!$D$188*Drivers!D$205-(Drivers!$D$185+Drivers!$D$187*Drivers!$D$186))/Drivers!$D$181 | F24: =(Drivers!$E$263*Drivers!D$191+$A24*F$17*Drivers!D$198+Drivers!$D$188*Drivers!D$205-(Drivers!$D$185+Drivers!$D$187*Drivers!$D$186))/Drivers!$D$181 | G24: =(Drivers!$E$263*Drivers!D$191+$A24*G$17*Drivers!D$198+Drivers!$D$188*Drivers!D$205-(Drivers!$D$185+Drivers!$D$187*Drivers!$D$186))/Drivers!$D$181
A25: 100 | B25: =(Drivers!$E$263*Drivers!D$191+$A25*B$17*Drivers!D$198+Drivers!$D$188*Drivers!D$205-(Drivers!$D$185+Drivers!$D$187*Drivers!$D$186))/Drivers!$D$181 | C25: =(Drivers!$E$263*Drivers!D$191+$A25*C$17*Drivers!D$198+Drivers!$D$188*Drivers!D$205-(Drivers!$D$185+Drivers!$D$187*Drivers!$D$186))/Drivers!$D$181 | D25: =(Drivers!$E$263*Drivers!D$191+$A25*D$17*Drivers!D$198+Drivers!$D$188*Drivers!D$205-(Drivers!$D$185+Drivers!$D$187*Drivers!$D$186))/Drivers!$D$181 | E25: =(Drivers!$E$263*Drivers!D$191+$A25*E$17*Drivers!D$198+Drivers!$D$188*Drivers!D$205-(Drivers!$D$185+Drivers!$D$187*Drivers!$D$186))/Drivers!$D$181 | F25: =(Drivers!$E$263*Drivers!D$191+$A25*F$17*Drivers!D$198+Drivers!$D$188*Drivers!D$205-(Drivers!$D$185+Drivers!$D$187*Drivers!$D$186))/Drivers!$D$181 | G25: =(Drivers!$E$263*Drivers!D$191+$A25*G$17*Drivers!D$198+Drivers!$D$188*Drivers!D$205-(Drivers!$D$185+Drivers!$D$187*Drivers!$D$186))/Drivers!$D$181
A27: Grid 3: FY26E clean CFO + CFI ($M): inventory conversion % (rows) x 2H26 Aerospace EBITDA margin (columns), selected scenario
A28: Inventory conversion % \ 2H26 Aerospace margin | B28: 0.24 | C28: 0.26 | D28: 0.28 | E28: 0.3 | F28: 0.32
A29: 0 | B29: =Quarterly!$J$74+(B$28-((Quarterly!$D$12+Quarterly!$E$12)/(Quarterly!$D$8+Quarterly!$E$8)))*(Quarterly!$D$8+Quarterly!$E$8)*(1-Drivers!$D$133)-((Drivers!$D$157-$A29*(Drivers!$D$157-Drivers!$D$158)*Drivers!$E$159)*(Quarterly!$E$14-(B$28-((Quarterly!$D$12+Quarterly!$E$12)/(Quarterly!$D$8+Quarterly!$E$8)))*Quarterly!$E$8)/Drivers!$D$19-Quarterly!$E$86) | C29: =Quarterly!$J$74+(C$28-((Quarterly!$D$12+Quarterly!$E$12)/(Quarterly!$D$8+Quarterly!$E$8)))*(Quarterly!$D$8+Quarterly!$E$8)*(1-Drivers!$D$133)-((Drivers!$D$157-$A29*(Drivers!$D$157-Drivers!$D$158)*Drivers!$E$159)*(Quarterly!$E$14-(C$28-((Quarterly!$D$12+Quarterly!$E$12)/(Quarterly!$D$8+Quarterly!$E$8)))*Quarterly!$E$8)/Drivers!$D$19-Quarterly!$E$86) | D29: =Quarterly!$J$74+(D$28-((Quarterly!$D$12+Quarterly!$E$12)/(Quarterly!$D$8+Quarterly!$E$8)))*(Quarterly!$D$8+Quarterly!$E$8)*(1-Drivers!$D$133)-((Drivers!$D$157-$A29*(Drivers!$D$157-Drivers!$D$158)*Drivers!$E$159)*(Quarterly!$E$14-(D$28-((Quarterly!$D$12+Quarterly!$E$12)/(Quarterly!$D$8+Quarterly!$E$8)))*Quarterly!$E$8)/Drivers!$D$19-Quarterly!$E$86) | E29: =Quarterly!$J$74+(E$28-((Quarterly!$D$12+Quarterly!$E$12)/(Quarterly!$D$8+Quarterly!$E$8)))*(Quarterly!$D$8+Quarterly!$E$8)*(1-Drivers!$D$133)-((Drivers!$D$157-$A29*(Drivers!$D$157-Drivers!$D$158)*Drivers!$E$159)*(Quarterly!$E$14-(E$28-((Quarterly!$D$12+Quarterly!$E$12)/(Quarterly!$D$8+Quarterly!$E$8)))*Quarterly!$E$8)/Drivers!$D$19-Quarterly!$E$86) | F29: =Quarterly!$J$74+(F$28-((Quarterly!$D$12+Quarterly!$E$12)/(Quarterly!$D$8+Quarterly!$E$8)))*(Quarterly!$D$8+Quarterly!$E$8)*(1-Drivers!$D$133)-((Drivers!$D$157-$A29*(Drivers!$D$157-Drivers!$D$158)*Drivers!$E$159)*(Quarterly!$E$14-(F$28-((Quarterly!$D$12+Quarterly!$E$12)/(Quarterly!$D$8+Quarterly!$E$8)))*Quarterly!$E$8)/Drivers!$D$19-Quarterly!$E$86)
A30: 0.1 | B30: =Quarterly!$J$74+(B$28-((Quarterly!$D$12+Quarterly!$E$12)/(Quarterly!$D$8+Quarterly!$E$8)))*(Quarterly!$D$8+Quarterly!$E$8)*(1-Drivers!$D$133)-((Drivers!$D$157-$A30*(Drivers!$D$157-Drivers!$D$158)*Drivers!$E$159)*(Quarterly!$E$14-(B$28-((Quarterly!$D$12+Quarterly!$E$12)/(Quarterly!$D$8+Quarterly!$E$8)))*Quarterly!$E$8)/Drivers!$D$19-Quarterly!$E$86) | C30: =Quarterly!$J$74+(C$28-((Quarterly!$D$12+Quarterly!$E$12)/(Quarterly!$D$8+Quarterly!$E$8)))*(Quarterly!$D$8+Quarterly!$E$8)*(1-Drivers!$D$133)-((Drivers!$D$157-$A30*(Drivers!$D$157-Drivers!$D$158)*Drivers!$E$159)*(Quarterly!$E$14-(C$28-((Quarterly!$D$12+Quarterly!$E$12)/(Quarterly!$D$8+Quarterly!$E$8)))*Quarterly!$E$8)/Drivers!$D$19-Quarterly!$E$86) | D30: =Quarterly!$J$74+(D$28-((Quarterly!$D$12+Quarterly!$E$12)/(Quarterly!$D$8+Quarterly!$E$8)))*(Quarterly!$D$8+Quarterly!$E$8)*(1-Drivers!$D$133)-((Drivers!$D$157-$A30*(Drivers!$D$157-Drivers!$D$158)*Drivers!$E$159)*(Quarterly!$E$14-(D$28-((Quarterly!$D$12+Quarterly!$E$12)/(Quarterly!$D$8+Quarterly!$E$8)))*Quarterly!$E$8)/Drivers!$D$19-Quarterly!$E$86) | E30: =Quarterly!$J$74+(E$28-((Quarterly!$D$12+Quarterly!$E$12)/(Quarterly!$D$8+Quarterly!$E$8)))*(Quarterly!$D$8+Quarterly!$E$8)*(1-Drivers!$D$133)-((Drivers!$D$157-$A30*(Drivers!$D$157-Drivers!$D$158)*Drivers!$E$159)*(Quarterly!$E$14-(E$28-((Quarterly!$D$12+Quarterly!$E$12)/(Quarterly!$D$8+Quarterly!$E$8)))*Quarterly!$E$8)/Drivers!$D$19-Quarterly!$E$86) | F30: =Quarterly!$J$74+(F$28-((Quarterly!$D$12+Quarterly!$E$12)/(Quarterly!$D$8+Quarterly!$E$8)))*(Quarterly!$D$8+Quarterly!$E$8)*(1-Drivers!$D$133)-((Drivers!$D$157-$A30*(Drivers!$D$157-Drivers!$D$158)*Drivers!$E$159)*(Quarterly!$E$14-(F$28-((Quarterly!$D$12+Quarterly!$E$12)/(Quarterly!$D$8+Quarterly!$E$8)))*Quarterly!$E$8)/Drivers!$D$19-Quarterly!$E$86)
A31: 0.2 | B31: =Quarterly!$J$74+(B$28-((Quarterly!$D$12+Quarterly!$E$12)/(Quarterly!$D$8+Quarterly!$E$8)))*(Quarterly!$D$8+Quarterly!$E$8)*(1-Drivers!$D$133)-((Drivers!$D$157-$A31*(Drivers!$D$157-Drivers!$D$158)*Drivers!$E$159)*(Quarterly!$E$14-(B$28-((Quarterly!$D$12+Quarterly!$E$12)/(Quarterly!$D$8+Quarterly!$E$8)))*Quarterly!$E$8)/Drivers!$D$19-Quarterly!$E$86) | C31: =Quarterly!$J$74+(C$28-((Quarterly!$D$12+Quarterly!$E$12)/(Quarterly!$D$8+Quarterly!$E$8)))*(Quarterly!$D$8+Quarterly!$E$8)*(1-Drivers!$D$133)-((Drivers!$D$157-$A31*(Drivers!$D$157-Drivers!$D$158)*Drivers!$E$159)*(Quarterly!$E$14-(C$28-((Quarterly!$D$12+Quarterly!$E$12)/(Quarterly!$D$8+Quarterly!$E$8)))*Quarterly!$E$8)/Drivers!$D$19-Quarterly!$E$86) | D31: =Quarterly!$J$74+(D$28-((Quarterly!$D$12+Quarterly!$E$12)/(Quarterly!$D$8+Quarterly!$E$8)))*(Quarterly!$D$8+Quarterly!$E$8)*(1-Drivers!$D$133)-((Drivers!$D$157-$A31*(Drivers!$D$157-Drivers!$D$158)*Drivers!$E$159)*(Quarterly!$E$14-(D$28-((Quarterly!$D$12+Quarterly!$E$12)/(Quarterly!$D$8+Quarterly!$E$8)))*Quarterly!$E$8)/Drivers!$D$19-Quarterly!$E$86) | E31: =Quarterly!$J$74+(E$28-((Quarterly!$D$12+Quarterly!$E$12)/(Quarterly!$D$8+Quarterly!$E$8)))*(Quarterly!$D$8+Quarterly!$E$8)*(1-Drivers!$D$133)-((Drivers!$D$157-$A31*(Drivers!$D$157-Drivers!$D$158)*Drivers!$E$159)*(Quarterly!$E$14-(E$28-((Quarterly!$D$12+Quarterly!$E$12)/(Quarterly!$D$8+Quarterly!$E$8)))*Quarterly!$E$8)/Drivers!$D$19-Quarterly!$E$86) | F31: =Quarterly!$J$74+(F$28-((Quarterly!$D$12+Quarterly!$E$12)/(Quarterly!$D$8+Quarterly!$E$8)))*(Quarterly!$D$8+Quarterly!$E$8)*(1-Drivers!$D$133)-((Drivers!$D$157-$A31*(Drivers!$D$157-Drivers!$D$158)*Drivers!$E$159)*(Quarterly!$E$14-(F$28-((Quarterly!$D$12+Quarterly!$E$12)/(Quarterly!$D$8+Quarterly!$E$8)))*Quarterly!$E$8)/Drivers!$D$19-Quarterly!$E$86)
A32: 0.3 | B32: =Quarterly!$J$74+(B$28-((Quarterly!$D$12+Quarterly!$E$12)/(Quarterly!$D$8+Quarterly!$E$8)))*(Quarterly!$D$8+Quarterly!$E$8)*(1-Drivers!$D$133)-((Drivers!$D$157-$A32*(Drivers!$D$157-Drivers!$D$158)*Drivers!$E$159)*(Quarterly!$E$14-(B$28-((Quarterly!$D$12+Quarterly!$E$12)/(Quarterly!$D$8+Quarterly!$E$8)))*Quarterly!$E$8)/Drivers!$D$19-Quarterly!$E$86) | C32: =Quarterly!$J$74+(C$28-((Quarterly!$D$12+Quarterly!$E$12)/(Quarterly!$D$8+Quarterly!$E$8)))*(Quarterly!$D$8+Quarterly!$E$8)*(1-Drivers!$D$133)-((Drivers!$D$157-$A32*(Drivers!$D$157-Drivers!$D$158)*Drivers!$E$159)*(Quarterly!$E$14-(C$28-((Quarterly!$D$12+Quarterly!$E$12)/(Quarterly!$D$8+Quarterly!$E$8)))*Quarterly!$E$8)/Drivers!$D$19-Quarterly!$E$86) | D32: =Quarterly!$J$74+(D$28-((Quarterly!$D$12+Quarterly!$E$12)/(Quarterly!$D$8+Quarterly!$E$8)))*(Quarterly!$D$8+Quarterly!$E$8)*(1-Drivers!$D$133)-((Drivers!$D$157-$A32*(Drivers!$D$157-Drivers!$D$158)*Drivers!$E$159)*(Quarterly!$E$14-(D$28-((Quarterly!$D$12+Quarterly!$E$12)/(Quarterly!$D$8+Quarterly!$E$8)))*Quarterly!$E$8)/Drivers!$D$19-Quarterly!$E$86) | E32: =Quarterly!$J$74+(E$28-((Quarterly!$D$12+Quarterly!$E$12)/(Quarterly!$D$8+Quarterly!$E$8)))*(Quarterly!$D$8+Quarterly!$E$8)*(1-Drivers!$D$133)-((Drivers!$D$157-$A32*(Drivers!$D$157-Drivers!$D$158)*Drivers!$E$159)*(Quarterly!$E$14-(E$28-((Quarterly!$D$12+Quarterly!$E$12)/(Quarterly!$D$8+Quarterly!$E$8)))*Quarterly!$E$8)/Drivers!$D$19-Quarterly!$E$86) | F32: =Quarterly!$J$74+(F$28-((Quarterly!$D$12+Quarterly!$E$12)/(Quarterly!$D$8+Quarterly!$E$8)))*(Quarterly!$D$8+Quarterly!$E$8)*(1-Drivers!$D$133)-((Drivers!$D$157-$A32*(Drivers!$D$157-Drivers!$D$158)*Drivers!$E$159)*(Quarterly!$E$14-(F$28-((Quarterly!$D$12+Quarterly!$E$12)/(Quarterly!$D$8+Quarterly!$E$8)))*Quarterly!$E$8)/Drivers!$D$19-Quarterly!$E$86)
A33: 0.4 | B33: =Quarterly!$J$74+(B$28-((Quarterly!$D$12+Quarterly!$E$12)/(Quarterly!$D$8+Quarterly!$E$8)))*(Quarterly!$D$8+Quarterly!$E$8)*(1-Drivers!$D$133)-((Drivers!$D$157-$A33*(Drivers!$D$157-Drivers!$D$158)*Drivers!$E$159)*(Quarterly!$E$14-(B$28-((Quarterly!$D$12+Quarterly!$E$12)/(Quarterly!$D$8+Quarterly!$E$8)))*Quarterly!$E$8)/Drivers!$D$19-Quarterly!$E$86) | C33: =Quarterly!$J$74+(C$28-((Quarterly!$D$12+Quarterly!$E$12)/(Quarterly!$D$8+Quarterly!$E$8)))*(Quarterly!$D$8+Quarterly!$E$8)*(1-Drivers!$D$133)-((Drivers!$D$157-$A33*(Drivers!$D$157-Drivers!$D$158)*Drivers!$E$159)*(Quarterly!$E$14-(C$28-((Quarterly!$D$12+Quarterly!$E$12)/(Quarterly!$D$8+Quarterly!$E$8)))*Quarterly!$E$8)/Drivers!$D$19-Quarterly!$E$86) | D33: =Quarterly!$J$74+(D$28-((Quarterly!$D$12+Quarterly!$E$12)/(Quarterly!$D$8+Quarterly!$E$8)))*(Quarterly!$D$8+Quarterly!$E$8)*(1-Drivers!$D$133)-((Drivers!$D$157-$A33*(Drivers!$D$157-Drivers!$D$158)*Drivers!$E$159)*(Quarterly!$E$14-(D$28-((Quarterly!$D$12+Quarterly!$E$12)/(Quarterly!$D$8+Quarterly!$E$8)))*Quarterly!$E$8)/Drivers!$D$19-Quarterly!$E$86) | E33: =Quarterly!$J$74+(E$28-((Quarterly!$D$12+Quarterly!$E$12)/(Quarterly!$D$8+Quarterly!$E$8)))*(Quarterly!$D$8+Quarterly!$E$8)*(1-Drivers!$D$133)-((Drivers!$D$157-$A33*(Drivers!$D$157-Drivers!$D$158)*Drivers!$E$159)*(Quarterly!$E$14-(E$28-((Quarterly!$D$12+Quarterly!$E$12)/(Quarterly!$D$8+Quarterly!$E$8)))*Quarterly!$E$8)/Drivers!$D$19-Quarterly!$E$86) | F33: =Quarterly!$J$74+(F$28-((Quarterly!$D$12+Quarterly!$E$12)/(Quarterly!$D$8+Quarterly!$E$8)))*(Quarterly!$D$8+Quarterly!$E$8)*(1-Drivers!$D$133)-((Drivers!$D$157-$A33*(Drivers!$D$157-Drivers!$D$158)*Drivers!$E$159)*(Quarterly!$E$14-(F$28-((Quarterly!$D$12+Quarterly!$E$12)/(Quarterly!$D$8+Quarterly!$E$8)))*Quarterly!$E$8)/Drivers!$D$19-Quarterly!$E$86)
A34: 0.5 | B34: =Quarterly!$J$74+(B$28-((Quarterly!$D$12+Quarterly!$E$12)/(Quarterly!$D$8+Quarterly!$E$8)))*(Quarterly!$D$8+Quarterly!$E$8)*(1-Drivers!$D$133)-((Drivers!$D$157-$A34*(Drivers!$D$157-Drivers!$D$158)*Drivers!$E$159)*(Quarterly!$E$14-(B$28-((Quarterly!$D$12+Quarterly!$E$12)/(Quarterly!$D$8+Quarterly!$E$8)))*Quarterly!$E$8)/Drivers!$D$19-Quarterly!$E$86) | C34: =Quarterly!$J$74+(C$28-((Quarterly!$D$12+Quarterly!$E$12)/(Quarterly!$D$8+Quarterly!$E$8)))*(Quarterly!$D$8+Quarterly!$E$8)*(1-Drivers!$D$133)-((Drivers!$D$157-$A34*(Drivers!$D$157-Drivers!$D$158)*Drivers!$E$159)*(Quarterly!$E$14-(C$28-((Quarterly!$D$12+Quarterly!$E$12)/(Quarterly!$D$8+Quarterly!$E$8)))*Quarterly!$E$8)/Drivers!$D$19-Quarterly!$E$86) | D34: =Quarterly!$J$74+(D$28-((Quarterly!$D$12+Quarterly!$E$12)/(Quarterly!$D$8+Quarterly!$E$8)))*(Quarterly!$D$8+Quarterly!$E$8)*(1-Drivers!$D$133)-((Drivers!$D$157-$A34*(Drivers!$D$157-Drivers!$D$158)*Drivers!$E$159)*(Quarterly!$E$14-(D$28-((Quarterly!$D$12+Quarterly!$E$12)/(Quarterly!$D$8+Quarterly!$E$8)))*Quarterly!$E$8)/Drivers!$D$19-Quarterly!$E$86) | E34: =Quarterly!$J$74+(E$28-((Quarterly!$D$12+Quarterly!$E$12)/(Quarterly!$D$8+Quarterly!$E$8)))*(Quarterly!$D$8+Quarterly!$E$8)*(1-Drivers!$D$133)-((Drivers!$D$157-$A34*(Drivers!$D$157-Drivers!$D$158)*Drivers!$E$159)*(Quarterly!$E$14-(E$28-((Quarterly!$D$12+Quarterly!$E$12)/(Quarterly!$D$8+Quarterly!$E$8)))*Quarterly!$E$8)/Drivers!$D$19-Quarterly!$E$86) | F34: =Quarterly!$J$74+(F$28-((Quarterly!$D$12+Quarterly!$E$12)/(Quarterly!$D$8+Quarterly!$E$8)))*(Quarterly!$D$8+Quarterly!$E$8)*(1-Drivers!$D$133)-((Drivers!$D$157-$A34*(Drivers!$D$157-Drivers!$D$158)*Drivers!$E$159)*(Quarterly!$E$14-(F$28-((Quarterly!$D$12+Quarterly!$E$12)/(Quarterly!$D$8+Quarterly!$E$8)))*Quarterly!$E$8)/Drivers!$D$19-Quarterly!$E$86)
A35: Grid 3 holds all other selected-scenario drivers fixed: margin changes EBITDA after tax and cost of sales (inventory base); conversion changes Q4'26 inventory days. Exact at the selected scenario's own conversion and margin. Limitation: a higher margin also lowers the cost-of-sales proxy and so the days-based inventory balance, which amplifies the margin sensitivity.

Sheet Checks
A1: Checks and tie-outs (formula-driven pass/fail)
A2: Model integrity checks for the spec's Verification section. 'By construction' means the Q4 data are derived as FY less 9M, so the check is an identity, not independent verification.
A4: Check | B4: Model value | C4: Expected / comparator | D4: Tolerance | E4: Result | F4: Notes
A5: 1. Historical quarters sum to FY (FY2024 and FY2025; Q4 derived as FY less 9M, so by construction)
A6: Total revenues: sum of quarters vs FY2024 | B6: =Historical!$E$12+Historical!$F$12+Historical!$G$12+Historical!$H$12 | C6: =Historical!$C$12 | D6: 0.1 | E6: =IF(ISERROR(B6-C6),"FAIL",IF(ABS(B6-C6)<=D6,"PASS","FAIL")) | F6: by construction for derived Q4
A7: Total revenues: sum of quarters vs FY2025 | B7: =Historical!$I$12+Historical!$J$12+Historical!$K$12+Historical!$L$12 | C7: =Historical!$D$12 | D7: 0.1 | E7: =IF(ISERROR(B7-C7),"FAIL",IF(ABS(B7-C7)<=D7,"PASS","FAIL")) | F7: by construction for derived Q4
A8: Cost of sales: sum of quarters vs FY2024 | B8: =Historical!$E$16+Historical!$F$16+Historical!$G$16+Historical!$H$16 | C8: =Historical!$C$16 | D8: 0.1 | E8: =IF(ISERROR(B8-C8),"FAIL",IF(ABS(B8-C8)<=D8,"PASS","FAIL")) | F8: by construction for derived Q4
A9: Cost of sales: sum of quarters vs FY2025 | B9: =Historical!$I$16+Historical!$J$16+Historical!$K$16+Historical!$L$16 | C9: =Historical!$D$16 | D9: 0.1 | E9: =IF(ISERROR(B9-C9),"FAIL",IF(ABS(B9-C9)<=D9,"PASS","FAIL")) | F9: by construction for derived Q4
A10: D&A: sum of quarters vs FY2024 | B10: =Historical!$E$21+Historical!$F$21+Historical!$G$21+Historical!$H$21 | C10: =Historical!$C$21 | D10: 0.1 | E10: =IF(ISERROR(B10-C10),"FAIL",IF(ABS(B10-C10)<=D10,"PASS","FAIL")) | F10: by construction for derived Q4
A11: D&A: sum of quarters vs FY2025 | B11: =Historical!$I$21+Historical!$J$21+Historical!$K$21+Historical!$L$21 | C11: =Historical!$D$21 | D11: 0.1 | E11: =IF(ISERROR(B11-C11),"FAIL",IF(ABS(B11-C11)<=D11,"PASS","FAIL")) | F11: by construction for derived Q4
A12: Interest expense: sum of quarters vs FY2024 | B12: =Historical!$E$22+Historical!$F$22+Historical!$G$22+Historical!$H$22 | C12: =Historical!$C$22 | D12: 0.1 | E12: =IF(ISERROR(B12-C12),"FAIL",IF(ABS(B12-C12)<=D12,"PASS","FAIL")) | F12: by construction for derived Q4
A13: Interest expense: sum of quarters vs FY2025 | B13: =Historical!$I$22+Historical!$J$22+Historical!$K$22+Historical!$L$22 | C13: =Historical!$D$22 | D13: 0.1 | E13: =IF(ISERROR(B13-C13),"FAIL",IF(ABS(B13-C13)<=D13,"PASS","FAIL")) | F13: by construction for derived Q4
A14: Aerospace Adj. EBITDA: sum of quarters vs FY2024 | B14: =Historical!$E$33+Historical!$F$33+Historical!$G$33+Historical!$H$33 | C14: =Historical!$C$33 | D14: 0.1 | E14: =IF(ISERROR(B14-C14),"FAIL",IF(ABS(B14-C14)<=D14,"PASS","FAIL")) | F14: by construction for derived Q4
A15: Aerospace Adj. EBITDA: sum of quarters vs FY2025 | B15: =Historical!$I$33+Historical!$J$33+Historical!$K$33+Historical!$L$33 | C15: =Historical!$D$33 | D15: 0.1 | E15: =IF(ISERROR(B15-C15),"FAIL",IF(ABS(B15-C15)<=D15,"PASS","FAIL")) | F15: by construction for derived Q4
A16: Leasing Adj. EBITDA: sum of quarters vs FY2024 | B16: =Historical!$E$34+Historical!$F$34+Historical!$G$34+Historical!$H$34 | C16: =Historical!$C$34 | D16: 0.1 | E16: =IF(ISERROR(B16-C16),"FAIL",IF(ABS(B16-C16)<=D16,"PASS","FAIL")) | F16: by construction for derived Q4
A17: Leasing Adj. EBITDA: sum of quarters vs FY2025 | B17: =Historical!$I$34+Historical!$J$34+Historical!$K$34+Historical!$L$34 | C17: =Historical!$D$34 | D17: 0.1 | E17: =IF(ISERROR(B17-C17),"FAIL",IF(ABS(B17-C17)<=D17,"PASS","FAIL")) | F17: by construction for derived Q4
A18: Corporate EBITDA: sum of quarters vs FY2024 | B18: =Historical!$E$35+Historical!$F$35+Historical!$G$35+Historical!$H$35 | C18: =Historical!$C$35 | D18: 0.1 | E18: =IF(ISERROR(B18-C18),"FAIL",IF(ABS(B18-C18)<=D18,"PASS","FAIL")) | F18: by construction for derived Q4
A19: Corporate EBITDA: sum of quarters vs FY2025 | B19: =Historical!$I$35+Historical!$J$35+Historical!$K$35+Historical!$L$35 | C19: =Historical!$D$35 | D19: 0.1 | E19: =IF(ISERROR(B19-C19),"FAIL",IF(ABS(B19-C19)<=D19,"PASS","FAIL")) | F19: by construction for derived Q4
A20: Eliminations: sum of quarters vs FY2024 | B20: =Historical!$E$36+Historical!$F$36+Historical!$G$36+Historical!$H$36 | C20: =Historical!$C$36 | D20: 0.1 | E20: =IF(ISERROR(B20-C20),"FAIL",IF(ABS(B20-C20)<=D20,"PASS","FAIL")) | F20: by construction for derived Q4
A21: Eliminations: sum of quarters vs FY2025 | B21: =Historical!$I$36+Historical!$J$36+Historical!$K$36+Historical!$L$36 | C21: =Historical!$D$36 | D21: 0.1 | E21: =IF(ISERROR(B21-C21),"FAIL",IF(ABS(B21-C21)<=D21,"PASS","FAIL")) | F21: by construction for derived Q4
A22: Total Adj. EBITDA: sum of quarters vs FY2024 | B22: =Historical!$E$37+Historical!$F$37+Historical!$G$37+Historical!$H$37 | C22: =Historical!$C$37 | D22: 0.1 | E22: =IF(ISERROR(B22-C22),"FAIL",IF(ABS(B22-C22)<=D22,"PASS","FAIL")) | F22: by construction for derived Q4
A23: Total Adj. EBITDA: sum of quarters vs FY2025 | B23: =Historical!$I$37+Historical!$J$37+Historical!$K$37+Historical!$L$37 | C23: =Historical!$D$37 | D23: 0.1 | E23: =IF(ISERROR(B23-C23),"FAIL",IF(ABS(B23-C23)<=D23,"PASS","FAIL")) | F23: by construction for derived Q4
A24: CFO: sum of quarters vs FY2024 | B24: =Historical!$E$48+Historical!$F$48+Historical!$G$48+Historical!$H$48 | C24: =Historical!$C$48 | D24: 0.1 | E24: =IF(ISERROR(B24-C24),"FAIL",IF(ABS(B24-C24)<=D24,"PASS","FAIL")) | F24: CFO/CFI quarters derived from YTD
A25: CFO: sum of quarters vs FY2025 | B25: =Historical!$I$48+Historical!$J$48+Historical!$K$48+Historical!$L$48 | C25: =Historical!$D$48 | D25: 0.1 | E25: =IF(ISERROR(B25-C25),"FAIL",IF(ABS(B25-C25)<=D25,"PASS","FAIL")) | F25: CFO/CFI quarters derived from YTD
A26: CFI: sum of quarters vs FY2024 | B26: =Historical!$E$49+Historical!$F$49+Historical!$G$49+Historical!$H$49 | C26: =Historical!$C$49 | D26: 0.1 | E26: =IF(ISERROR(B26-C26),"FAIL",IF(ABS(B26-C26)<=D26,"PASS","FAIL")) | F26: CFO/CFI quarters derived from YTD
A27: CFI: sum of quarters vs FY2025 | B27: =Historical!$I$49+Historical!$J$49+Historical!$K$49+Historical!$L$49 | C27: =Historical!$D$49 | D27: 0.1 | E27: =IF(ISERROR(B27-C27),"FAIL",IF(ABS(B27-C27)<=D27,"PASS","FAIL")) | F27: CFO/CFI quarters derived from YTD
A28: Net income attributable: sum of quarters vs FY2024 | B28: =Historical!$E$28+Historical!$F$28+Historical!$G$28+Historical!$H$28 | C28: =Historical!$C$28 | D28: 0.1 | E28: =IF(ISERROR(B28-C28),"FAIL",IF(ABS(B28-C28)<=D28,"PASS","FAIL")) | F28: by construction for derived Q4
A29: Net income attributable: sum of quarters vs FY2025 | B29: =Historical!$I$28+Historical!$J$28+Historical!$K$28+Historical!$L$28 | C29: =Historical!$D$28 | D29: 0.1 | E29: =IF(ISERROR(B29-C29),"FAIL",IF(ABS(B29-C29)<=D29,"PASS","FAIL")) | F29: by construction for derived Q4
A30: 2. Quarterly sums to Annual (FY2026E, FY2027E)
A31: Aerospace EBITDA: Quarterly Q1'26-Q4'26 vs Annual FY26 | B31: =SUM(Quarterly!B12:E12) | C31: =Annual!E12 | D31: 0.001 | E31: =IF(ISERROR(B31-C31),"FAIL",IF(ABS(B31-C31)<=D31,"PASS","FAIL"))
A32: Aerospace EBITDA: Quarterly Q1'27-Q4'27 vs Annual FY27 | B32: =SUM(Quarterly!F12:I12) | C32: =Annual!F12 | D32: 0.001 | E32: =IF(ISERROR(B32-C32),"FAIL",IF(ABS(B32-C32)<=D32,"PASS","FAIL"))
A33: Power EBITDA: Quarterly Q1'26-Q4'26 vs Annual FY26 | B33: =SUM(Quarterly!B18:E18) | C33: =Annual!E18 | D33: 0.001 | E33: =IF(ISERROR(B33-C33),"FAIL",IF(ABS(B33-C33)<=D33,"PASS","FAIL"))
A34: Power EBITDA: Quarterly Q1'27-Q4'27 vs Annual FY27 | B34: =SUM(Quarterly!F18:I18) | C34: =Annual!F18 | D34: 0.001 | E34: =IF(ISERROR(B34-C34),"FAIL",IF(ABS(B34-C34)<=D34,"PASS","FAIL"))
A35: Leasing EBITDA: Quarterly Q1'26-Q4'26 vs Annual FY26 | B35: =SUM(Quarterly!B32:E32) | C35: =Annual!E32 | D35: 0.001 | E35: =IF(ISERROR(B35-C35),"FAIL",IF(ABS(B35-C35)<=D35,"PASS","FAIL"))
A36: Leasing EBITDA: Quarterly Q1'27-Q4'27 vs Annual FY27 | B36: =SUM(Quarterly!F32:I32) | C36: =Annual!F32 | D36: 0.001 | E36: =IF(ISERROR(B36-C36),"FAIL",IF(ABS(B36-C36)<=D36,"PASS","FAIL"))
A37: Segment-basis EBITDA: Quarterly Q1'26-Q4'26 vs Annual FY26 | B37: =SUM(Quarterly!B38:E38) | C37: =Annual!E38 | D37: 0.001 | E37: =IF(ISERROR(B37-C37),"FAIL",IF(ABS(B37-C37)<=D37,"PASS","FAIL"))
A38: Segment-basis EBITDA: Quarterly Q1'27-Q4'27 vs Annual FY27 | B38: =SUM(Quarterly!F38:I38) | C38: =Annual!F38 | D38: 0.001 | E38: =IF(ISERROR(B38-C38),"FAIL",IF(ABS(B38-C38)<=D38,"PASS","FAIL"))
A39: Total Adj. EBITDA: Quarterly Q1'26-Q4'26 vs Annual FY26 | B39: =SUM(Quarterly!B37:E37) | C39: =Annual!E37 | D39: 0.001 | E39: =IF(ISERROR(B39-C39),"FAIL",IF(ABS(B39-C39)<=D39,"PASS","FAIL"))
A40: Total Adj. EBITDA: Quarterly Q1'27-Q4'27 vs Annual FY27 | B40: =SUM(Quarterly!F37:I37) | C40: =Annual!F37 | D40: 0.001 | E40: =IF(ISERROR(B40-C40),"FAIL",IF(ABS(B40-C40)<=D40,"PASS","FAIL"))
A41: Net income to common: Quarterly Q1'26-Q4'26 vs Annual FY26 | B41: =SUM(Quarterly!B52:E52) | C41: =Annual!E52 | D41: 0.001 | E41: =IF(ISERROR(B41-C41),"FAIL",IF(ABS(B41-C41)<=D41,"PASS","FAIL"))
A42: Net income to common: Quarterly Q1'27-Q4'27 vs Annual FY27 | B42: =SUM(Quarterly!F52:I52) | C42: =Annual!F52 | D42: 0.001 | E42: =IF(ISERROR(B42-C42),"FAIL",IF(ABS(B42-C42)<=D42,"PASS","FAIL"))
A43: CFO + CFI: Quarterly Q1'26-Q4'26 vs Annual FY26 | B43: =SUM(Quarterly!B71:E71) | C43: =Annual!E71 | D43: 0.001 | E43: =IF(ISERROR(B43-C43),"FAIL",IF(ABS(B43-C43)<=D43,"PASS","FAIL"))
A44: CFO + CFI: Quarterly Q1'27-Q4'27 vs Annual FY27 | B44: =SUM(Quarterly!F71:I71) | C44: =Annual!F71 | D44: 0.001 | E44: =IF(ISERROR(B44-C44),"FAIL",IF(ABS(B44-C44)<=D44,"PASS","FAIL"))
A45: Clean CFO + CFI: Quarterly Q1'26-Q4'26 vs Annual FY26 | B45: =SUM(Quarterly!B74:E74) | C45: =Annual!E74 | D45: 0.001 | E45: =IF(ISERROR(B45-C45),"FAIL",IF(ABS(B45-C45)<=D45,"PASS","FAIL"))
A46: Clean CFO + CFI: Quarterly Q1'27-Q4'27 vs Annual FY27 | B46: =SUM(Quarterly!F74:I74) | C46: =Annual!F74 | D46: 0.001 | E46: =IF(ISERROR(B46-C46),"FAIL",IF(ABS(B46-C46)<=D46,"PASS","FAIL"))
A47: Adjusted FCF: Quarterly Q1'26-Q4'26 vs Annual FY26 | B47: =SUM(Quarterly!B75:E75) | C47: =Annual!E75 | D47: 0.001 | E47: =IF(ISERROR(B47-C47),"FAIL",IF(ABS(B47-C47)<=D47,"PASS","FAIL"))
A48: Adjusted FCF: Quarterly Q1'27-Q4'27 vs Annual FY27 | B48: =SUM(Quarterly!F75:I75) | C48: =Annual!F75 | D48: 0.001 | E48: =IF(ISERROR(B48-C48),"FAIL",IF(ABS(B48-C48)<=D48,"PASS","FAIL"))
A49: D&A: Quarterly Q1'26-Q4'26 vs Annual FY26 | B49: =SUM(Quarterly!B43:E43) | C49: =Annual!E43 | D49: 0.001 | E49: =IF(ISERROR(B49-C49),"FAIL",IF(ABS(B49-C49)<=D49,"PASS","FAIL"))
A50: D&A: Quarterly Q1'27-Q4'27 vs Annual FY27 | B50: =SUM(Quarterly!F43:I43) | C50: =Annual!F43 | D50: 0.001 | E50: =IF(ISERROR(B50-C50),"FAIL",IF(ABS(B50-C50)<=D50,"PASS","FAIL"))
A51: Interest: Quarterly Q1'26-Q4'26 vs Annual FY26 | B51: =SUM(Quarterly!B46:E46) | C51: =Annual!E46 | D51: 0.001 | E51: =IF(ISERROR(B51-C51),"FAIL",IF(ABS(B51-C51)<=D51,"PASS","FAIL"))
A52: Interest: Quarterly Q1'27-Q4'27 vs Annual FY27 | B52: =SUM(Quarterly!F46:I46) | C52: =Annual!F46 | D52: 0.001 | E52: =IF(ISERROR(B52-C52),"FAIL",IF(ABS(B52-C52)<=D52,"PASS","FAIL"))
A53: 3. Scenario engine ties to guidance and to A_2027_guide_segment_build.csv
A54: Mgmt Guide FY2027E segment EBITDA = $2,300M | B54: =Drivers!$G$266 | C54: 2300 | D54: 1 | E54: =IF(ISERROR(B54-C54),"FAIL",IF(ABS(B54-C54)<=D54,"PASS","FAIL"))
A55: Mgmt Guide FY2027E Aerospace = $1,400M | B55: =Drivers!$G$263 | C55: 1400 | D55: 1 | E55: =IF(ISERROR(B55-C55),"FAIL",IF(ABS(B55-C55)<=D55,"PASS","FAIL"))
A56: Mgmt Guide FY2027E Power = $450M | B56: =Drivers!$G$264 | C56: 450 | D56: 1 | E56: =IF(ISERROR(B56-C56),"FAIL",IF(ABS(B56-C56)<=D56,"PASS","FAIL"))
A57: Mgmt Guide FY2027E Leasing = $450M | B57: =Drivers!$G$265 | C57: 450 | D57: 1 | E57: =IF(ISERROR(B57-C57),"FAIL",IF(ABS(B57-C57)<=D57,"PASS","FAIL"))
A58: Mgmt Guide FY2026E segment EBITDA = $1,525M | B58: =Drivers!$G$262 | C58: 1525 | D58: 1 | E58: =IF(ISERROR(B58-C58),"FAIL",IF(ABS(B58-C58)<=D58,"PASS","FAIL"))
A59: Mgmt Guide FY2026E Aerospace = $1,050M | B59: =Drivers!$G$259 | C59: 1050 | D59: 1 | E59: =IF(ISERROR(B59-C59),"FAIL",IF(ABS(B59-C59)<=D59,"PASS","FAIL"))
A60: Mgmt Guide FY2026E Leasing = $475M | B60: =Drivers!$G$261 | C60: 475 | D60: 1 | E60: =IF(ISERROR(B60-C60),"FAIL",IF(ABS(B60-C60)<=D60,"PASS","FAIL"))
A61: Base FY2027E segment EBITDA ~ $1,920M | B61: =Drivers!$E$266 | C61: 1920 | D61: 5 | E61: =IF(ISERROR(B61-C61),"FAIL",IF(ABS(B61-C61)<=D61,"PASS","FAIL"))
A62: Bear FY2027E segment EBITDA ~ $1,470M | B62: =Drivers!$D$266 | C62: 1470 | D62: 5 | E62: =IF(ISERROR(B62-C62),"FAIL",IF(ABS(B62-C62)<=D62,"PASS","FAIL"))
A63: Bull FY2027E segment EBITDA ~ $2,480M | B63: =Drivers!$F$266 | C63: 2480 | D63: 5 | E63: =IF(ISERROR(B63-C63),"FAIL",IF(ABS(B63-C63)<=D63,"PASS","FAIL"))
A64: Engine (selected) FY27 segment EBITDA = Quarterly FY27 (no logic drift) | B64: =Drivers!$H$266 | C64: =Quarterly!K38 | D64: 0.01 | E64: =IF(ISERROR(B64-C64),"FAIL",IF(ABS(B64-C64)<=D64,"PASS","FAIL"))
A65: Engine (selected) FY26 segment EBITDA = Quarterly FY26 | B65: =Drivers!$H$262 | C65: =Quarterly!J38 | D65: 0.01 | E65: =IF(ISERROR(B65-C65),"FAIL",IF(ABS(B65-C65)<=D65,"PASS","FAIL"))
A66: 4. Valuation targets (thesis.md section 2: Base ~172, Bear ~115, Bull ~280)
A67: Base SOTP ex-corporate ~ $172 | B67: =Valuation!C36 | C67: 172 | D67: 2 | E67: =IF(ISERROR(B67-C67),"FAIL",IF(ABS(B67-C67)<=D67,"PASS","FAIL")) | F67: Difference mainly the $65M preferred deduction and book 1,511.9
A68: Bear SOTP ex-corporate ~ $115 | B68: =Valuation!B36 | C68: 115 | D68: 2 | E68: =IF(ISERROR(B68-C68),"FAIL",IF(ABS(B68-C68)<=D68,"PASS","FAIL"))
A69: Bull SOTP ex-corporate ~ $280 | B69: =Valuation!D36 | C69: 280 | D69: 2 | E69: =IF(ISERROR(B69-C69),"FAIL",IF(ABS(B69-C69)<=D69,"PASS","FAIL"))
A70: Net debt: balance sheet vs stockanalysis (EV - market cap) | B70: =Drivers!$D$185 | C70: =Drivers!$D$184 | D70: 5 | E70: =IF(ISERROR(B70-C70),"FAIL",IF(ABS(B70-C70)<=D70,"PASS","FAIL"))
A71: 5. Cash flow facts from the filings
A72: FY25 CFO = -310.7 | B72: =Historical!$D$48 | C72: -310.7 | D72: 0.1 | E72: =IF(ISERROR(B72-C72),"FAIL",IF(ABS(B72-C72)<=D72,"PASS","FAIL"))
A73: FY25 CFI = +723.3 | B73: =Historical!$D$49 | C73: 723.3 | D73: 0.1 | E73: =IF(ISERROR(B73-C73),"FAIL",IF(ABS(B73-C73)<=D73,"PASS","FAIL"))
A74: FY25 CFO + CFI = 412.6 | B74: =Historical!$D$50 | C74: 412.6 | D74: 0.1 | E74: =IF(ISERROR(B74-C74),"FAIL",IF(ABS(B74-C74)<=D74,"PASS","FAIL"))
A75: 1H26 CFO + CFI = 250.4 | B75: =Historical!$M$50+Historical!$N$50 | C75: 250.4 | D75: 0.1 | E75: =IF(ISERROR(B75-C75),"FAIL",IF(ABS(B75-C75)<=D75,"PASS","FAIL"))
A76: 1H26 seed-sale proceeds = 175.7 | B76: =Historical!$M$52+Historical!$N$52 | C76: 175.7 | D76: 0.1 | E76: =IF(ISERROR(B76-C76),"FAIL",IF(ABS(B76-C76)<=D76,"PASS","FAIL"))
A77: 1H26 insurance proceeds = 48.3 | B77: =Historical!$M$53+Historical!$N$53 | C77: 48.3 | D77: 0.1 | E77: =IF(ISERROR(B77-C77),"FAIL",IF(ABS(B77-C77)<=D77,"PASS","FAIL"))
A78: 1H26 clean CFO + CFI ~ 26 (after ~351 inventory build) | B78: =Historical!$M$86+Historical!$N$86 | C78: 26.4 | D78: 0.2 | E78: =IF(ISERROR(B78-C78),"FAIL",IF(ABS(B78-C78)<=D78,"PASS","FAIL"))
A79: FY25: 724 - 412.6 - 252 = 59.4 inferred residual | B79: =FCF_Quality!B36 | C79: 59.4 | D79: 0.2 | E79: =IF(ISERROR(B79-C79),"FAIL",IF(ABS(B79-C79)<=D79,"PASS","FAIL")) | F79: INFERRED, not confirmed
A80: Mgmt Guide FY2026E company-defined Adjusted FCF = $878M (snapshot, back-solved) | B80: =Valuation!E94 | C80: 878 | D80: 1 | E80: =IF(ISERROR(B80-C80),"FAIL",IF(ABS(B80-C80)<=D80,"PASS","FAIL")) | F80: KEY #2 conversion back-solved to the guide
A81: 6. EPS bridge back-test on actual quarters (driver-based vs reported)
A82: Q1'26 predicted EPS vs reported 1.29 (within $0.10) | B82: =Quarterly!B92 | C82: =Quarterly!B93 | D82: 0.1 | E82: =IF(ISERROR(B82-C82),"FAIL",IF(ABS(B82-C82)<=D82,"PASS","FAIL"))
A83: Q2'26 predicted EPS vs reported 1.13 (within $0.10) | B83: =Quarterly!C92 | C83: =Quarterly!C93 | D83: 0.1 | E83: =IF(ISERROR(B83-C83),"FAIL",IF(ABS(B83-C83)<=D83,"PASS","FAIL"))
A84: 1H26 predicted EPS vs reported (within $0.05) | B84: =Quarterly!B92+Quarterly!C92 | C84: =Quarterly!B93+Quarterly!C93 | D84: 0.05 | E84: =IF(ISERROR(B84-C84),"FAIL",IF(ABS(B84-C84)<=D84,"PASS","FAIL"))
A85: 7. Leasing book guards and error scan
A86: Leasing book never negative, Bear (min of book end rows, floor 0) | B86: =MAX(0,-MIN(Drivers!D235:I235)) | C86: 0 | D86: 0.001 | E86: =IF(ISERROR(B86-C86),"FAIL",IF(ABS(B86-C86)<=D86,"PASS","FAIL"))
A87: Leasing book never negative, Base (min of book end rows, floor 0) | B87: =MAX(0,-MIN(Drivers!D241:I241)) | C87: 0 | D87: 0.001 | E87: =IF(ISERROR(B87-C87),"FAIL",IF(ABS(B87-C87)<=D87,"PASS","FAIL"))
A88: Leasing book never negative, Bull (min of book end rows, floor 0) | B88: =MAX(0,-MIN(Drivers!D247:I247)) | C88: 0 | D88: 0.001 | E88: =IF(ISERROR(B88-C88),"FAIL",IF(ABS(B88-C88)<=D88,"PASS","FAIL"))
A89: Leasing book never negative, Mgmt Guide (min of book end rows, floor 0) | B89: =MAX(0,-MIN(Drivers!D253:I253)) | C89: 0 | D89: 0.001 | E89: =IF(ISERROR(B89-C89),"FAIL",IF(ABS(B89-C89)<=D89,"PASS","FAIL"))
A90: Book sold <= beginning book in every selected-scenario quarter (count of violations) | B90: =SUMPRODUCT(--(Quarterly!D22:I22>Quarterly!D21:I21)) | C90: 0 | D90: 0.001 | E90: =IF(ISERROR(B90-C90),"FAIL",IF(ABS(B90-C90)<=D90,"PASS","FAIL"))
A91: Annual: leasing book end >= 0 FY28-30 (min) | B91: =MAX(0,-MIN(Annual!G25:I25)) | C91: 0 | D91: 0.001 | E91: =IF(ISERROR(B91-C91),"FAIL",IF(ABS(B91-C91)<=D91,"PASS","FAIL"))
A92: Error cells in Quarterly (count) | B92: =SUMPRODUCT(--ISERROR(Quarterly!B5:K94)) | C92: 0 | D92: 0.001 | E92: =IF(ISERROR(B92-C92),"FAIL",IF(ABS(B92-C92)<=D92,"PASS","FAIL"))
A93: Error cells in Annual (count) | B93: =SUMPRODUCT(--ISERROR(Annual!B5:I88)) | C93: 0 | D93: 0.001 | E93: =IF(ISERROR(B93-C93),"FAIL",IF(ABS(B93-C93)<=D93,"PASS","FAIL"))
A94: Error cells in Valuation (count) | B94: =SUMPRODUCT(--ISERROR(Valuation!B4:F101)) | C94: 0 | D94: 0.001 | E94: =IF(ISERROR(B94-C94),"FAIL",IF(ABS(B94-C94)<=D94,"PASS","FAIL"))
A95: Probability weights sum to 100% | B95: =Valuation!F97 | C95: 1 | D95: 0.0001 | E95: =IF(ISERROR(B95-C95),"FAIL",IF(ABS(B95-C95)<=D95,"PASS","FAIL"))
A96: Blend weights sum to 100% | B96: =Drivers!$D$218+Drivers!$D$219+Drivers!$D$220 | C96: 1 | D96: 0.0001 | E96: =IF(ISERROR(B96-C96),"FAIL",IF(ABS(B96-C96)<=D96,"PASS","FAIL"))
A97: Revolver never drawn above 0 in selected scenario (info) | B97: =MAX(Quarterly!D83:I83,Annual!G83:I83) | C97: 0 | D97: 0.001 | E97: =IF(ISERROR(B97-C97),"FAIL",IF(ABS(B97-C97)<=D97,"PASS","FAIL")) | F97: Cash stays above the minimum balance
A99: SUMMARY: checks passed | B99: =COUNTIF(E5:E97,"PASS")
A100: SUMMARY: checks failed | B100: =COUNTIF(E5:E97,"FAIL")

Sheet Sources
A1: Sources, inferred / unverified items, and method note
A2: Every typed input in Historical and Drivers carries a source or rationale in its row. Dates are retrieval or filing dates.
A4: Source | B4: URL / accession | C4: Date | D4: Used for
A5: SEC EDGAR, FTAI Aviation Ltd. (CIK 1590364): Q2-26 10-Q | B5: acc 0001628280-26-051412; https://www.sec.gov/Archives/edgar/data/1590364/000162828026051412/ftai-20260630.htm | C5: Period ended 2026-06-30; pulled 2026-10-06 | D5: Segment, IS, BS, CF, debt note, related party
A6: Q2-26 earnings release (8-K Ex99.1) | B6: acc 0001628280-26-050622; https://www.sec.gov/Archives/edgar/data/1590364/000162828026050622/ftai6302026earningsrelease.htm | C6: 2026-07-29 | D6: 2026/2027 guidance (1,525 / 2,300; Leasing cut to 475), Adj. EBITDA definition
A7: Q1-26 earnings release (8-K Ex99.1) | B7: acc 0001628280-26-028390 | C7: 2026-04-29 | D7: Q1-26 results, Jereh JV bullet, 100-unit Power target
A8: Q4-25 earnings release (8-K Ex99.1) | B8: acc 0001628280-26-011685 | C8: 2026-02-25 | D8: 2026 guide 1,625 (Aero 1,050 + Leasing 575)
A9: Q3-25 earnings release (8-K Ex99.1) | B9: acc 0001590364-25-000038 | C9: 2025-10-29 | D9: 2026 guide 1,525
A10: Q4-24 earnings release (8-K Ex99.1) | B10: acc 0001140361-25-006099 | C10: 2025-02-26 | D10: 2025 FCF target 650, module assumption
A11: 10-Qs 2023-2025, 10-K FY23/FY24/FY25 (segment notes, cash flow statements, balance sheets) | B11: acc 0001590364-24-000011 (Q1-24), 0001590364-24-000016 (Q2-24), 0001590364-23-000013 (Q1-23), others per phase2/data CSV source columns | C11: 2023-2026 | D11: Historical tab
A12: Q4-25 earnings call transcript (Motley Fool) | B12: https://www.fool.com/earnings/call-transcripts/2026/02/26/ftai-ftai-q4-2025-earnings-call-transcript/ | C12: 2026-02-26 | D12: FY25 Adjusted FCF 724, three named investments (52 / 150 / 50), Power margin comment (secondary)
A13: Q2-26 earnings call transcript (Investing.com) | B13: investing.com transcript | C13: 2026-07-30 | D13: FY26 FCF guide 878 (from 915), 1,200 modules 2026, 1,700 modules 2027, Power range 450-750, Leasing components 5 / 48 / 35 (secondary)
A14: stockanalysis.com /forecast and /statistics | B14: https://stockanalysis.com/stocks/ftai/statistics/ ; https://stockanalysis.com/stocks/ftai/forecast/ | C14: 2026-10-06 | D14: Price 179.44, market cap, EV, shares, peer multiples, forward P/E, FY26 EPS 5.83
A15: MarketBeat itemised price targets | B15: https://www.marketbeat.com/stocks/NASDAQ/FTAI/price-target/ | C15: 2026-10-06 | D15: Seven dated post-June PTs, mean 330 / median 325
... A18: Team research files | B18: research/FTAI/thesis.md; phase2/A_2027_guide.md; phase2/A_2027_guide_segment_build.csv; phase2/B_data_notes.md; phase2/data/*.csv | C18: 2026-10-06 | D18: Scenario builds, thesis, peer multiples, data notes
A20: Inferred, unverified or assumed items (blue inputs with rationale on the Drivers tab)
A21: INFERRED: FY25 Adjusted FCF residual of ~$59M (probably $49.1M acquisitions + ~$10M JV item). Not confirmed.
A22: UNVERIFIED: Power EBITDA per unit $7.5M and revenue per unit ~$25M (secondary reports); J&F ownership split and FTAI's accounting for Power economics.
A23: UNVERIFIED: $500M buyback (model toggle default OFF). UNVERIFIED: 2027 module target of 1,700 (truncated transcript read).
A24: SECONDARY: module counts (Q4-25 228, Q2-26 296) and Q1-25 (~138) back-solved. Q1-26 modules are an ESTIMATE (EBITDA / 0.84).
A25: ASSUMED (not in provided data): common dividend $0.30/quarter; SCI AUM path and ~6,000 starting AUM; fee rate derived from $7.0M servicing fees; revolver rate 6%, refinancing coupon 7%, minimum cash $300M.
A26: ASSUMED: Power cash conversion 75% and EBITDA-to-pretax conversion 75% (invented); pro-rata SCI EBITDA Q1-26 equal to Q2-26 (28.0); other pre-tax adjustments calibrated on 1H26.
A27: ASSUMED: leasing yield 8.5%, gain on sale 15%, seed share 30%, book sold paths, FY28-30 growth, margin cap/elasticity, inventory target days 150, tax rate 18%, DCF WACC 10% and terminal growth 3%, blend weights 40/30/30.
A28: CAVEAT: consensus FY27 EPS of ~$8.87 is implied from stockanalysis's 20.2x forward P/E, which conflicts with its own FY26 EPS (30.8x). Use as an indication only.
A29: NOT DISCLOSED: gains by segment (company-level only), SCI fee/promote terms, Q3-25 and Q1-26 module counts.
A30: Q4 flows in Historical are derived as FY less 9M; quarters therefore sum to FY by construction.
A32: Method note: this model was built with GenAI assistance (Claude, Anthropic) from a blank workbook via a reproducible Python/openpyxl script (build_model.py) and verified against filings and the team's sourced data files; no external or outside-research models were used or copied.
